Workbook

Sheet Funnel
A1: Factory Shadow – TAM / SAM / SOM (v2)
A2: AI production-disruption decision engine: spots machines drifting to failure and recommends the cheapest response that keeps orders on time.
A5: Layer | B5: Who it covers | C5: Plants | D5: Price / plant (₹ L) | E5: Market (₹ Cr) | F5: Calculation
A6: TAM | B6: All factories in our 7 target industries in India | C6: =Inputs!$C$6 -> 63728 | D6: =IFERROR(E6/C6*100,0) -> 21.359214 | E6: =(Inputs!$C$27*Inputs!$C$10+Inputs!$C$7*Inputs!$C$28)/100 -> 13611.8 | F6: Smaller plants × Starter price + SAM plants × SAM price
A7: SAM | B7: Machine-intensive plants with 100+ workers, where disruption decisions are costly | C7: =Inputs!$C$7 -> 20263 | D7: =Inputs!$C$28 -> 35 | E7: =C7*D7/100 -> 7092.05 | F7: SAM plants × Professional/Enterprise mix price
A8: Launch market | B8: SAM plants in MH, GJ, TN, KA, UP (go-to-market focus, not a funnel layer) | C8: =ROUND(C7*Inputs!$C$8,0) -> 10800 | D8: =D7 -> 35 | E8: =C8*D8/100 -> 3780 | F8: SAM × five-state share
A9: SOM | B9: Live paying plants at Year-5 (FY31) exit | C9: =Inputs!$C$20 -> 600 | D9: =Inputs!$C$29 -> 29.5 | E9: =C9*D9/100 -> 177 | F9: Target plants × our tier mix price (see SOM Build)
A11: Market share | B11: Measure | C11: Value
A12: SOM ÷ SAM (plants) | B12: Year-5 share of serviceable plants | C12: =IFERROR(C9/C7,0) -> 0.02961062
A13: SOM ÷ SAM (₹) | B13: Year-5 share of serviceable value | C13: =IFERROR(E9/E7,0) -> 0.024957523
A14: SOM ÷ launch market | B14: Share of five-state plants | C14: =IFERROR(C9/C8,0) -> 0.055555556
A15: SOM ÷ TAM (plants) | B15: Share of all target-industry factories | C15: =IFERROR(C9/C6,0) -> 0.0094150138
A16: SAM ÷ TAM (₹) | B16: Serviceable share of total value | C16: =IFERROR(E7/E6,0) -> 0.5210222
A18: SOM tier mix | B18: Tier | C18: Plants | D18: Price (₹ L) | E18: ARR (₹ Cr)
B19: Starter | C19: =C$9*Inputs!$C$16 -> 180 | D19: =Inputs!$C$10 -> 15 | E19: =C19*D19/100 -> 27
B20: Professional | C20: =C$9*Inputs!$C$17 -> 300 | D20: =Inputs!$C$11 -> 30 | E20: =C20*D20/100 -> 90
B21: Enterprise | C21: =C$9*Inputs!$C$18 -> 120 | D21: =Inputs!$C$12 -> 50 | E21: =C21*D21/100 -> 60
B22: Total | C22: =SUM(C19:C21) -> 600 | D22: =IFERROR(E22/C22*100,0) -> 29.5 | E22: =SUM(E19:E21) -> 177
A24: Pitch line: | B24: ="A ₹"&TEXT(E6,"#,##0")&" Cr market; ₹"&TEXT(E7,"#,##0")&" Cr serviceable in machine-intensive plants; we target ₹"&TEXT(E9,"#,##0")&" Cr ARR from "&TEXT(C9,"#,##0")&" live plants by FY31 – "&TEXT(C12,"0.0%")&" of serviceable plants." -> A ₹13,612 Cr market; ₹7,092 Cr serviceable in machine-intensive plants; we target ₹177 Cr ARR from 600 live plants by FY31 – 3.0% of serviceable plants.

Sheet Inputs
A1: Factory Shadow – Market Sizing Inputs (v2: 600 plants, tiered premium pricing)
A2: Blue = input you can change · Yellow = key assumption to validate · Black = formula. Edit only column C.
A4: # | B4: Input | C4: Value | D4: Unit | E4: Source / basis
B5: MARKET (plant counts)
A6: 1 | B6: Factories in our 7 target industries, all sizes | C6: 63728 | D6: plants | E6: ASI 2023-24 (MoSPI), per team research – cite exact table on appendix
A7: 2 | B7: Of which: machine-intensive plants with 100+ workers | C7: 20263 | D7: plants | E7: Team model – re-pull from ASI (7 industries × 100+ workers) so it is a strict subset
A8: 3 | B8: Five priority states' share (MH, GJ, TN, KA, UP) | C8: 0.533 | D8: % | E8: ASI FY2024-25 establishment share – proxy, not sector-specific
B9: TIER PRICES (subscription, per plant per year)
A10: 4 | B10: Starter – Disruption Intelligence (one production area) | C10: 15 | D10: ₹ lakh | E10: Midpoint of ₹12–18 L band; hypothesis to validate
A11: 5 | B11: Professional – Production Recovery (multi-line) | C11: 30 | D11: ₹ lakh | E11: Midpoint of ₹24–36 L band; hypothesis to validate
A12: 6 | B12: Enterprise – Plant Optimisation (plant-wide) | C12: 50 | D12: ₹ lakh | E12: Midpoint of ₹40–60 L+ band; hypothesis to validate
B13: MARKET PRICE MIX (used for TAM / SAM)
A14: 7 | B14: SAM plants on Professional | C14: 0.75 | D14: % | E14: Assumption – remainder on Enterprise
B15: OUR CUSTOMER MIX (used for SOM)
A16: 8 | B16: Customers on Starter (incl. land-and-expand) | C16: 0.3 | D16: % | E16: Team plan: 180 of 600
A17: 9 | B17: Customers on Professional | C17: 0.5 | D17: % | E17: Team plan: 300 of 600
A18: 10 | B18: Customers on Enterprise | C18: 0.2 | D18: % | E18: Team plan: 120 of 600
B19: SOM / GO-TO-MARKET
A20: 11 | B20: Live-plant target at Year-5 (FY31) exit | C20: 600 | D20: plants | E20: Team target
A21: 12 | B21: Annual customer churn | C21: 0.1 | D21: % | E21: Assumption
A22: 13 | B22: Paid pilot → annual contract conversion | C22: 0.65 | D22: % | E22: Team plan assumption – unvalidated
A23: 14 | B23: Factory audit → paid pilot conversion | C23: 0.45 | D23: % | E23: Team plan assumption – unvalidated
A24: 15 | B24: Minimum customer ROI for price to hold | C24: 3 | D24: x | E24: Rule of thumb for B2B industrial software
B26: DERIVED (formulas)
A27: 16 | B27: Target-industry plants below SAM (smaller plants) | C27: =$C$6-$C$7 -> 43465 | D27: plants | E27: TAM plants − SAM plants
A28: 17 | B28: SAM price per plant (Professional/Enterprise mix) | C28: =$C$11*$C$14+$C$12*(1-$C$14) -> 35 | D28: ₹ lakh | E28: Used for SAM
A29: 18 | B29: Our weighted price per plant (SOM mix) | C29: =$C$10*$C$16+$C$11*$C$17+$C$12*$C$18 -> 29.5 | D29: ₹ lakh | E29: Used for SOM
A30: 19 | B30: Check: SOM mix adds to 100% | C30: =$C$16+$C$17+$C$18 -> 1 | D30: % | E30: Must be 100%
A31: 20 | B31: Verified savings each plant needs (at minimum ROI) | C31: =$C$29*$C$24 -> 88.5 | D31: ₹ lakh | E31: Weighted price × minimum ROI – prove this in pilots
B33: Gain-share, implementation, hardware and pilot fees are excluded from all figures (upside / one-time).

Sheet SOM Build
A1: SOM – bottom-up build to 600+ live plants (FY31 exit)
A2: Blue row = new plants won each year (input). Everything else is calculated.
A4: Metric | B4: FY27 | C4: FY28 | D4: FY29 | E4: FY30 | F4: FY31
A5: New plants won (gross) | B5: 15 | C5: 55 | D5: 120 | E5: 200 | F5: 300
A6: Live plants – opening | B6: 0 | C6: =B8 -> 15 | D6: =C8 -> 68.5 | E6: =D8 -> 181.65 | F6: =E8 -> 363.485
A7: Plants churned | B7: =B6*Inputs!$C$21 -> 0 | C7: =C6*Inputs!$C$21 -> 1.5 | D7: =D6*Inputs!$C$21 -> 6.85 | E7: =E6*Inputs!$C$21 -> 18.165 | F7: =F6*Inputs!$C$21 -> 36.3485
A8: Live plants – closing | B8: =B6-B7+B5 -> 15 | C8: =C6-C7+C5 -> 68.5 | D8: =D6-D7+D5 -> 181.65 | E8: =E6-E7+E5 -> 363.485 | F8: =F6-F7+F5 -> 627.1365
A9: Cumulative plants won | B9: =B5 -> 15 | C9: =B9+C5 -> 70 | D9: =C9+D5 -> 190 | E9: =D9+E5 -> 390 | F9: =E9+F5 -> 690
A10: Paid pilots needed | B10: =ROUNDUP(B5/Inputs!$C$22,0) -> 24 | C10: =ROUNDUP(C5/Inputs!$C$22,0) -> 85 | D10: =ROUNDUP(D5/Inputs!$C$22,0) -> 185 | E10: =ROUNDUP(E5/Inputs!$C$22,0) -> 308 | F10: =ROUNDUP(F5/Inputs!$C$22,0) -> 462
A11: Factory audits needed | B11: =ROUNDUP(B10/Inputs!$C$23,0) -> 54 | C11: =ROUNDUP(C10/Inputs!$C$23,0) -> 189 | D11: =ROUNDUP(D10/Inputs!$C$23,0) -> 412 | E11: =ROUNDUP(E10/Inputs!$C$23,0) -> 685 | F11: =ROUNDUP(F10/Inputs!$C$23,0) -> 1027
A12: New plants per month | B12: =B5/12 -> 1.25 | C12: =C5/12 -> 4.5833333 | D12: =D5/12 -> 10 | E12: =E5/12 -> 16.666667 | F12: =F5/12 -> 25
A13: Exit ARR (₹ Cr) | B13: =B8*Inputs!$C$29/100 -> 4.425 | C13: =C8*Inputs!$C$29/100 -> 20.2075 | D13: =D8*Inputs!$C$29/100 -> 53.58675 | E13: =E8*Inputs!$C$29/100 -> 107.22808 | F13: =F8*Inputs!$C$29/100 -> 185.00527
A14: Recognised revenue (₹ Cr) | B14: =(B6+B8)/2*Inputs!$C$29/100 -> 2.2125 | C14: =(C6+C8)/2*Inputs!$C$29/100 -> 12.31625 | D14: =(D6+D8)/2*Inputs!$C$29/100 -> 36.897125 | E14: =(E6+E8)/2*Inputs!$C$29/100 -> 80.407413 | F14: =(F6+F8)/2*Inputs!$C$29/100 -> 146.11667
A15: Share of SAM (plants) | B15: =B8/Funnel!$C$7 -> 0.00074026551 | C15: =C8/Funnel!$C$7 -> 0.0033805458 | D15: =D8/Funnel!$C$7 -> 0.0089646153 | E15: =E8/Funnel!$C$7 -> 0.017938361 | F15: =F8/Funnel!$C$7 -> 0.030949835
A16: Share of launch market (plants) | B16: =B8/Funnel!$C$8 -> 0.0013888889 | C16: =C8/Funnel!$C$8 -> 0.0063425926 | D16: =D8/Funnel!$C$8 -> 0.016819444 | E16: =E8/Funnel!$C$8 -> 0.033656019 | F16: =F8/Funnel!$C$8 -> 0.058068194
A18: Check: plan reaches target? | B18: =IF(F8>=Inputs!$C$20,"Yes – "&TEXT(F8-Inputs!$C$20,"0")&" plants of cushion","No – short by "&TEXT(Inputs!$C$20-F8,"0")) -> Yes – 27 plants of cushion
A20: Churn is applied to opening plants. Recognised revenue = average live plants × weighted price (even onboarding through the year).
A21: SOM headline uses exit ARR at the 600-plant target; FY31 recognised revenue is the P&L figure.

Sheet Sensitivity
A1: Sensitivity – low / base / high
A3: Driver | B3: Low | C3: Base | D3: High
A4: SAM plants (7 industries, 100+ workers) | B4: 16000 | C4: =Inputs!$C$7 -> 20263 | D4: 24000
A5: Starter price (₹ L) | B5: 12 | C5: =Inputs!$C$10 -> 15 | D5: 18
A6: SAM price per plant (₹ L) | B6: 27 | C6: =Inputs!$C$28 -> 35 | D6: 45
A7: SOM live plants (FY31) | B7: 400 | C7: =Inputs!$C$20 -> 600 | D7: 700
A8: Our weighted price (₹ L) | B8: 20 | C8: =Inputs!$C$29 -> 29.5 | D8: 35
A10: Output | B10: Low | C10: Base | D10: High
A11: TAM (₹ Cr) | B11: =((Inputs!$C$6)-B4)*B5/100+B4*B6/100 -> 10047.36 | C11: =((Inputs!$C$6)-C4)*C5/100+C4*C6/100 -> 13611.8 | D11: =((Inputs!$C$6)-D4)*D5/100+D4*D6/100 -> 17951.04
A12: SAM (₹ Cr) | B12: =B4*B6/100 -> 4320 | C12: =C4*C6/100 -> 7092.05 | D12: =D4*D6/100 -> 10800
A13: SOM ARR (₹ Cr) | B13: =B7*B8/100 -> 80 | C13: =C7*C8/100 -> 177 | D13: =D7*D8/100 -> 245
A14: SOM ÷ SAM (plants) | B14: =IFERROR(B7/B4,0) -> 0.025 | C14: =IFERROR(C7/C4,0) -> 0.02961062 | D14: =IFERROR(D7/D4,0) -> 0.029166667
A16: Low/high ranges are placeholders; tighten once ASI counts and pilot pricing are confirmed.

Sheet Competitor Pricing
A1: Competitor pricing reference (from team research – re-check links before citing)
A3: Vendor | B3: Category | C3: Published price | D3: Approx. annual (₹ L) | E3: Comparable to us?
A4: Infinite Uptime – PlantOS | B4: Prescriptive asset-reliability AI | C4: Custom quote | E4: Closest strategic benchmark; reliability-led, not production re-planning
A5: Sight Machine | B5: Agentic manufacturing platform | C5: US$5,000/month (AWS Marketplace, 1-month option) | D5: 50 | E5: List price, not negotiated annual contract; ~US$60k/yr
A6: Augury | B6: Machine health / predictive maintenance | C6: Per machine per year, quote-based | E6: Priced per machine; plant cost scales with machine count
A7: Tulip | B7: Operations app platform | C7: US$100–250 per interface/month, min 10 | E7: ~US$12k–30k/yr at 10 interfaces; not a decision engine
A8: Fiix | B8: CMMS (maintenance workflow) | C8: US$45–75 per user/month | E8: Workflow tool, cheaper category
A9: Proqura | B9: Factory management SaaS (India) | C9: ₹12,000–30,000/month billed yearly | D9: 3.6 | E9: ₹1.44–3.6 L/yr; basic scope, not comparable
A11: Positioning: we price on value delivered (verified savings), not on matching the cheapest factory software.

Sheet Sources & To-Do
A1: Sources and validation checklist
A3: Item | B3: Status | C3: Action before pitch
A4: 63,728 factories in 7 industries | B4: Sourced (team) | C4: Cite the exact ASI 2023-24 table and NIC codes on the appendix slide.
A5: 20,263 SAM plants | B5: Model estimate | C5: Earlier count used 9 segments; re-pull ASI for the same 7 industries × 100+ workers.
A6: Tier prices ₹15 / 30 / 50 L | B6: Hypothesis | C6: Test in 10+ plant-leader interviews; get at least 2–3 paid pilots at these levels.
A7: Weighted price ₹29.5 L → needs ~₹89 L savings/plant | B7: Assumption | C7: Measure baseline disruption losses in pilots; keep ROI ≥3x.
A8: 600 live plants FY31 | B8: Team target | C8: Update the financial model (still 120) and hiring plan so all slides agree.
A9: Year-5: 300 new plants (25/month) | B9: Stretch | C9: Show partner channel (OEMs, system integrators) and multi-plant groups as the route.
A10: Pilot 65% / audit 45% conversion, 10% churn | B10: Assumption | C10: Track from first cohort; update SOM Build.
