Workbook

Sheet Cover
A1: AI PLANT OPERATIONS OPTIMISER: INTEGRATED FINANCIAL MODEL, FY2027-FY2031
A2: Prepared 10-Oct-2026 for the IIM Kozhikode team; revised 10-Oct-2026 for financial viability (see 15_Change_Log). Proposed product; nothing here is commercially validated.
A4: How to use | B4: Change blue cells on 'Inputs' (and scenario prices on '3_Pricing'). Switch scenario with Inputs!C3 (1 Bear, 2 Base, 3 Bull). Everything else is formula-driven.
A6: Units | B6: ₹ lakh unless stated (₹1 crore = ₹100 lakh). Customer counts are expected values, so they can be fractional.
A8: Colour code | B8: Blue text, cream fill = input. Black = formula. Green = link from another sheet. Green fill = key output. Yellow = scenario switch / master check.
A10: Data status tags | B10: Inputs column G: 'Verified fact' (official or published source), 'Assumption' (management judgement), 'Validate' (must be tested with customers before the pitch).
A12: Engine | B12: 'Engine_Monthly' runs all 60 months (Apr-2026 to Mar-2031): funnel → pilots → contracts → implementation capacity → go-live → ARR → costs → P&L → cash → balance sheet. Annual sheets aggregate it.
A14: Timing note | B14: FY27 starts Apr-2026 as requested; six months have already elapsed. Move Inputs 'Model start date' to re-base.
A16: Snapshots | B16: '12_Scenarios' bear/base/bull and sensitivity tables, the NPV bridge on '15_Change_Log' and the FY27-FY31 scenario rows in 14_Valuation section F are values from full re-runs of this model. If you change engine inputs, re-run each case and read the LIVE column.
A18: Sheet map | B18: 1 Dashboard · Inputs · 2 Market · 3 Pricing · 4 Revenue build · 5 Cost of service · 6 Personnel & opex · 7 Financial statements · 8 Unit economics · 9 Customer ROI · 10 GTM · 11 Funding · 12 Scenarios · 13 Risks & checks · 14 Valuation · 15 Change log · Engine · Sources
A20: Revision | B20: Valuation: 14_Valuation (base DCF at the team's 12% WACC with a steady-state terminal value, probability-weighted scenarios, comparable-company cross-check, equity bridge). What changed versus the model as received, and the NPV bridge: 15_Change_Log.
A22: v4 update | B22: v4 (11-Oct-2026): TAM = 63,728 operating factories in 7 industries (ASI 2023-24); SAM via size, state and readiness filters; Year-5 live plants solved to 200 / 400 / 600; tiered pricing ₹12-60 lakh; gain-share on its own line. Bear / base / bull comparison and flags: 16_SOM_Scenarios. Changes: 15_Change_Log section F.

Sheet 1_Dashboard
A1: 1. EXECUTIVE DASHBOARD: AI PLANT OPERATIONS OPTIMISER (₹ lakh unless stated)
A3: Active scenario | C3: =Inputs!D3 -> BASE | E3: Model checks | F3: =IF(13_Risks_Checks!$B$22,"ALL PASS","CHECK 13_Risks_Checks") -> ALL PASS
A5: HEADLINES
A6: FY31 revenue | B6: ₹ crore | C6: =7_Financials!$G$11/100 -> 150.92972
A7: FY31 closing ARR | B7: ₹ crore | C7: =4_Revenue_Build!G30/100 -> 157.45778
A8: ="Live paying plants, end FY31 (target "&TEXT(Inputs!C151,"0")&")" -> Live paying plants, end FY31 (target 400) | B8: # | C8: =4_Revenue_Build!G21 -> 400.00001
A9: EBITDA break-even (first month trailing-3-month EBITDA > 0) | B9: month | C9: =IF(COUNT(Engine_Monthly!$D$176:$BK$176)=0,"Not within 5 years",TEXT(INDEX(Engine_Monthly!$D$9:$BK$9,1,MIN(Engine_Monthly!$D$176:$BK$176)),"mmm-yy")&" ("&INDEX(Engine_Monthly!$D$10:$BK$10,1,MIN(Engine_Monthly!$D$176:$BK$176))&")") -> Aug-28 (FY29)
A10: Peak cumulative cash deficit | B10: ₹ crore | C10: =11_Funding!C5/100 -> 6.9294953
A11: Total equity requirement incl. buffer & contingency | B11: ₹ crore | C11: =11_Funding!C11/100 -> 11.029115
A12: Seed requirement (to Series A) | B12: ₹ crore | C12: =11_Funding!C15/100 -> 9.7157586
A13: Live plants needed to cover FY31 cost base | B13: # | C13: =8_Unit_Economics!G33 -> 62.889947
A14: Customer value: gross benefit ÷ Professional price (Low / Base / High) | B14: x | C14: =TEXT(9_Customer_ROI!C52,"0.0")&"x / "&TEXT(9_Customer_ROI!D52,"0.0")&"x / "&TEXT(9_Customer_ROI!E52,"0.0")&"x" -> 0.7x / 3.9x / 12.6x
A15: Enterprise value @ 12%: base DCF (₹ crore; see 14_Valuation) | B15: ₹ crore | C15: =14_Valuation!C75 -> 367.69834
A16: Probability-weighted EV / comps range (EV/ARR) / base DCF at 20% (₹ crore) | B16: ₹ crore | C16: =TEXT(14_Valuation!F195,"0.0")&" / "&TEXT(14_Valuation!C225,"0.0")&"-"&TEXT(14_Valuation!E225,"0.0")&" / "&TEXT(14_Valuation!C86,"0.0") -> 503.1 / 315.5-672.9 / 161.4
A17: ANNUAL KPIs
A18: KPI | B18: Unit | C18: =INDEX(Engine_Monthly!$D$10:$BK$10,1,12) -> FY27 | D18: =INDEX(Engine_Monthly!$D$10:$BK$10,1,24) -> FY28 | E18: =INDEX(Engine_Monthly!$D$10:$BK$10,1,36) -> FY29 | F18: =INDEX(Engine_Monthly!$D$10:$BK$10,1,48) -> FY30 | G18: =INDEX(Engine_Monthly!$D$10:$BK$10,1,60) -> FY31
A19: Revenue | B19: ₹ lakh | C19: =7_Financials!C11 -> 28.637625 | D19: =7_Financials!D11 -> 478.84504 | E19: =7_Financials!E11 -> 2411.1478 | F19: =7_Financials!F11 -> 7026.3162 | G19: =7_Financials!G11 -> 15092.972
A20: Revenue growth | B20: % | C20: =7_Financials!C12 -> 0 | D20: =7_Financials!D12 -> 15.720836 | E20: =7_Financials!E12 -> 4.0353405 | F20: =7_Financials!F12 -> 1.914096 | G20: =7_Financials!G12 -> 1.1480633
A21: Closing ARR | B21: ₹ lakh | C21: =4_Revenue_Build!C30 -> 30.996799 | D21: =4_Revenue_Build!D30 -> 552.94498 | E21: =4_Revenue_Build!E30 -> 2619.6435 | F21: =4_Revenue_Build!F30 -> 7429.6244 | G21: =4_Revenue_Build!G30 -> 15745.778
A22: Closing MRR | B22: ₹ lakh | C22: =4_Revenue_Build!C32 -> 2.5830666 | D22: =4_Revenue_Build!D32 -> 46.078748 | E22: =4_Revenue_Build!E32 -> 218.30362 | F22: =4_Revenue_Build!F32 -> 619.13536 | G22: =4_Revenue_Build!G32 -> 1312.1482
A23: New paying customers (contracts) | B23: # | C23: =4_Revenue_Build!C13 -> 1.98 | D23: =4_Revenue_Build!D13 -> 23.57939 | E23: =4_Revenue_Build!E13 -> 75.260059 | F23: =4_Revenue_Build!F13 -> 152.50012 | G23: =4_Revenue_Build!G13 -> 237.16518
A24: Live paying plants (year end) | B24: # | C24: =4_Revenue_Build!C21 -> 1.0609353 | D24: =4_Revenue_Build!D21 -> 17.598591 | E24: =4_Revenue_Build!E21 -> 77.249595 | F24: =4_Revenue_Build!F21 -> 203.40003 | G24: =4_Revenue_Build!G21 -> 400.00001
A25: Active pilots at year end (not customers) | B25: # | C25: =4_Revenue_Build!C12 -> 3.6 | D25: =4_Revenue_Build!D12 -> 20.985809 | E25: =4_Revenue_Build!E12 -> 54.182426 | F25: =4_Revenue_Build!F12 -> 93.454044 | G25: =4_Revenue_Build!G12 -> 130.02566
A26: Gross margin | B26: % | C26: =7_Financials!C15 -> -0.57596702 | D26: =7_Financials!D15 -> 0.45347733 | E26: =7_Financials!E15 -> 0.65539399 | F26: =7_Financials!F15 -> 0.74060472 | G26: =7_Financials!G15 -> 0.79356308
A27: SaaS gross margin | B27: % | C27: =5_Cost_of_Service!C17 -> -3.9482785 | D27: =5_Cost_of_Service!D17 -> 0.59280881 | E27: =5_Cost_of_Service!E17 -> 0.84371307 | F27: =5_Cost_of_Service!F17 -> 0.89154548 | G27: =5_Cost_of_Service!G17 -> 0.91268428
A28: EBITDA | B28: ₹ lakh | C28: =7_Financials!C19 -> -203.33499 | D28: =7_Financials!D19 -> -349.49934 | E28: =7_Financials!E19 -> 354.79406 | F28: =7_Financials!F19 -> 3061.3425 | G28: =7_Financials!G19 -> 8786.0955
A29: EBITDA margin | B29: % | C29: =7_Financials!C20 -> -7.1002744 | D29: =7_Financials!D20 -> -0.72987986 | E29: =7_Financials!E20 -> 0.14714737 | F29: =7_Financials!F20 -> 0.43569666 | G29: =7_Financials!G20 -> 0.58213157
A30: Cash burn (operating + investing outflow) | B30: ₹ lakh | C30: =SUMIF(Engine_Monthly!$D$7:$BK$7,1,Engine_Monthly!$D$167:$BK$167) -> 223.80611 | D30: =SUMIF(Engine_Monthly!$D$7:$BK$7,2,Engine_Monthly!$D$167:$BK$167) -> 394.90198 | E30: =SUMIF(Engine_Monthly!$D$7:$BK$7,3,Engine_Monthly!$D$167:$BK$167) -> 74.241433 | F30: =SUMIF(Engine_Monthly!$D$7:$BK$7,4,Engine_Monthly!$D$167:$BK$167) -> 0 | G30: =SUMIF(Engine_Monthly!$D$7:$BK$7,5,Engine_Monthly!$D$167:$BK$167) -> 0
A31: Closing cash | B31: ₹ lakh | C31: =7_Financials!C43 -> 676.19389 | D31: =7_Financials!D43 -> 1181.2919 | E31: =7_Financials!E43 -> 1443.5127 | F31: =7_Financials!F43 -> 3674.9102 | G31: =7_Financials!G43 -> 10114.97
A32: CAC, fully loaded (estimate) | B32: ₹ lakh | C32: =8_Unit_Economics!C17 -> n.m. | D32: =8_Unit_Economics!D17 -> 12.999213 | E32: =8_Unit_Economics!E17 -> 10.792681 | F32: =8_Unit_Economics!F17 -> 10.221104 | G32: =8_Unit_Economics!G17 -> 10.058048
A33: LTV (estimate) | B33: ₹ lakh | C33: =8_Unit_Economics!C27 -> n.m. | D33: =8_Unit_Economics!D27 -> 46.240472 | E33: =8_Unit_Economics!E27 -> 76.878186 | F33: =8_Unit_Economics!F27 -> 89.481784 | G33: =8_Unit_Economics!G27 -> 99.817619
A34: LTV / CAC (estimate) | B34: x | C34: =8_Unit_Economics!C28 -> n.m. | D34: =8_Unit_Economics!D28 -> 3.5571747 | E34: =8_Unit_Economics!E28 -> 7.1231781 | F34: =8_Unit_Economics!F28 -> 8.7546108 | G34: =8_Unit_Economics!G28 -> 9.924154
A35: CAC payback (estimate) | B35: months | C35: =8_Unit_Economics!C29 -> n.m. | D35: =8_Unit_Economics!D29 -> 9.4132897 | E35: =8_Unit_Economics!E29 -> 4.8967909 | F35: =8_Unit_Economics!F29 -> 4.0194093 | G35: =8_Unit_Economics!G29 -> 3.5580541
A36: Annual logo churn (assumption) | B36: % | C36: =8_Unit_Economics!C21 -> 0.09 | D36: =8_Unit_Economics!D21 -> 0.09 | E36: =8_Unit_Economics!E21 -> 0.09 | F36: =8_Unit_Economics!F21 -> 0.09 | G36: =8_Unit_Economics!G21 -> 0.09
A37: Average ARR per live plant | B37: ₹ lakh | C37: =8_Unit_Economics!C7 -> 22.969133 | D37: =8_Unit_Economics!D7 -> 27.953889 | E37: =8_Unit_Economics!E7 -> 31.347596 | F37: =8_Unit_Economics!F7 -> 34.227352 | G37: =8_Unit_Economics!G7 -> 37.167371
A38: Headcount (year end) | B38: # | C38: =6_Personnel_Opex!C24 -> 11 | D38: =6_Personnel_Opex!D24 -> 25 | E38: =6_Personnel_Opex!E24 -> 53 | F38: =6_Personnel_Opex!F24 -> 88 | G38: =6_Personnel_Opex!G24 -> 128
A40: SCENARIO COMPARISON (snapshot; live column follows Inputs!C3)
A41: Output | B41: Unit | C41: Bear | D41: Base | E41: Bull | F41: Live
A42: =12_Scenarios!A28 -> FY31 revenue | B42: =12_Scenarios!B28 -> ₹ lakh | C42: =12_Scenarios!C28 -> 4938.4899 | D42: =12_Scenarios!D28 -> 15092.972 | E42: =12_Scenarios!E28 -> 31192.844 | F42: =12_Scenarios!F28 -> 15092.972
A43: =12_Scenarios!A29 -> FY31 closing ARR | B43: =12_Scenarios!B29 -> ₹ lakh | C43: =12_Scenarios!C29 -> 4678.5326 | D43: =12_Scenarios!D29 -> 15745.778 | E43: =12_Scenarios!E29 -> 33677.888 | F43: =12_Scenarios!F29 -> 15745.778
A44: =12_Scenarios!A30 -> FY31 live paying plants | B44: =12_Scenarios!B30 -> # | C44: =12_Scenarios!C30 -> 200 | D44: =12_Scenarios!D30 -> 400.00001 | E44: =12_Scenarios!E30 -> 600.00001 | F44: =12_Scenarios!F30 -> 400.00001
A45: =12_Scenarios!A31 -> FY31 EBITDA | B45: =12_Scenarios!B31 -> ₹ lakh | C45: =12_Scenarios!C31 -> -160.22956 | D45: =12_Scenarios!D31 -> 8786.0955 | E45: =12_Scenarios!E31 -> 23770.269 | F45: =12_Scenarios!F31 -> 8786.0955
A46: =12_Scenarios!A33 -> Cumulative EBITDA FY27-FY31 | B46: =12_Scenarios!B33 -> ₹ lakh | C46: =12_Scenarios!C33 -> -2660.6051 | D46: =12_Scenarios!D33 -> 11649.398 | E46: =12_Scenarios!E33 -> 36128.171 | F46: =12_Scenarios!F33 -> 11649.398
A47: =12_Scenarios!A36 -> Total equity requirement (incl. buffer & contingency) | B47: =12_Scenarios!B36 -> ₹ lakh | C47: =12_Scenarios!C36 -> 4666.7394 | D47: =12_Scenarios!D36 -> 1102.9115 | E47: =12_Scenarios!E36 -> 508.94275 | F47: =12_Scenarios!F36 -> 1102.9115
A48: =12_Scenarios!A37 -> EBITDA break-even month (trailing 3 months > 0) | B48: =12_Scenarios!B37 -> month # | C48: =12_Scenarios!C37 -> 57 | D48: =12_Scenarios!D37 -> 29 | E48: =12_Scenarios!E37 -> 20 | F48: =12_Scenarios!F37 -> 29
A49: =12_Scenarios!A42 -> Enterprise value @ 12% (two-stage DCF, steady-state terminal value) | B49: =12_Scenarios!B42 -> ₹ crore | C49: =12_Scenarios!C42 -> 41.597272 | D49: =12_Scenarios!D42 -> 367.69834 | E49: =12_Scenarios!E42 -> 2140.1683 | F49: =12_Scenarios!F42 -> 367.69834

Sheet Inputs
A1: INPUTS & ASSUMPTIONS REGISTER (all values in ₹ lakh unless stated)
A2: Blue = hardcoded input. Black = formula. Green = link. Column C is what the model uses. Scenario-varied inputs have Bear / Base / Bull values; fixed inputs only a Base value. v4 (11-Oct-2026) inputs are in section K.
A3: ACTIVE SCENARIO (1 = Bear, 2 = Base, 3 = Bull) | C3: 2 | D3: =CHOOSE($C$3,"BEAR","BASE","BULL") -> BASE
A5: Parameter | B5: Unit | C5: ACTIVE | D5: Bear | E5: Base | F5: Bull | G5: Type | H5: Source / rationale | I5: Validation needed
A7: A. GENERAL & MACRO
A8: Model start date (first month of FY27) | B8: date | C8: =IF(D8="",E8,CHOOSE($C$3,D8,E8,F8)) -> 46113 | E8: 46113 | G8: Assumption | H8: FY2027 = Apr-2026 to Mar-2027 as requested. Months 1-6 have already elapsed at 10-Oct-2026; shift this date to re-base the whole model.
A9: USD / INR | B9: ₹ per $ | C9: =IF(D9="",E9,CHOOSE($C$3,D9,E9,F9)) -> 95 | E9: 95 | G9: Verified fact | H9: ~₹95-96 per USD in Aug-Sep 2026 (OFX 5-Aug-2026: 95.03; longforecast 16-Sep-2026: 95.95). Used only to convert $ benchmarks.
A10: Corporate tax rate (concessional 22% regime + 10% surcharge + 4% cess) | B10: % | C10: =IF(D10="",E10,CHOOSE($C$3,D10,E10,F10)) -> 0.25168 | E10: 0.25168 | G10: Verified fact | H10: Sec 200, Income-tax Act 2025 (formerly 115BAA): 22% + 10% surcharge + 4% cess = 25.168%; MAT not applicable. | I10: Confirm with a CA: loss carry-forward (8 yrs), any startup holiday eligibility, GST treatment.
A11: Employer on-cost over CTC (PF, gratuity, insurance) | B11: % of CTC | C11: =IF(D11="",E11,CHOOSE($C$3,D11,E11,F11)) -> 0.12 | E11: 0.12 | G11: Assumption | H11: Typical Indian employer statutory and benefit load; varies by salary structure.
A12: Annual salary increment | B12: % p.a. | C12: =IF(D12="",E12,CHOOSE($C$3,D12,E12,F12)) -> 0.08 | E12: 0.08 | G12: Assumption | H12: Mid-range Indian tech increment assumption.
A13: Non-people cost inflation | B13: % p.a. | C13: =IF(D13="",E13,CHOOSE($C$3,D13,E13,F13)) -> 0.05 | E13: 0.05 | G13: Assumption | H13: Approximates Indian CPI plus vendor price drift.
A14: Discount rate for LTV | B14: % p.a. | C14: =IF(D14="",E14,CHOOSE($C$3,D14,E14,F14)) -> 0.2 | E14: 0.2 | G14: Assumption | H14: Early-stage cost of capital proxy; not a WACC estimate.
A15: Maximum customer life used in LTV | B15: years | C15: =IF(D15="",E15,CHOOSE($C$3,D15,E15,F15)) -> 7 | E15: 7 | G15: Assumption | H15: Caps LTV so low churn cannot imply a near-perpetual customer.
A17: B. SALES CAPACITY & FUNNEL
A18: Month first account executive (AE) joins in FY27 | B18: month of FY | C18: =IF(D18="",E18,CHOOSE($C$3,D18,E18,F18)) -> 4 | E18: 4 | G18: Assumption | H18: Seed closes before sales hiring; founders sell alone until then.
A19: AE ramp to full productivity | B19: months | C19: =IF(D19="",E19,CHOOSE($C$3,D19,E19,F19)) -> 6 | D19: 6 | E19: 6 | F19: 4 | G19: Assumption | H19: Complex industrial B2B sale; new reps need plant/OT credibility.
A20: Founder selling capacity, FY27-FY28 | B20: AE equivalents | C20: =IF(D20="",E20,CHOOSE($C$3,D20,E20,F20)) -> 0.5 | E20: 0.5 | G20: Assumption | H20: Founder-led sales in early stage.
A21: Founder selling capacity, FY29+ | B21: AE equivalents | C21: =IF(D21="",E21,CHOOSE($C$3,D21,E21,F21)) -> 0.25 | E21: 0.25 | G21: Assumption | H21: Founder shifts to enterprise accounts and fundraising.
A22: Qualified opportunities per ramped AE per month | B22: # | C22: =IF(D22="",E22,CHOOSE($C$3,D22,E22,F22)) -> 3 | D22: 2 | E22: 3 | F22: 4 | G22: Validate | H22: No India-specific benchmark found. Qualified = plant visit done, data-readiness confirmed, decision maker engaged. | I22: Track in first 6 months of selling; this is the single largest volume driver.
A23: Lead to qualified opportunity | B23: % | C23: =IF(D23="",E23,CHOOSE($C$3,D23,E23,F23)) -> 0.2 | E23: 0.2 | G23: Assumption | H23: Used only to back-solve lead and account volumes.
A24: Target account to engaged lead | B24: % | C24: =IF(D24="",E24,CHOOSE($C$3,D24,E24,F24)) -> 0.25 | E24: 0.25 | G24: Assumption | H24: Used only to back-solve target-account list size.
A25: Opportunity to pilot (direct) | B25: % | C25: =IF(D25="",E25,CHOOSE($C$3,D25,E25,F25)) -> 0.3 | D25: 0.25 | E25: 0.3 | F25: 0.35 | G25: Validate | H25: Assumption; plants often want proof on their own machines before buying. | I25: Pilot design and acceptance criteria must be tested in interviews.
A26: Opportunity to pilot (partner-sourced) | B26: % | C26: =IF(D26="",E26,CHOOSE($C$3,D26,E26,F26)) -> 0.35 | D26: 0.3 | E26: 0.35 | F26: 0.4 | G26: Assumption | H26: Partner referral carries trust; modestly higher than direct.
A27: Sales cycle: qualified opportunity to pilot start | B27: months | C27: =IF(D27="",E27,CHOOSE($C$3,D27,E27,F27)) -> 3 | D27: 4 | E27: 3 | F27: 2 | G27: Validate | H27: Mid-market capex and IT approvals; total opp-to-go-live = this + pilot + implementation. | I27: Measure on first 10 opportunities.
A28: Paid pilot duration | B28: months | C28: =IF(D28="",E28,CHOOSE($C$3,D28,E28,F28)) -> 3 | E28: 3 | G28: Assumption | H28: Long enough to observe disruption events on critical machines.
A29: Pilot to paid annual contract | B29: % | C29: =IF(D29="",E29,CHOOSE($C$3,D29,E29,F29)) -> 0.55 | D29: 0.4 | E29: 0.55 | F29: 0.65 | G29: Validate | H29: Assumption. Industrial pilots frequently stall ('pilot purgatory'). | I29: Critical: define success metrics before each pilot.
A30: Partner channel productivity multiplier | B30: x plan | C30: =IF(D30="",E30,CHOOSE($C$3,D30,E30,F30)) -> 1 | D30: 0.5 | E30: 1 | F30: 1.5 | G30: Assumption | H30: Scales the partner opportunity plan in section H.
A32: C. IMPLEMENTATION & DEPLOYMENT
A33: Contract signature to go-live (implementation time) | B33: months | C33: =IF(D33="",E33,CHOOSE($C$3,D33,E33,F33)) -> 2 | D33: 3 | E33: 2 | F33: 2 | G33: Assumption | H33: PlanetTogether states many APS integrations take 4-8 weeks; plants with poor data take longer.
A34: Concurrent implementations per implementation engineer | B34: # | C34: =IF(D34="",E34,CHOOSE($C$3,D34,E34,F34)) -> 3 | D34: 2 | E34: 3 | F34: 3.5 | G34: Assumption | H34: REVISED from 2 (bear 1.5 / bull 2.5). Partner-led delivery: SI partners do on-site wiring; our engineers configure remotely from a standard connector library, so each runs 3 at once. The partner's fee is in the direct cost per go-live (row 38).
A35: Engineer load of one active pilot vs one implementation | B35: x | C35: =IF(D35="",E35,CHOOSE($C$3,D35,E35,F35)) -> 0.5 | E35: 0.5 | G35: Assumption | H35: Pilots use a lighter, time-boxed scope.
A36: Month implementation team starts | B36: month # | C36: =IF(D36="",E36,CHOOSE($C$3,D36,E36,F36)) -> 3 | E36: 3 | G36: Assumption | H36: First hire with seed money.
A37: Minimum implementation engineers once started | B37: # | C37: =IF(D37="",E37,CHOOSE($C$3,D37,E37,F37)) -> 1 | E37: 1 | G37: Assumption
A38: Direct cost per go-live (travel, on-site, connectors, integration tooling) | B38: ₹ lakh | C38: =IF(D38="",E38,CHOOSE($C$3,D38,E38,F38)) -> 2.5 | E38: 2.5 | G38: Assumption | H38: REVISED from ₹1.5 lakh. Now includes ~₹1 lakh paid to the SI partner per site (wiring, gateway set-up) plus travel and connectors. Excludes our engineer salaries (modelled separately). | I38: Cost a real implementation end to end.
A39: Implementation direct-cost multiplier | B39: x | C39: =IF(D39="",E39,CHOOSE($C$3,D39,E39,F39)) -> 1 | D39: 1.3 | E39: 1 | F39: 0.85 | G39: Assumption | H39: Bear reflects customisation creep.
A40: Direct cost per pilot started | B40: ₹ lakh | C40: =IF(D40="",E40,CHOOSE($C$3,D40,E40,F40)) -> 1 | E40: 1 | G40: Assumption | H40: Site visits, temporary data connections.
A41: Share of new plants needing the optional IoT kit | B41: % | C41: =IF(D41="",E41,CHOOSE($C$3,D41,E41,F41)) -> 0.5 | D41: 0.6 | E41: 0.5 | F41: 0.4 | G41: Validate | H41: Software-first: kit only where PLC/CNC data cannot be read. | I41: Survey data-readiness of target plants.
A42: Critical machines connected per plant (average) | B42: # | C42: =IF(D42="",E42,CHOOSE($C$3,D42,E42,F42)) -> 20 | E42: 20 | G42: Assumption | H42: Between Essential (≤15) and Professional (≤30) coverage.
A43: IoT kit cost per plant (sensors + gateway, ~12 machines) | B43: ₹ lakh | C43: =IF(D43="",E43,CHOOSE($C$3,D43,E43,F43)) -> 3.5 | E43: 3.5 | G43: Assumption | H43: Benchmark: non-intrusive sensors typically $200-600 per machine (TeepTrak 2026). 12 x ~$300 x ₹95 = ₹3.4 lakh incl. gateway.
A44: Markup on resold IoT kit | B44: % | C44: =IF(D44="",E44,CHOOSE($C$3,D44,E44,F44)) -> 0.1 | E44: 0.1 | G44: Assumption | H44: Pass-through with handling margin; not a profit engine.
A46: D. PRICING, RETENTION & EXPANSION (tier prices are on 3_Pricing)
A47: Scenario price multiplier on tier list prices | B47: x | C47: =IF(D47="",E47,CHOOSE($C$3,D47,E47,F47)) -> 1 | D47: 1 | E47: 1 | F47: 1 | G47: Validate | H47: v4: 1.0 in all scenarios. Scenario prices are now explicit on 3_Pricing (bear at the low end of each range), so a multiplier would double-count. | I47: Willingness-to-pay interviews (Van Westendorp / Gabor-Granger).
A48: Annual list-price escalation | B48: % p.a. | C48: =IF(D48="",E48,CHOOSE($C$3,D48,E48,F48)) -> 0.05 | D48: 0.03 | E48: 0.05 | F48: 0.05 | G48: Assumption | H48: Applied to new-customer list price and to existing ARR at renewal.
A49: Expansion ARR from existing plants (upsell, lines, modules) | B49: % of ARR p.a. | C49: =IF(D49="",E49,CHOOSE($C$3,D49,E49,F49)) -> 0.1 | D49: 0.05 | E49: 0.1 | F49: 0.15 | G49: Assumption | H49: REVISED from 6% (bear 3% / bull 10%). Land-and-expand: a quarter of new logos are Enterprise plants or groups that add lines and sister plants. With 9% churn and 5% escalation, NRR ≈ 104.7%, just above the SaaS Capital 2025 median of 103% for ACV $12-25k (this model's ACV ≈ $14k). | I49: Track expansion by source (new lines, sister plants, modules) from the first renewal.
A50: Annual logo churn | B50: % p.a. | C50: =IF(D50="",E50,CHOOSE($C$3,D50,E50,F50)) -> 0.09 | D50: 0.15 | E50: 0.09 | F50: 0.06 | G50: Validate | H50: REVISED from 12% (bear 18% / bull 8%). Deep PLC/CNC integration and the planner workflow make switching costly; 9% churn = 91% gross revenue retention, equal to the SaaS Capital 2025 median for ACV $12-25k. Applied monthly as a smooth rate. | I50: Churn is unknown until first renewals in FY28-FY29; track logo and revenue churn separately.
A51: Paid pilot fee (whole pilot) | B51: ₹ lakh | C51: =IF(D51="",E51,CHOOSE($C$3,D51,E51,F51)) -> 2.5 | D51: 1.5 | E51: 2.5 | F51: 3 | G51: Validate | H51: REVISED from ₹1.5 lakh (bear 1 / bull 2). A 3-month pilot at about the Professional monthly price (₹83k a month); covers the ₹1 lakh direct pilot cost plus engineer time. Not credited against the subscription.
A52: Gain-share fee per live plant per month (expected, after haircut) | B52: ₹ lakh | C52: =IF(D52="",E52,CHOOSE($C$3,D52,E52,F52)) -> 0.1453125 | D52: =D153*D154*D155*D156/12 -> 0 | E52: =E153*E154*E155*E156/12 -> 0.1453125 | F52: =F153*F154*F155*F156/12 -> 0.406875 | G52: Calculated | H52: v4: share on gain-share × verified savings × share charged × collection probability ÷ 12 (section K). Kept out of ARR.
A54: E. COST TO SERVE (per plant per month, ₹ lakh)
A55: Cloud hosting & compute | B55: ₹ lakh/plant/mo | C55: =IF(D55="",E55,CHOOSE($C$3,D55,E55,F55)) -> 0.07 | E55: 0.07 | G55: Assumption | H55: Assumption: ~25-40 connected assets streaming at minute-level resolution. | I55: Benchmark from a real pilot's cloud bill.
A56: AI inference & optimisation solver runs | B56: ₹ lakh/plant/mo | C56: =IF(D56="",E56,CHOOSE($C$3,D56,E56,F56)) -> 0.03 | E56: 0.03 | G56: Assumption | H56: Assumption; scenario solving is run on disruption events, not continuously.
A57: Industrial data ingestion & storage | B57: ₹ lakh/plant/mo | C57: =IF(D57="",E57,CHOOSE($C$3,D57,E57,F57)) -> 0.02 | E57: 0.02 | G57: Assumption | H57: Assumption.
A58: Third-party software licences (connectors, solver, monitoring) | B58: ₹ lakh/plant/mo | C58: =IF(D58="",E58,CHOOSE($C$3,D58,E58,F58)) -> 0.025 | E58: 0.025 | G58: Assumption | H58: Assumption; commercial solver/OPC-UA licences may cost more.
A59: Ongoing model monitoring & retraining effort | B59: ₹ lakh/plant/mo | C59: =IF(D59="",E59,CHOOSE($C$3,D59,E59,F59)) -> 0.025 | E59: 0.025 | G59: Assumption | H59: Assumption; allocated ML-ops time.
A60: Cloud & AI cost multiplier | B60: x | C60: =IF(D60="",E60,CHOOSE($C$3,D60,E60,F60)) -> 1 | D60: 1.25 | E60: 1 | F60: 0.9 | G60: Assumption | H60: Bear = AI/cloud cost escalation.
A61: Change in cloud/AI cost per plant each year | B61: % p.a. | C61: =IF(D61="",E61,CHOOSE($C$3,D61,E61,F61)) -> -0.05 | D61: 0 | E61: -0.05 | F61: -0.1 | G61: Assumption | H61: Unit cloud costs usually fall with scale and engineering (reserved instances, edge pre-processing). Bear: no efficiency gain.
A62: Fixed platform security & data-management cost | B62: ₹ lakh/mo | C62: =IF(D62="",E62,CHOOSE($C$3,D62,E62,F62)) -> 1.5 | E62: 1.5 | G62: Assumption | H62: SIEM, backups, pen-testing, ISO 27001 readiness. OT cyber risk makes this non-optional.
A63: Month fixed platform cost starts | B63: month # | C63: =IF(D63="",E63,CHOOSE($C$3,D63,E63,F63)) -> 3 | E63: 3 | G63: Assumption
A64: Live plants per customer success manager | B64: # | C64: =IF(D64="",E64,CHOOSE($C$3,D64,E64,F64)) -> 25 | D64: 20 | E64: 25 | F64: 30 | G64: Assumption | H64: REVISED from 20 (bear 15 / bull 25). Remote monthly value reviews and automated health monitoring let one CSM cover 25 plants.
A65: Live plants per technical support engineer | B65: # | C65: =IF(D65="",E65,CHOOSE($C$3,D65,E65,F65)) -> 30 | E65: 30 | G65: Assumption | H65: REVISED from 25. Pooled shift support with automated alert triage.
A67: F. COMPENSATION (annual CTC at FY27 levels, ₹ lakh)
A68: Founders (each, below-market) | B68: ₹ lakh p.a. | C68: =IF(D68="",E68,CHOOSE($C$3,D68,E68,F68)) -> 12 | E68: 12 | G68: Assumption | H68: Assumption for a tier-1 city startup; benchmark against Naukri/AmbitionBox before use.
A69: AI/ML engineer | B69: ₹ lakh p.a. | C69: =IF(D69="",E69,CHOOSE($C$3,D69,E69,F69)) -> 18 | E69: 18 | G69: Validate | H69: Indeed India: ML engineer average base ~₹11.6-11.9 lakh (Jun-Aug 2026); startups competing for mid-level talent pay more.
A70: Software developer | B70: ₹ lakh p.a. | C70: =IF(D70="",E70,CHOOSE($C$3,D70,E70,F70)) -> 14 | E70: 14 | G70: Assumption | H70: Assumption for a tier-1 city startup; benchmark against Naukri/AmbitionBox before use.
A71: Data engineer | B71: ₹ lakh p.a. | C71: =IF(D71="",E71,CHOOSE($C$3,D71,E71,F71)) -> 15 | E71: 15 | G71: Assumption | H71: Assumption for a tier-1 city startup; benchmark against Naukri/AmbitionBox before use.
A72: Industrial automation / manufacturing engineer | B72: ₹ lakh p.a. | C72: =IF(D72="",E72,CHOOSE($C$3,D72,E72,F72)) -> 12 | E72: 12 | G72: Assumption | H72: Assumption for a tier-1 city startup; benchmark against Naukri/AmbitionBox before use.
A73: Product manager | B73: ₹ lakh p.a. | C73: =IF(D73="",E73,CHOOSE($C$3,D73,E73,F73)) -> 24 | E73: 24 | G73: Assumption | H73: Assumption for a tier-1 city startup; benchmark against Naukri/AmbitionBox before use.
A74: Implementation & integration engineer | B74: ₹ lakh p.a. | C74: =IF(D74="",E74,CHOOSE($C$3,D74,E74,F74)) -> 10 | E74: 10 | G74: Assumption | H74: Assumption for a tier-1 city startup; benchmark against Naukri/AmbitionBox before use.
A75: Customer success manager | B75: ₹ lakh p.a. | C75: =IF(D75="",E75,CHOOSE($C$3,D75,E75,F75)) -> 9 | E75: 9 | G75: Assumption | H75: Assumption for a tier-1 city startup; benchmark against Naukri/AmbitionBox before use.
A76: Technical support engineer | B76: ₹ lakh p.a. | C76: =IF(D76="",E76,CHOOSE($C$3,D76,E76,F76)) -> 6 | E76: 6 | G76: Assumption | H76: Assumption for a tier-1 city startup; benchmark against Naukri/AmbitionBox before use.
A77: B2B account executive (fixed pay) | B77: ₹ lakh p.a. | C77: =IF(D77="",E77,CHOOSE($C$3,D77,E77,F77)) -> 14 | E77: 14 | G77: Assumption | H77: Assumption for a tier-1 city startup; benchmark against Naukri/AmbitionBox before use.
A78: Pre-sales / solution engineer | B78: ₹ lakh p.a. | C78: =IF(D78="",E78,CHOOSE($C$3,D78,E78,F78)) -> 15 | E78: 15 | G78: Assumption | H78: Assumption for a tier-1 city startup; benchmark against Naukri/AmbitionBox before use.
A79: Enterprise account manager | B79: ₹ lakh p.a. | C79: =IF(D79="",E79,CHOOSE($C$3,D79,E79,F79)) -> 20 | E79: 20 | G79: Assumption | H79: Assumption for a tier-1 city startup; benchmark against Naukri/AmbitionBox before use.
... A82: Cybersecurity & IT lead | B82: ₹ lakh p.a. | C82: =IF(D82="",E82,CHOOSE($C$3,D82,E82,F82)) -> 20 | E82: 20 | G82: Assumption | H82: Assumption for a tier-1 city startup; benchmark against Naukri/AmbitionBox before use.
A83: AEs per pre-sales engineer | B83: # | C83: =IF(D83="",E83,CHOOSE($C$3,D83,E83,F83)) -> 3 | E83: 3 | G83: Assumption
A84: Month non-founder hires start in FY27 | B84: month of FY | C84: =IF(D84="",E84,CHOOSE($C$3,D84,E84,F84)) -> 3 | E84: 3 | G84: Assumption | H84: Avoids assuming a full team on day one.
A86: G. OPERATING EXPENSES, CAPEX, WORKING CAPITAL
A87: Sales travel per customer-facing seller | B87: ₹ lakh/mo | C87: =IF(D87="",E87,CHOOSE($C$3,D87,E87,F87)) -> 0.6 | E87: 0.6 | G87: Assumption | H87: Plant visits across industrial clusters.
A88: Sales commission on first-year ACV (direct) | B88: % | C88: =IF(D88="",E88,CHOOSE($C$3,D88,E88,F88)) -> 0.08 | E88: 0.08 | G88: Assumption | H88: Expensed when signed (simplification of Ind AS 115 contract-cost rules).
A89: Channel partner commission on first-year ACV | B89: % | C89: =IF(D89="",E89,CHOOSE($C$3,D89,E89,F89)) -> 0.2 | E89: 0.2 | G89: Assumption | H89: REVISED from 15%. Integrators may ask 15-25%; set at 20% because the partner channel now carries far more volume. | I89: Negotiate terms with the first 3-5 integrators in FY28; scale to 15-20 active partners by FY31.
A90: Partner programme cost (enablement, co-marketing) once active | B90: ₹ lakh/mo | C90: =IF(D90="",E90,CHOOSE($C$3,D90,E90,F90)) -> 1.5 | E90: 1.5 | G90: Assumption | H90: REVISED from ₹0.5 lakh a month. Scaled for a 15-20 partner programme (partner manager time, enablement, co-marketing).
A91: R&D tools per R&D head | B91: ₹ lakh/mo | C91: =IF(D91="",E91,CHOOSE($C$3,D91,E91,F91)) -> 0.15 | E91: 0.15 | G91: Assumption
A92: Development & test cloud environment | B92: ₹ lakh/mo | C92: =IF(D92="",E92,CHOOSE($C$3,D92,E92,F92)) -> 0.75 | E92: 0.75 | G92: Assumption
A93: Office / co-working per head | B93: ₹ lakh/mo | C93: =IF(D93="",E93,CHOOSE($C$3,D93,E93,F93)) -> 0.12 | E93: 0.12 | G93: Assumption
A94: Legal, compliance, audit, secretarial | B94: ₹ lakh/mo | C94: =IF(D94="",E94,CHOOSE($C$3,D94,E94,F94)) -> 0.75 | E94: 0.75 | G94: Assumption
A95: Cyber & professional-indemnity insurance | B95: ₹ lakh/mo | C95: =IF(D95="",E95,CHOOSE($C$3,D95,E95,F95)) -> 0.25 | E95: 0.25 | G95: Assumption | H95: Needed before connecting to customer OT networks.
A96: Month insurance starts | B96: month # | C96: =IF(D96="",E96,CHOOSE($C$3,D96,E96,F96)) -> 6 | E96: 6 | G96: Assumption
A97: Recruitment cost per new hire | B97: ₹ lakh | C97: =IF(D97="",E97,CHOOSE($C$3,D97,E97,F97)) -> 0.75 | E97: 0.75 | G97: Assumption
A98: Capex per new hire (laptop, peripherals) | B98: ₹ lakh | C98: =IF(D98="",E98,CHOOSE($C$3,D98,E98,F98)) -> 1.2 | E98: 1.2 | G98: Assumption
A99: Test rig / demo lab (PLCs, sensors, edge devices) | B99: ₹ lakh | C99: =IF(D99="",E99,CHOOSE($C$3,D99,E99,F99)) -> 10 | E99: 10 | G99: Assumption | H99: One-off; lets the team test connectors without customer downtime.
A100: Month of test-rig purchase | B100: month # | C100: =IF(D100="",E100,CHOOSE($C$3,D100,E100,F100)) -> 3 | E100: 3 | G100: Assumption
A101: Depreciation life of capex | B101: months | C101: =IF(D101="",E101,CHOOSE($C$3,D101,E101,F101)) -> 36 | E101: 36 | G101: Assumption | H101: Straight line. R&D is expensed, not capitalised (Ind AS 38 criteria not demonstrable pre-revenue).
A102: Receivable days (DSO) | B102: days | C102: =IF(D102="",E102,CHOOSE($C$3,D102,E102,F102)) -> 45 | D102: 75 | E102: 45 | F102: 30 | G102: Assumption | H102: REVISED from 60 days (bear 90 / bull 45). MSMED Act s.15 caps payment to registered micro/small suppliers at 45 days, and Income-tax s.43B(h) (from FY24) defers the buyer's tax deduction if it pays late. | I102: Register on Udyam; check customer payment terms.
A103: Payable days on non-people costs | B103: days | C103: =IF(D103="",E103,CHOOSE($C$3,D103,E103,F103)) -> 30 | E103: 30 | G103: Assumption
A104: Subscription billed in advance (avg months of MRR held as deferred revenue) | B104: months | C104: =IF(D104="",E104,CHOOSE($C$3,D104,E104,F104)) -> 1.5 | E104: 1.5 | G104: Assumption | H104: Quarterly-in-advance billing gives ~1.5 months average deferred revenue.
A105: Interest earned on cash | B105: % p.a. | C105: =IF(D105="",E105,CHOOSE($C$3,D105,E105,F105)) -> 0 | E105: 0 | G105: Assumption | H105: Set to 0 so the funding requirement is not flattered by treasury income.
A107: H. FUNDING
A108: Seed equity raised | B108: ₹ lakh | C108: =IF(D108="",E108,CHOOSE($C$3,D108,E108,F108)) -> 900 | E108: 900 | G108: Assumption | H108: Sized by re-running the base case: seed covers deficit to the Series A month + 6 months' burn + 15% contingency.
A109: Seed close month | B109: month # | C109: =IF(D109="",E109,CHOOSE($C$3,D109,E109,F109)) -> 1 | E109: 1 | G109: Assumption
A110: Series A equity raised | B110: ₹ lakh | C110: =IF(D110="",E110,CHOOSE($C$3,D110,E110,F110)) -> 900 | E110: 900 | G110: Assumption | H110: REVISED from ₹1,400 lakh. Timing unchanged at month 22 (Jan-2028), when the base case has about ₹1.2 crore ARR: the round is raised on pilot conversion, reference plants and first renewals, not scale. Sized to carry the revised base case past EBITDA break-even with buffer (see 11_Funding).
A111: Series A close month | B111: month # | C111: =IF(D111="",E111,CHOOSE($C$3,D111,E111,F111)) -> 22 | E111: 22 | G111: Assumption | H111: Month 22 (Jan-2028). Base-case ARR is then about ₹1.2 crore with first renewals due; seed alone lasts 32 months, so a later close still fits.
...

Sheet 2_Market
A1: 2. MARKET SIZING: TAM, SAM, SOM (revised 11-Oct-2026: TAM = 63,728 operating factories in 7 target industries, ASI 2023-24)
A2: TAM is the broad industry pool, not the qualified customer base. SAM applies size, geography and readiness filters once each (section F). SOM is the Year-5 live-plant outcome of the sales-capacity engine, solved to the bear / base / bull targets.
A4: A. SEGMENT PLANT COUNTS: CROSS-CHECK AND SIZE MIX (ASI 2019-20 by NIC, scaled; the TAM itself now uses ASI 2023-24, section F)
A5: Segment (NIC-2008 2-digit) | B5: Role | C5: Factories in operation ASI 2019-20 | D5: Persons engaged ASI 2019-20 | E5: Avg persons per factory | F5: Share with 100+ workers, est. | G5: Factories 2024-25 (scaled) | H5: Plants with 100+ workers 2024-25, est. | I5: Notes
A6: 29 Motor vehicles, trailers (incl. auto components) | B6: SAM | C6: 5353 | D6: 1082076 | E6: =D6/C6 -> 202.14384 | F6: =MIN($C$24,$C$23*E6/$C$22) -> 0.48304529 | G6: =C6*$C$26 -> 5889.7068 | H6: =G6*F6 -> 2844.9951 | I6: Beachhead. Large plants.
A7: 28 Machinery & equipment n.e.c. | B7: SAM | C7: 10949 | D7: 935811 | E7: =D7/C7 -> 85.469997 | F7: =MIN($C$24,$C$23*E7/$C$22) -> 0.2042401 | G7: =C7*$C$26 -> 12046.777 | H7: =G7*F7 -> 2460.4351 | I7: Core.
A8: 25 Fabricated metal products | B8: SAM | C8: 12635 | D8: 705038 | E8: =D8/C8 -> 55.800396 | F8: =MIN($C$24,$C$23*E8/$C$22) -> 0.13334128 | G8: =C8*$C$26 -> 13901.821 | H8: =G8*F8 -> 1853.6865 | I8: Core.
A9: 24 Basic metals (castings, forgings, steel processing) | B9: SAM | C9: 10106 | D9: 1204877 | E9: =D9/C9 -> 119.22393 | F9: =MIN($C$24,$C$23*E9/$C$22) -> 0.28489889 | G9: =C9*$C$26 -> 11119.256 | H9: =G9*F9 -> 3167.8636 | I9: ADDED: furnaces, presses and casting lines that feed auto and machinery supply chains.
A10: 22 Rubber & plastics products | B10: SAM | C10: 11732 | D10: 843562 | E10: =D10/C10 -> 71.902659 | F10: =MIN($C$24,$C$23*E10/$C$22) -> 0.17181943 | G10: =C10*$C$26 -> 12908.283 | H10: =G10*F10 -> 2217.8939 | I10: MOVED from adjacent to SAM: injection-moulding cells have the same machine-and-schedule problem.
A11: 27 Electrical equipment | B11: SAM | C11: 6076 | D11: 635006 | E11: =D11/C11 -> 104.51053 | F11: =MIN($C$24,$C$23*E11/$C$22) -> 0.24973959 | G11: =C11*$C$26 -> 6685.1968 | H11: =G11*F11 -> 1669.5583 | I11: MOVED from adjacent to SAM: machining and assembly lines.
A12: 30 Other transport equipment | B12: SAM | C12: 1855 | D12: 421386 | E12: =D12/C12 -> 227.16226 | F12: =MIN($C$24,$C$23*E12/$C$22) -> 0.5 | G12: =C12*$C$26 -> 2040.9875 | H12: =G12*F12 -> 1020.4937 | I12: ADDED: two-wheeler, rail and aerospace component plants.
A13: 13 Textiles | B13: TAM only | C13: 13539 | D13: 1629101 | E13: =D13/C13 -> 120.32654 | F13: =MIN($C$24,$C$23*E13/$C$22) -> 0.2875337 | G13: =C13*$C$26 -> 14896.458 | H13: =G13*F13 -> 4283.2337 | I13: Machine-intensive but continuous spinning and weaving; different scheduling logic.
A14: 26 Computer, electronic & optical products | B14: TAM only | C14: 1908 | D14: 283470 | E14: =D14/C14 -> 148.56918 | F14: =MIN($C$24,$C$23*E14/$C$22) -> 0.35502265 | G14: =C14*$C$26 -> 2099.3014 | H14: =G14*F14 -> 745.29956 | I14: Assembly-led; outside the current product.
A15: Target industries (7) | C15: =SUMIF($B$6:$B$14,"SAM",C6:C14) -> 58706 | D15: =SUMIF($B$6:$B$14,"SAM",D6:D14) -> 5827756 | G15: =SUMIF($B$6:$B$14,"SAM",G6:G14) -> 64592.028 | H15: =SUMIF($B$6:$B$14,"SAM",H6:H14) -> 15234.926 | I15: Counts are from ASI 2019-20 (latest NIC-wise table found) scaled to the 2024-25 factory total.
A16: Machine-intensive segments (9) | C16: =SUM(C6:C14) -> 74153 | D16: =SUM(D6:D14) -> 7740327 | G16: =SUM(G6:G14) -> 81587.788 | H16: =SUM(H6:H14) -> 20263.46
A18: B. PARAMETERS
A19: Parameter | B19: Unit | C19: Value | D19: Type | E19: Source / rationale
A20: All-India factories in operation, ASI 2019-20 | B20: # | C20: 198628 | D20: Verified fact | E20: Lok Sabha Unstarred Q.541 (6-Dec-2023), MoSPI annexure.
A21: All-India persons engaged, ASI 2019-20 | B21: # | C21: 16624291 | D21: Verified fact | E21: Lok Sabha Unstarred Q.541 (6-Dec-2023), MoSPI annexure.
A22: All-India average persons per factory | B22: # | C22: =C21/C20 -> 83.695607 | D22: Calculated
A23: Share of all factories with 100+ workers | B23: % | C23: 0.2 | D23: Verified fact (rounded) | E23: 'About one in five' operational factories employed 100+ workers (ASI 2022-23, via Data For India). Workers are fewer than persons engaged, so this is conservative. Replaces the ASI 2008-09 figure (14.1% for 100-999 persons) used before.
A24: Cap on any segment's 100+ share | B24: % | C24: 0.5 | D24: Assumption | E24: Stops the size-scaling method overshooting in large-plant segments (binds only for NIC 30 at current inputs).
A25: All-India factories in operation, ASI 2024-25 | B25: # | C25: 218543 | D25: Verified fact | E25: MoSPI press note and factsheet, ASI 2024-25 (2,18,543 in operation; 2,66,931 total).
A26: Scaling factor 2019-20 → 2024-25 | B26: x | C26: =C25/C20 -> 1.1002628 | D26: Assumption | E26: Assumes each segment grew in line with all manufacturing.
A27: Technical readiness (machine data readable or kit acceptable; planner exists) | B27: % | C27: 0.4 | D27: Validate | E27: Unchanged from the original model. No published source; survey 30+ target plants.
A28: Share of factories in the top-5 manufacturing states | B28: % | C28: 0.533 | D28: Verified fact | E28: Tamil Nadu, Gujarat, Maharashtra, Uttar Pradesh and Karnataka hold 53.3% of establishments (ASI 2024-25 press note). Direct sales cover these; partner reach beyond them is not counted.
A30: C. TAM / SAM / SOM
A31: Measure | B31: Unit | C31: Plants | D31: ₹ lakh per plant p.a. | E31: Market ₹ lakh p.a. | F31: Market ₹ crore p.a. | I31: Definition
A32: TAM: 7 target industries, operating factories (ASI 2023-24): broad industry pool, not qualified customers | C32: =D56 -> 63728 | D32: =3_Pricing!$F$8 -> 28.75 | E32: =C32*D32 -> 1832180 | F32: =E32/100 -> 18321.8 | I32: Pool × active scenario's blended realised price. Overstates value: most of these plants are too small for this pricing.
A33: Size-qualified pool: 100+ workers | C33: =D58 -> 15031.133 | D33: =3_Pricing!$F$8 -> 28.75 | E33: =C33*D33 -> 432145.08 | F33: =E33/100 -> 4321.4508 | I33: After filter 2 (section F).
A34: SAM: × top-5 states × operational readiness | C34: =D61 -> 3204.6376 | D34: =3_Pricing!$F$8 -> 28.75 | E34: =C34*D34 -> 92133.332 | F34: =E34/100 -> 921.33332 | I34: After filters 3 and 4 (section F). Filters 2-4 are estimates or unvalidated.
A35: SOM FY31: live paying plants (engine, active scenario; solved to the scenario target) | C35: =INDEX(Engine_Monthly!$D$49:$BK$49,1,5*12) -> 400.00001 | D35: =4_Revenue_Build!G34 -> 39.364444 | E35: =C35*D35 -> 15745.778 | F35: =E35/100 -> 157.45778 | I35: From AEs, partners, conversion, implementation capacity and churn. Not a share assumption.
A36: SOM FY31 as % of SAM plants | C36: =IFERROR(C35/C34,0) -> 0.12481911 | I36: Low single digits five years in: room to grow without new segments.
A37: SOM FY36: implied live plants (valuation fade) | C37: =14_Valuation!C87 -> 388.30242 | D37: =14_Valuation!C89 -> 50.240114 | E37: =C37*D37 -> 19508.358 | F37: =E37/100 -> 195.08358 | I37: FY36 subscription revenue ÷ ARR per plant grown at list-price escalation. A ceiling check on the fade, not a driver.
A38: SOM FY36 as % of SAM plants | C38: =IFERROR(C37/C34,0) -> 0.1211689 | I38: Against today’s SAM, which itself grows with the factory count. Above ~25% would make the fade implausible.
A39: TAM and SAM are valued at the FY27 blended list price; SOM at FY31 / FY36 ARR per plant, which includes price escalation and expansion. Compare shares on plant counts.
A40: D. RECONCILIATION WITH THE SALES FORECAST
A41: Qualified opportunities generated over 5 years | C41: =SUM(Engine_Monthly!$D$20:$BK$20) -> 3570.1908
A42: …as % of SAM plants | C42: =IFERROR(C41/C34,0) -> 1.11407 | I42: Below 100% means the funnel can be fed from SAM plants alone (re-engagements counted).
A43: Target-account engagements over 5 years (back-solved; repeat touches counted) | C43: =SUM(Engine_Monthly!$D$22:$BK$22) -> 71403.815
A44: …as % of size-qualified pool | C44: =IFERROR(C43/C33,0) -> 4.7503946 | I44: =IFERROR("Over 5 years: "&TEXT(C43/C34,"0.0")&"x SAM plants, about "&TEXT(C43/C34/5,"0.0")&" engagements per SAM plant a year (events, outbound, partner referrals; repeats counted). Unique demand test is row 42.","") -> Over 5 years: 22.3x SAM plants, about 4.5 engagements per SAM plant a year (events, outbound, partner referrals; repeats counted). Unique demand test is row 42.
A45: Contracts signed over 5 years | C45: =SUM(Engine_Monthly!$D$32:$BK$32) -> 490.48474
A47: E. ORIGINAL MODEL VS REVISED
A48: Measure | C48: Original plants | D48: Original ₹ crore | E48: Revised plants | F48: Revised ₹ crore | G48: v3 plants | H48: v3 ₹ crore | I48: What changed
A49: TAM | C49: 30749 | D49: 2748.96 | E49: =C32 -> 63728 | F49: =F32 -> 18321.8 | G49: 43708.6 | H49: 5638.41 | I49: v4: 63,728-factory pool in 7 industries (ASI 2023-24) replaces all 100+ worker factories; valued at the scenario's realised price.
A50: SAM | C50: 1007.29 | D50: 90.05 | E50: =C34 -> 3204.6376 | F50: =F34 -> 921.33332 | G50: 3248.09 | H50: 419 | I50: v4: same filters (size, top-5 states, readiness) applied once each to the new pool.
A51: SOM FY31 | C51: 83.37 | D51: 9.94 | E51: =C35 -> 400.00001 | F51: =F35 -> 157.45778 | G51: 120.1 | H51: 21.67 | I51: v4: SOM solved to the scenario's Year-5 target (bear 200 / base 400 / bull 600).
A52: Original figures are values from the team's model as received (10-Oct-2026); v3 values from the 10-Oct-2026 revision.
A54: F. TAM → SAM FILTER WATERFALL (each filter applied once, in order; v4, 11-Oct-2026)
A55: Step | B55: Unit | C55: Share kept | D55: Plants | E55: Type | I55: Source / rationale and caveats
A56: TAM: operating factories in the 7 target industries (broad industry pool) | B56: # | D56: 63728 | E56: Team-provided (ASI 2023-24) | I56: NIC 22, 24, 25, 27, 28, 29, 30, ASI 2023-24, as supplied by the team. Segment table not yet attached to this workbook: attach it. Cross-check: the same 7 industries in ASI 2019-20 scaled to 2024-25 give 64,592 (row 15). Not a qualified customer base.
A57: Filter 1. Target industry | B57: % | C57: 1 | D57: =D56*C57 -> 63728 | E57: Already applied | I57: The TAM is already limited to the 7 industries, so this filter is 100% here. Applying an industry share again would double-count.
A58: Filter 2. Plant size: 100+ workers | B58: % | C58: =H15/G15 -> 0.23586388 | D58: =D57*C58 -> 15031.133 | E58: Calculated estimate | I58: Segment-weighted share from section A (ASI 2019-20 average plant size per industry, anchored to the ~20% all-industry 100+ share, ASI 2022-23). Method assumption, not a published NIC × size table. Pricing at ₹15-50 lakh implies larger plants than 100 workers: see flag on 16_SOM_Scenarios.
A59: Filter 3. Geography: top-5 manufacturing states | B59: % | C59: =C28 -> 0.533 | D59: =D58*C59 -> 8011.5941 | E59: Verified (all manufacturing) | I59: 53.3% of establishments are in TN, GJ, MH, UP, KA (ASI 2024-25). Applying an all-manufacturing share to these 7 industries is an assumption.
A60: Filter 4. Operational readiness (readable machine data or kit acceptable; planner in place) | B60: % | C60: =C27 -> 0.4 | D60: =D59*C60 -> 3204.6376 | E60: Unvalidated | I60: No published source. Survey 30+ target plants.
A61: SAM: plants the company can serve and reach | B61: # | D61: =D60 -> 3204.6376 | E61: Calculated | I61: Filters multiplied as if independent. Larger plants are likely more data-ready and more concentrated in the top-5 states, so this may understate SAM slightly.
A62: Combined SAM ÷ TAM | C62: =IFERROR(D61/D56,0) -> 0.050286179
A64: Year-5 SOM by scenario | B64: Unit | C64: Bear | D64: Base | E64: Bull | I64: Note
A65: FY31 live paying plants: target | B65: # | C65: =Inputs!D151 -> 200 | D65: =Inputs!E151 -> 400 | E65: =Inputs!F151 -> 600
A66: …as % of SAM plants | B66: % | C66: =IFERROR(C65/$D$61,0) -> 0.062409552 | D66: =IFERROR(D65/$D$61,0) -> 0.1248191 | E66: =IFERROR(E65/$D$61,0) -> 0.18722866 | I66: A new vendor winning more than ~10% of its serviceable market in five years would be exceptional. Flagged on 16_SOM_Scenarios.
A67: …as % of TAM (broad pool) | B67: % | C67: =IFERROR(C65/$D$56,0) -> 0.0031383379 | D67: =IFERROR(D65/$D$56,0) -> 0.0062766759 | E67: =IFERROR(E65/$D$56,0) -> 0.0094150138

Sheet 3_Pricing
A1: 3. BUSINESS MODEL & PRICING (tier prices are hypotheses to validate; revised 11-Oct-2026)
A3: Pricing tiers (per plant, annual subscription)
A4: Attribute | C4: Starter | D4: Professional | E4: Enterprise | F4: Blended (new-customer mix) | G4: Notes
A5: Target customer | C5: Single-line plant (~₹100-250 crore revenue), 10-15 critical machines. Hypothesis. | D5: Mid-sized plant (~₹250-500 crore revenue), 15-30 critical machines, planner in place. Hypothesis. | E5: ₹500 crore+ plant or multi-plant group, ERP/MES integration expected. Hypothesis.
A6: Included functionality | C6: Machine-health risk alerts, downtime capture, disruption log, basic dashboards | D6: Starter + constraint-aware disruption scenarios, ranked recommendations with ₹ trade-offs, approval workflow | E6: Professional + ERP/MES integration, multi-line optimisation, group reporting, SSO, SLA
A7: Coverage | C7: Up to 15 critical machines, 1 line | D7: Up to 30 critical machines, up to 3 lines | E7: Unlimited lines in a plant; group pricing per plant
A8: Average realised annual subscription per plant (₹ lakh, FY27; active scenario, from row 51-53) | C8: =INDEX(C$51:C$53,Inputs!$C$3,1) -> 15 | D8: =INDEX(D$51:D$53,Inputs!$C$3,1) -> 30 | E8: =INDEX(E$51:E$53,Inputs!$C$3,1) -> 50 | F8: =SUMPRODUCT($C$11:$E$11,C8:E8) -> 28.75 | G8: REVISED from 4.8 / 9.6 / 18.0. Professional = ₹95k a month, equal to PlanetTogether's Essential APS listing ($1,000/plant/month ≈ ₹11.4 lakh a year at ₹95/$) and inside the 3x value rule on 9_Customer_ROI (3.05x; customer payback ≈ 13 months). Benefits there are in today's ₹, so the test holds over time if they rise with wages and input costs at the 5% list-price escalation. Enterprise = 2x Professional for multi-line plants and groups.
A9: Monthly equivalent (₹ lakh) | C9: =C8/12 -> 1.25 | D9: =D8/12 -> 2.5 | E9: =E8/12 -> 4.1666667
A10: One-time implementation fee (₹ lakh) | C10: 3 | D10: 6 | E10: 12 | F10: =SUMPRODUCT($C$11:$E$11,C10:E10) -> 6.15 | G10: REVISED from 1.5 / 4 / 8. Priced to recover deployment cost including SI partner fees, at roughly an IT-services margin; ≈0.5x first-year ACV, usual for software that connects to PLC/CNC data.
A11: Share of new customers by tier (active scenario, from rows 54-56) | C11: =INDEX(C$54:C$56,Inputs!$C$3,1) -> 0.35 | D11: =INDEX(D$54:D$56,Inputs!$C$3,1) -> 0.45 | E11: =INDEX(E$54:E$56,Inputs!$C$3,1) -> 0.2 | F11: =SUM(C11:E11) -> 1 | G11: REVISED from 40 / 45 / 15. Focus on the ₹100-500 crore plants in the problem statement. Validate in the first 20 deals.
A12: Cloud/AI load vs average plant | C12: 0.6 | D12: 1 | E12: 1.8 | G12: Relative data volume and solver usage.
A13: Support load vs average plant | C13: 0.7 | D13: 1 | E13: 1.6
A14: Recurring cost to serve per plant (₹ lakh p.a., FY27) | C14: =(Inputs!$C$55+Inputs!$C$56+Inputs!$C$57+Inputs!$C$58+Inputs!$C$59)*12*C12+(Inputs!$C$75/Inputs!$C$64+Inputs!$C$76/Inputs!$C$65)*(1+Inputs!$C$11)*C13 -> 1.66304 | D14: =(Inputs!$C$55+Inputs!$C$56+Inputs!$C$57+Inputs!$C$58+Inputs!$C$59)*12*D12+(Inputs!$C$75/Inputs!$C$64+Inputs!$C$76/Inputs!$C$65)*(1+Inputs!$C$11)*D13 -> 2.6672 | E14: =(Inputs!$C$55+Inputs!$C$56+Inputs!$C$57+Inputs!$C$58+Inputs!$C$59)*12*E12+(Inputs!$C$75/Inputs!$C$64+Inputs!$C$76/Inputs!$C$65)*(1+Inputs!$C$11)*E13 -> 4.67552 | F14: =SUMPRODUCT($C$11:$E$11,C14:E14) -> 2.717408 | G14: Cloud, AI, data, licences, monitoring + allocated customer success & support. Excludes shared fixed platform cost.
A15: Expected SaaS gross margin per tier | C15: =IFERROR(1-C14/C8,0) -> 0.88913067 | D15: =IFERROR(1-D14/D8,0) -> 0.91109333 | E15: =IFERROR(1-E14/E8,0) -> 0.9064896 | F15: =IFERROR(1-F14/F8,0) -> 0.90548146 | G15: Before shared platform cost. Essential is thin: the tier exists to land, not to earn.
A16: Support requirements | C16: Business-hours remote support; quarterly review | D16: Named CSM; monthly value review; shift-hour support | E16: Dedicated CSM; SLA; quarterly executive review
A17: Upselling path | C17: Upgrade to Professional once alerts prove reliable | D17: Add lines/machines; move to Enterprise for ERP sync | E17: Roll out to sister plants; group contract
A18: Mix check (must equal 100%) | C18: =IF(ABS(F11-1)<0.0001,"OK","MIX ≠ 100%") -> OK
A20: Other revenue streams evaluated
A21: Stream | C21: In model? | D21: How modelled | G21: Why
A22: Annual SaaS subscription per plant | C22: Yes | D22: ARR per live plant by tier | G22: Core recurring revenue; only this counts in ARR.
A23: One-time implementation & integration fee | C23: Yes | D23: Recognised at go-live | G23: Excluded from ARR. Priced to recover deployment cost, including SI partner fees, at about an IT-services margin (≈40% services gross margin, 5_Cost_of_Service).
A24: Paid pilots | C24: Yes | D24: Recognised over pilot months | G24: Paid pilots filter serious buyers. Not ARR.
A25: Machine / line add-ons | C25: Partly | D25: Inside expansion % of ARR | G25: Captured as upsell rather than a separate meter, to keep pricing simple.
A26: Premium analytics modules | C26: Partly | D26: Inside expansion % of ARR | G26: Not specified until core product is proven.
A27: Multi-plant enterprise contracts | C27: Partly | D27: Enterprise tier + enterprise account managers | G27: Upside once a group adopts at one plant.
A28: Gain-share (performance-linked) fee | C28: Yes, haircut | D28: Inputs section K; zero in bear | G28: Separate revenue line; never in ARR; expected value after a collection haircut.
A29: IoT kit resale | C29: Yes | D29: Other operating revenue at go-live | G29: Pass-through at 10% markup; only for plants without readable machine data.
A31: Pricing unit: which structure fits mid-sized Indian plants?
A32: Structure | C32: For | D32: Against | E32: Fit | G32: Verdict
A33: Per plant (flat) | C33: Simple budget line; easy to approve | D33: Under-charges large plants, over-charges small ones | E33: Medium | G33: Use as the platform base.
A34: Per machine | C34: Scales with value; common in OEE tools ($30-150/machine/month) | D34: Buyers limit coverage to save money, which weakens the optimiser | E34: Low | G34: Avoid as the primary meter.
A35: Per production line | C35: Matches how plants think about capacity | D35: Line definitions vary; hard to audit | E35: Medium | G35: Use as a tier boundary only.
A36: Hybrid: per-plant tier with machine/line bands | C36: Predictable price; still scales with plant size | D36: Needs clear band rules | E36: High | G36: RECOMMENDED
A38: Price benchmarks (context only; products are not directly comparable)
A39: Benchmark | C39: Published price | D39: Unit | E39: ₹ lakh per year (converted) | F39: Source type | G39: Comparability
A40: OEE / production monitoring software (market range) | C40: $30-150 | D40: per machine per month | E40: =30*12*Inputs!$C$9/100000*20 -> 6.84 | F40: Vendor blog (TeepTrak, Aug 2026) | G40: ₹ figure = low end x 20 machines. Monitoring only, no optimisation.
A41: OEE software, mid-market tier | C41: $200-450 | D41: per machine per month | E41: =200*12*Inputs!$C$9/100000*20 -> 45.6 | F41: Vendor blog (Fabrico 2026) | G41: ₹ figure = low end x 20 machines. Western pricing; Indian buyers will push lower.
A42: OEE site licence | C42: $1,500-8,000 | D42: per site per month | E42: =1500*12*Inputs!$C$9/100000 -> 17.1 | F42: Vendor blog (Fabrico 2026) | G42: ₹ figure = low end.
A43: PlanetTogether Essential APS | C43: $1,000 | D43: per plant per month, billed annually | E43: =1000*12*Inputs!$C$9/100000 -> 11.4 | F43: Third-party listing (FitGap) | G43: Scheduling only; closest analogue to the Professional tier.
A44: Siemens Opcenter APS | C44: from $20,000 | D44: per organisation licence + 18-22% maintenance | E44: =20000*Inputs!$C$9/100000 -> 19 | F44: Third-party estimate (ITQlick) | G44: Perpetual licence; enterprise buyer.
A45: Augury, PTC ThingWorx | C45: Not published | D45: quote-based | F45: No public pricing found | G45: Do not cite a number.
A47: SCENARIO PRICING HYPOTHESES (v4, 11-Oct-2026): average realised annual subscription per plant, FY27, ₹ lakh. Not validated market prices.
A48: Item | C48: Starter | D48: Professional | E48: Enterprise | F48: Blended (mix-weighted) | G48: Type / note
A49: Stated price range: low | C49: 12 | D49: 24 | E49: 40 | G49: Team hypothesis (ranges ₹12-18 / 24-36 / 40-60+ lakh).
A50: Stated price range: high | C50: 18 | D50: 36 | E50: 60 | G50: Enterprise is open-ended above ₹60 lakh (multi-plant deals).
A51: Bear: average realised price | C51: 12 | D51: 24 | E51: 40 | F51: =SUMPRODUCT(C51:E51,C54:E54) -> 19.6 | G51: Low end of each range. Blended = average realised new-customer price.
A52: Base: average realised price | C52: 15 | D52: 30 | E52: 50 | F52: =SUMPRODUCT(C52:E52,C55:E55) -> 28.75 | G52: Midpoints.
A53: Bull: average realised price | C53: 18 | D53: 36 | E53: 60 | F53: =SUMPRODUCT(C53:E53,C56:E56) -> 38.7 | G53: High end of each range.
A54: Bear: share of new customers | C54: 0.5 | D54: 0.4 | E54: 0.1 | F54: =SUM(C54:E54) -> 1 | G54: Skews to Starter.
A55: Base: share of new customers | C55: 0.35 | D55: 0.45 | E55: 0.2 | F55: =SUM(C55:E55) -> 1
A56: Bull: share of new customers | C56: 0.25 | D56: 0.45 | E56: 0.3 | F56: =SUM(C56:E56) -> 1
A57: Check: realised prices inside the stated ranges; each mix sums to 100% | C57: =IF(AND(SUMPRODUCT((C51:E53<C$49:E$49)*1)=0,SUMPRODUCT((C51:E53>C$50:E$50)*1)=0,ABS(F54-1)<0.0001,ABS(F55-1)<0.0001,ABS(F56-1)<0.0001),"OK","CHECK") -> OK
A58: Prices escalate at the list-price escalation on Inputs (5% a year) from FY27. Base Professional (₹30 lakh) is ~2.6x the PlanetTogether Essential APS listing (₹11.4 lakh, row 43): a large premium for an unproven vendor. Flagged on 16_SOM_Scenarios.

Sheet 4_Revenue_Build
A1: 4. CUSTOMER ACQUISITION & REVENUE BUILD (annual view of the monthly engine)
A2: Funnel → pilots → contracts → implementation → go-live → billing. Pilots are never counted as paying customers or ARR.
A3: ₹ lakh | B3: Unit | C3: =INDEX(Engine_Monthly!$D$10:$BK$10,1,12) -> FY27 | D3: =INDEX(Engine_Monthly!$D$10:$BK$10,1,24) -> FY28 | E3: =INDEX(Engine_Monthly!$D$10:$BK$10,1,36) -> FY29 | F3: =INDEX(Engine_Monthly!$D$10:$BK$10,1,48) -> FY30 | G3: =INDEX(Engine_Monthly!$D$10:$BK$10,1,60) -> FY31
A4: Fiscal-year index | C4: 1 | D4: 2 | E4: 3 | F4: 4 | G4: 5
A6: FUNNEL
A7: Target accounts engaged (back-solved) | B7: # | C7: =SUMIF(Engine_Monthly!$D$7:$BK$7,C$4,Engine_Monthly!$D$22:$BK$22) -> 750 | D7: =SUMIF(Engine_Monthly!$D$7:$BK$7,D$4,Engine_Monthly!$D$22:$BK$22) -> 4809.6134 | E7: =SUMIF(Engine_Monthly!$D$7:$BK$7,E$4,Engine_Monthly!$D$22:$BK$22) -> 12538.84 | F7: =SUMIF(Engine_Monthly!$D$7:$BK$7,F$4,Engine_Monthly!$D$22:$BK$22) -> 22038.067 | G7: =SUMIF(Engine_Monthly!$D$7:$BK$7,G$4,Engine_Monthly!$D$22:$BK$22) -> 31267.294
A8: Leads generated (back-solved) | B8: # | C8: =SUMIF(Engine_Monthly!$D$7:$BK$7,C$4,Engine_Monthly!$D$21:$BK$21) -> 187.5 | D8: =SUMIF(Engine_Monthly!$D$7:$BK$7,D$4,Engine_Monthly!$D$21:$BK$21) -> 1202.4034 | E8: =SUMIF(Engine_Monthly!$D$7:$BK$7,E$4,Engine_Monthly!$D$21:$BK$21) -> 3134.7101 | F8: =SUMIF(Engine_Monthly!$D$7:$BK$7,F$4,Engine_Monthly!$D$21:$BK$21) -> 5509.5168 | G8: =SUMIF(Engine_Monthly!$D$7:$BK$7,G$4,Engine_Monthly!$D$21:$BK$21) -> 7816.8235
A9: Qualified opportunities | B9: # | C9: =SUMIF(Engine_Monthly!$D$7:$BK$7,C$4,Engine_Monthly!$D$20:$BK$20) -> 37.5 | D9: =SUMIF(Engine_Monthly!$D$7:$BK$7,D$4,Engine_Monthly!$D$20:$BK$20) -> 240.48067 | E9: =SUMIF(Engine_Monthly!$D$7:$BK$7,E$4,Engine_Monthly!$D$20:$BK$20) -> 626.94202 | F9: =SUMIF(Engine_Monthly!$D$7:$BK$7,F$4,Engine_Monthly!$D$20:$BK$20) -> 1101.9034 | G9: =SUMIF(Engine_Monthly!$D$7:$BK$7,G$4,Engine_Monthly!$D$20:$BK$20) -> 1563.3647
A10: of which partner-sourced | B10: # | C10: =SUMIF(Engine_Monthly!$D$7:$BK$7,C$4,Engine_Monthly!$D$19:$BK$19) -> 0 | D10: =SUMIF(Engine_Monthly!$D$7:$BK$7,D$4,Engine_Monthly!$D$19:$BK$19) -> 100.98067 | E10: =SUMIF(Engine_Monthly!$D$7:$BK$7,E$4,Engine_Monthly!$D$19:$BK$19) -> 302.94202 | F10: =SUMIF(Engine_Monthly!$D$7:$BK$7,F$4,Engine_Monthly!$D$19:$BK$19) -> 504.90336 | G10: =SUMIF(Engine_Monthly!$D$7:$BK$7,G$4,Engine_Monthly!$D$19:$BK$19) -> 706.8647
A11: Paid pilots started | B11: # | C11: =SUMIF(Engine_Monthly!$D$7:$BK$7,C$4,Engine_Monthly!$D$26:$BK$26) -> 7.2 | D11: =SUMIF(Engine_Monthly!$D$7:$BK$7,D$4,Engine_Monthly!$D$26:$BK$26) -> 60.257426 | E11: =SUMIF(Engine_Monthly!$D$7:$BK$7,E$4,Engine_Monthly!$D$26:$BK$26) -> 170.03309 | F11: =SUMIF(Engine_Monthly!$D$7:$BK$7,F$4,Engine_Monthly!$D$26:$BK$26) -> 316.54456 | G11: =SUMIF(Engine_Monthly!$D$7:$BK$7,G$4,Engine_Monthly!$D$26:$BK$26) -> 467.78103
A12: Active pilots at year end (not customers) | B12: # | C12: =INDEX(Engine_Monthly!$D$28:$BK$28,1,C$4*12) -> 3.6 | D12: =INDEX(Engine_Monthly!$D$28:$BK$28,1,D$4*12) -> 20.985809 | E12: =INDEX(Engine_Monthly!$D$28:$BK$28,1,E$4*12) -> 54.182426 | F12: =INDEX(Engine_Monthly!$D$28:$BK$28,1,F$4*12) -> 93.454044 | G12: =INDEX(Engine_Monthly!$D$28:$BK$28,1,G$4*12) -> 130.02566
A13: Commercial contracts signed (new paying customers) | B13: # | C13: =SUMIF(Engine_Monthly!$D$7:$BK$7,C$4,Engine_Monthly!$D$32:$BK$32) -> 1.98 | D13: =SUMIF(Engine_Monthly!$D$7:$BK$7,D$4,Engine_Monthly!$D$32:$BK$32) -> 23.57939 | E13: =SUMIF(Engine_Monthly!$D$7:$BK$7,E$4,Engine_Monthly!$D$32:$BK$32) -> 75.260059 | F13: =SUMIF(Engine_Monthly!$D$7:$BK$7,F$4,Engine_Monthly!$D$32:$BK$32) -> 152.50012 | G13: =SUMIF(Engine_Monthly!$D$7:$BK$7,G$4,Engine_Monthly!$D$32:$BK$32) -> 237.16518
A14: of which partner-sourced | B14: # | C14: =SUMIF(Engine_Monthly!$D$7:$BK$7,C$4,Engine_Monthly!$D$31:$BK$31) -> 0 | D14: =SUMIF(Engine_Monthly!$D$7:$BK$7,D$4,Engine_Monthly!$D$31:$BK$31) -> 9.7193897 | E14: =SUMIF(Engine_Monthly!$D$7:$BK$7,E$4,Engine_Monthly!$D$31:$BK$31) -> 38.877559 | F14: =SUMIF(Engine_Monthly!$D$7:$BK$7,F$4,Engine_Monthly!$D$31:$BK$31) -> 77.755117 | G14: =SUMIF(Engine_Monthly!$D$7:$BK$7,G$4,Engine_Monthly!$D$31:$BK$31) -> 116.63268
A15: Opportunity-to-go-live elapsed time | B15: months | C15: =Inputs!$C$27+Inputs!$C$126+Inputs!$C$28+Inputs!$C$33 -> 8 | D15: =Inputs!$C$27+Inputs!$C$126+Inputs!$C$28+Inputs!$C$33 -> 8 | E15: =Inputs!$C$27+Inputs!$C$126+Inputs!$C$28+Inputs!$C$33 -> 8 | F15: =Inputs!$C$27+Inputs!$C$126+Inputs!$C$28+Inputs!$C$33 -> 8 | G15: =Inputs!$C$27+Inputs!$C$126+Inputs!$C$28+Inputs!$C$33 -> 8 | H15: Sales cycle + pilot + implementation. The cash cost of this lag is why revenue trails hiring.
A17: DEPLOYMENT & CUSTOMERS
A18: Plants gone live | B18: # | C18: =SUMIF(Engine_Monthly!$D$7:$BK$7,C$4,Engine_Monthly!$D$42:$BK$42) -> 1.0725 | D18: =SUMIF(Engine_Monthly!$D$7:$BK$7,D$4,Engine_Monthly!$D$42:$BK$42) -> 17.039593 | E18: =SUMIF(Engine_Monthly!$D$7:$BK$7,E$4,Engine_Monthly!$D$42:$BK$42) -> 63.335466 | F18: =SUMIF(Engine_Monthly!$D$7:$BK$7,F$4,Engine_Monthly!$D$42:$BK$42) -> 138.26552 | G18: =SUMIF(Engine_Monthly!$D$7:$BK$7,G$4,Engine_Monthly!$D$42:$BK$42) -> 223.67308
A19: Implementation backlog at year end | B19: # | C19: =INDEX(Engine_Monthly!$D$43:$BK$43,1,C$4*12) -> 0 | D19: =INDEX(Engine_Monthly!$D$43:$BK$43,1,D$4*12) -> 0 | E19: =INDEX(Engine_Monthly!$D$43:$BK$43,1,E$4*12) -> 0 | F19: =INDEX(Engine_Monthly!$D$43:$BK$43,1,F$4*12) -> 0 | G19: =INDEX(Engine_Monthly!$D$43:$BK$43,1,G$4*12) -> 0 | H19: Non-zero means deployment capacity is binding.
A20: Plants churned | B20: # | C20: =SUMIF(Engine_Monthly!$D$7:$BK$7,C$4,Engine_Monthly!$D$48:$BK$48) -> 0.011564652 | D20: =SUMIF(Engine_Monthly!$D$7:$BK$7,D$4,Engine_Monthly!$D$48:$BK$48) -> 0.50193751 | E20: =SUMIF(Engine_Monthly!$D$7:$BK$7,E$4,Engine_Monthly!$D$48:$BK$48) -> 3.6844616 | F20: =SUMIF(Engine_Monthly!$D$7:$BK$7,F$4,Engine_Monthly!$D$48:$BK$48) -> 12.115088 | G20: =SUMIF(Engine_Monthly!$D$7:$BK$7,G$4,Engine_Monthly!$D$48:$BK$48) -> 27.073106
A21: Live paying plants at year end | B21: # | C21: =INDEX(Engine_Monthly!$D$49:$BK$49,1,C$4*12) -> 1.0609353 | D21: =INDEX(Engine_Monthly!$D$49:$BK$49,1,D$4*12) -> 17.598591 | E21: =INDEX(Engine_Monthly!$D$49:$BK$49,1,E$4*12) -> 77.249595 | F21: =INDEX(Engine_Monthly!$D$49:$BK$49,1,F$4*12) -> 203.40003 | G21: =INDEX(Engine_Monthly!$D$49:$BK$49,1,G$4*12) -> 400.00001
A22: Average live paying plants | B22: # | C22: =AVERAGEIF(Engine_Monthly!$D$7:$BK$7,C$4,Engine_Monthly!$D$49:$BK$49) -> 0.2115167 | D22: =AVERAGEIF(Engine_Monthly!$D$7:$BK$7,D$4,Engine_Monthly!$D$49:$BK$49) -> 6.7212498 | E22: =AVERAGEIF(Engine_Monthly!$D$7:$BK$7,E$4,Engine_Monthly!$D$49:$BK$49) -> 44.191916 | F22: =AVERAGEIF(Engine_Monthly!$D$7:$BK$7,F$4,Engine_Monthly!$D$49:$BK$49) -> 139.47733 | G22: =AVERAGEIF(Engine_Monthly!$D$7:$BK$7,G$4,Engine_Monthly!$D$49:$BK$49) -> 304.57585
A23: Critical machines covered | B23: # | C23: =C21*Inputs!$C$42 -> 21.218707 | D23: =D21*Inputs!$C$42 -> 351.97182 | E23: =E21*Inputs!$C$42 -> 1544.9919 | F23: =F21*Inputs!$C$42 -> 4068.0006 | G23: =G21*Inputs!$C$42 -> 8000.0002 | H23: Live plants × machines per plant (Inputs).
A25: ARR & CONTRACT VALUE (subscription only; excludes one-time fees)
A26: Opening ARR | B26: ₹ lakh | C26: =0 -> 0 | D26: =C30 -> 30.996799 | E26: =D30 -> 552.94498 | F26: =E30 -> 2619.6435 | G26: =F30 -> 7429.6244
A27: + New plants | B27: ₹ lakh | C27: =SUMIF(Engine_Monthly!$D$7:$BK$7,C$4,Engine_Monthly!$D$55:$BK$55) -> 30.834375 | D27: =SUMIF(Engine_Monthly!$D$7:$BK$7,D$4,Engine_Monthly!$D$55:$BK$55) -> 514.38272 | E27: =SUMIF(Engine_Monthly!$D$7:$BK$7,E$4,Engine_Monthly!$D$55:$BK$55) -> 2007.5363 | F27: =SUMIF(Engine_Monthly!$D$7:$BK$7,F$4,Engine_Monthly!$D$55:$BK$55) -> 4601.7143 | G27: =SUMIF(Engine_Monthly!$D$7:$BK$7,G$4,Engine_Monthly!$D$55:$BK$55) -> 7816.4359
A28: + Expansion & escalation | B28: ₹ lakh | C28: =SUMIF(Engine_Monthly!$D$7:$BK$7,C$4,Engine_Monthly!$D$54:$BK$54) -> 0.49749492 | D28: =SUMIF(Engine_Monthly!$D$7:$BK$7,D$4,Engine_Monthly!$D$54:$BK$54) -> 23.172571 | E28: =SUMIF(Engine_Monthly!$D$7:$BK$7,E$4,Engine_Monthly!$D$54:$BK$54) -> 181.21016 | F28: =SUMIF(Engine_Monthly!$D$7:$BK$7,F$4,Engine_Monthly!$D$54:$BK$54) -> 637.90821 | G28: =SUMIF(Engine_Monthly!$D$7:$BK$7,G$4,Engine_Monthly!$D$54:$BK$54) -> 1530.6059
A29: − Churned | B29: ₹ lakh | C29: =-SUMIF(Engine_Monthly!$D$7:$BK$7,C$4,Engine_Monthly!$D$53:$BK$53) -> -0.33507096 | D29: =-SUMIF(Engine_Monthly!$D$7:$BK$7,D$4,Engine_Monthly!$D$53:$BK$53) -> -15.607105 | E29: =-SUMIF(Engine_Monthly!$D$7:$BK$7,E$4,Engine_Monthly!$D$53:$BK$53) -> -122.048 | F29: =-SUMIF(Engine_Monthly!$D$7:$BK$7,F$4,Engine_Monthly!$D$53:$BK$53) -> -429.64161 | G29: =-SUMIF(Engine_Monthly!$D$7:$BK$7,G$4,Engine_Monthly!$D$53:$BK$53) -> -1030.8881
A30: Closing ARR | B30: ₹ lakh | C30: =SUM(C26:C29) -> 30.996799 | D30: =SUM(D26:D29) -> 552.94498 | E30: =SUM(E26:E29) -> 2619.6435 | F30: =SUM(F26:F29) -> 7429.6244 | G30: =SUM(G26:G29) -> 15745.778
A31: Check vs engine (should be 0) | B31: ₹ lakh | C31: =ROUND(C30-INDEX(Engine_Monthly!$D$56:$BK$56,1,C$4*12),3) -> 0 | D31: =ROUND(D30-INDEX(Engine_Monthly!$D$56:$BK$56,1,D$4*12),3) -> 0 | E31: =ROUND(E30-INDEX(Engine_Monthly!$D$56:$BK$56,1,E$4*12),3) -> 0 | F31: =ROUND(F30-INDEX(Engine_Monthly!$D$56:$BK$56,1,F$4*12),3) -> 0 | G31: =ROUND(G30-INDEX(Engine_Monthly!$D$56:$BK$56,1,G$4*12),3) -> 0
A32: Closing MRR | B32: ₹ lakh | C32: =INDEX(Engine_Monthly!$D$57:$BK$57,1,C$4*12) -> 2.5830666 | D32: =INDEX(Engine_Monthly!$D$57:$BK$57,1,D$4*12) -> 46.078748 | E32: =INDEX(Engine_Monthly!$D$57:$BK$57,1,E$4*12) -> 218.30362 | F32: =INDEX(Engine_Monthly!$D$57:$BK$57,1,F$4*12) -> 619.13536 | G32: =INDEX(Engine_Monthly!$D$57:$BK$57,1,G$4*12) -> 1312.1482
A33: New-customer ACV (blended list price) | B33: ₹ lakh | C33: =INDEX(Engine_Monthly!$D$50:$BK$50,1,C$4*12) -> 28.75 | D33: =INDEX(Engine_Monthly!$D$50:$BK$50,1,D$4*12) -> 30.1875 | E33: =INDEX(Engine_Monthly!$D$50:$BK$50,1,E$4*12) -> 31.696875 | F33: =INDEX(Engine_Monthly!$D$50:$BK$50,1,F$4*12) -> 33.281719 | G33: =INDEX(Engine_Monthly!$D$50:$BK$50,1,G$4*12) -> 34.945805
A34: Average ARR per live plant (year end) | B34: ₹ lakh | C34: =IFERROR(C30/C21,0) -> 29.216482 | D34: =IFERROR(D30/D21,0) -> 31.419844 | E34: =IFERROR(E30/E21,0) -> 33.91142 | F34: =IFERROR(F30/F21,0) -> 36.527154 | G34: =IFERROR(G30/G21,0) -> 39.364444
A35: Renewal rate (1 − logo churn) | B35: % | C35: =1-MIN(0.95,Inputs!$C$50*Inputs!$C$127) -> 0.91 | D35: =1-MIN(0.95,Inputs!$C$50*Inputs!$C$127) -> 0.91 | E35: =1-MIN(0.95,Inputs!$C$50*Inputs!$C$127) -> 0.91 | F35: =1-MIN(0.95,Inputs!$C$50*Inputs!$C$127) -> 0.91 | G35: =1-MIN(0.95,Inputs!$C$50*Inputs!$C$127) -> 0.91
A37: REVENUE BY STREAM (recognised)
A38: Subscription | B38: ₹ lakh | C38: =SUMIF(Engine_Monthly!$D$7:$BK$7,C$4,Engine_Monthly!$D$60:$BK$60) -> 4.8583551 | D38: =SUMIF(Engine_Monthly!$D$7:$BK$7,D$4,Engine_Monthly!$D$60:$BK$60) -> 187.88507 | E38: =SUMIF(Engine_Monthly!$D$7:$BK$7,E$4,Engine_Monthly!$D$60:$BK$60) -> 1385.3103 | F38: =SUMIF(Engine_Monthly!$D$7:$BK$7,F$4,Engine_Monthly!$D$60:$BK$60) -> 4773.9397 | G38: =SUMIF(Engine_Monthly!$D$7:$BK$7,G$4,Engine_Monthly!$D$60:$BK$60) -> 11320.283
A39: Implementation | B39: ₹ lakh | C39: =SUMIF(Engine_Monthly!$D$7:$BK$7,C$4,Engine_Monthly!$D$61:$BK$61) -> 6.595875 | D39: =SUMIF(Engine_Monthly!$D$7:$BK$7,D$4,Engine_Monthly!$D$61:$BK$61) -> 110.03317 | E39: =SUMIF(Engine_Monthly!$D$7:$BK$7,E$4,Engine_Monthly!$D$61:$BK$61) -> 429.43821 | F39: =SUMIF(Engine_Monthly!$D$7:$BK$7,F$4,Engine_Monthly!$D$61:$BK$61) -> 984.36671 | G39: =SUMIF(Engine_Monthly!$D$7:$BK$7,G$4,Engine_Monthly!$D$61:$BK$61) -> 1672.0376
A40: Paid pilots | B40: ₹ lakh | C40: =SUMIF(Engine_Monthly!$D$7:$BK$7,C$4,Engine_Monthly!$D$62:$BK$62) -> 14.75 | D40: =SUMIF(Engine_Monthly!$D$7:$BK$7,D$4,Engine_Monthly!$D$62:$BK$62) -> 136.40539 | E40: =SUMIF(Engine_Monthly!$D$7:$BK$7,E$4,Engine_Monthly!$D$62:$BK$62) -> 397.41887 | F40: =SUMIF(Engine_Monthly!$D$7:$BK$7,F$4,Engine_Monthly!$D$62:$BK$62) -> 758.63505 | G40: =SUMIF(Engine_Monthly!$D$7:$BK$7,G$4,Engine_Monthly!$D$62:$BK$62) -> 1138.9762
A41: IoT kit resale | B41: ₹ lakh | C41: =SUMIF(Engine_Monthly!$D$7:$BK$7,C$4,Engine_Monthly!$D$63:$BK$63) -> 2.0645625 | D41: =SUMIF(Engine_Monthly!$D$7:$BK$7,D$4,Engine_Monthly!$D$63:$BK$63) -> 32.801217 | E41: =SUMIF(Engine_Monthly!$D$7:$BK$7,E$4,Engine_Monthly!$D$63:$BK$63) -> 121.92077 | F41: =SUMIF(Engine_Monthly!$D$7:$BK$7,F$4,Engine_Monthly!$D$63:$BK$63) -> 266.16113 | G41: =SUMIF(Engine_Monthly!$D$7:$BK$7,G$4,Engine_Monthly!$D$63:$BK$63) -> 430.57068
A42: Gain-share (performance-linked; not ARR) | B42: ₹ lakh | C42: =SUMIF(Engine_Monthly!$D$7:$BK$7,C$4,Engine_Monthly!$D$64:$BK$64) -> 0.36883224 | D42: =SUMIF(Engine_Monthly!$D$7:$BK$7,D$4,Engine_Monthly!$D$64:$BK$64) -> 11.720179 | E42: =SUMIF(Engine_Monthly!$D$7:$BK$7,E$4,Engine_Monthly!$D$64:$BK$64) -> 77.059653 | F42: =SUMIF(Engine_Monthly!$D$7:$BK$7,F$4,Engine_Monthly!$D$64:$BK$64) -> 243.2136 | G42: =SUMIF(Engine_Monthly!$D$7:$BK$7,G$4,Engine_Monthly!$D$64:$BK$64) -> 531.10413
A43: Total revenue | B43: ₹ lakh | C43: =SUM(C38:C42) -> 28.637625 | D43: =SUM(D38:D42) -> 478.84504 | E43: =SUM(E38:E42) -> 2411.1478 | F43: =SUM(F38:F42) -> 7026.3162 | G43: =SUM(G38:G42) -> 15092.972
A44: Check vs P&L (should be 0) | B44: ₹ lakh | C44: =ROUND(C43-7_Financials!C11,3) -> 0 | D44: =ROUND(D43-7_Financials!D11,3) -> 0 | E44: =ROUND(E43-7_Financials!E11,3) -> 0 | F44: =ROUND(F43-7_Financials!F11,3) -> 0 | G44: =ROUND(G43-7_Financials!G11,3) -> 0
A45: Recurring subscription share of revenue (gain-share excluded) | B45: % | C45: =IFERROR(C38/C43,0) -> 0.16964937 | D45: =IFERROR(D38/D43,0) -> 0.39237135 | E45: =IFERROR(E38/E43,0) -> 0.57454392 | F45: =IFERROR(F38/F43,0) -> 0.67943707 | G45: =IFERROR(G38/G43,0) -> 0.75003673
A47: REVENUE BY PRICING TIER (subscription, using new-customer mix)
A48: Essential | B48: ₹ lakh | C48: =C38*3_Pricing!$C$11*3_Pricing!$C$8/3_Pricing!$F$8 -> 0.88717789 | D48: =D38*3_Pricing!$C$11*3_Pricing!$C$8/3_Pricing!$F$8 -> 34.309448 | E48: =E38*3_Pricing!$C$11*3_Pricing!$C$8/3_Pricing!$F$8 -> 252.96971 | F48: =F38*3_Pricing!$C$11*3_Pricing!$C$8/3_Pricing!$F$8 -> 871.76291 | G48: =G38*3_Pricing!$C$11*3_Pricing!$C$8/3_Pricing!$F$8 -> 2067.1822
A49: Professional | B49: ₹ lakh | C49: =C38*3_Pricing!$D$11*3_Pricing!$D$8/3_Pricing!$F$8 -> 2.2813146 | D49: =D38*3_Pricing!$D$11*3_Pricing!$D$8/3_Pricing!$F$8 -> 88.224296 | E49: =E38*3_Pricing!$D$11*3_Pricing!$D$8/3_Pricing!$F$8 -> 650.49353 | F49: =F38*3_Pricing!$D$11*3_Pricing!$D$8/3_Pricing!$F$8 -> 2241.676 | G49: =G38*3_Pricing!$D$11*3_Pricing!$D$8/3_Pricing!$F$8 -> 5315.6113
A50: Enterprise | B50: ₹ lakh | C50: =C38*3_Pricing!$E$11*3_Pricing!$E$8/3_Pricing!$F$8 -> 1.6898626 | D50: =D38*3_Pricing!$E$11*3_Pricing!$E$8/3_Pricing!$F$8 -> 65.35133 | E50: =E38*3_Pricing!$E$11*3_Pricing!$E$8/3_Pricing!$F$8 -> 481.84706 | F50: =F38*3_Pricing!$E$11*3_Pricing!$E$8/3_Pricing!$F$8 -> 1660.5008 | G50: =G38*3_Pricing!$E$11*3_Pricing!$E$8/3_Pricing!$F$8 -> 3937.4899
A52: REVENUE BY CUSTOMER COHORT (fiscal year of go-live; subscription revenue)
A53: FY27 cohort | B53: ₹ lakh | C53: =SUMIF(Engine_Monthly!$D$7:$BK$7,1,Engine_Monthly!$D$55:$BK$55)*((1-MIN(0.95,Inputs!$C$50*Inputs!$C$127))*(1+Inputs!$C$49+Inputs!$C$48))^(0-0)*IF(0=0,0.5,1) -> 15.417188 | D53: =SUMIF(Engine_Monthly!$D$7:$BK$7,1,Engine_Monthly!$D$55:$BK$55)*((1-MIN(0.95,Inputs!$C$50*Inputs!$C$127))*(1+Inputs!$C$49+Inputs!$C$48))^(1-0)*IF(1=0,0.5,1) -> 32.268173 | E53: =SUMIF(Engine_Monthly!$D$7:$BK$7,1,Engine_Monthly!$D$55:$BK$55)*((1-MIN(0.95,Inputs!$C$50*Inputs!$C$127))*(1+Inputs!$C$49+Inputs!$C$48))^(2-0)*IF(2=0,0.5,1) -> 33.768644 | F53: =SUMIF(Engine_Monthly!$D$7:$BK$7,1,Engine_Monthly!$D$55:$BK$55)*((1-MIN(0.95,Inputs!$C$50*Inputs!$C$127))*(1+Inputs!$C$49+Inputs!$C$48))^(3-0)*IF(3=0,0.5,1) -> 35.338885 | G53: =SUMIF(Engine_Monthly!$D$7:$BK$7,1,Engine_Monthly!$D$55:$BK$55)*((1-MIN(0.95,Inputs!$C$50*Inputs!$C$127))*(1+Inputs!$C$49+Inputs!$C$48))^(4-0)*IF(4=0,0.5,1) -> 36.982144 | H53: Approximation: cohort's new ARR × annual net retention; half-year convention in the go-live year.
A54: FY28 cohort | B54: ₹ lakh | C54: =0 -> 0 | D54: =SUMIF(Engine_Monthly!$D$7:$BK$7,2,Engine_Monthly!$D$55:$BK$55)*((1-MIN(0.95,Inputs!$C$50*Inputs!$C$127))*(1+Inputs!$C$49+Inputs!$C$48))^(1-1)*IF(1=1,0.5,1) -> 257.19136 | E54: =SUMIF(Engine_Monthly!$D$7:$BK$7,2,Engine_Monthly!$D$55:$BK$55)*((1-MIN(0.95,Inputs!$C$50*Inputs!$C$127))*(1+Inputs!$C$49+Inputs!$C$48))^(2-1)*IF(2=1,0.5,1) -> 538.30151 | F54: =SUMIF(Engine_Monthly!$D$7:$BK$7,2,Engine_Monthly!$D$55:$BK$55)*((1-MIN(0.95,Inputs!$C$50*Inputs!$C$127))*(1+Inputs!$C$49+Inputs!$C$48))^(3-1)*IF(3=1,0.5,1) -> 563.33253 | G54: =SUMIF(Engine_Monthly!$D$7:$BK$7,2,Engine_Monthly!$D$55:$BK$55)*((1-MIN(0.95,Inputs!$C$50*Inputs!$C$127))*(1+Inputs!$C$49+Inputs!$C$48))^(4-1)*IF(4=1,0.5,1) -> 589.5275
A55: FY29 cohort | B55: ₹ lakh | C55: =0 -> 0 | D55: =0 -> 0 | E55: =SUMIF(Engine_Monthly!$D$7:$BK$7,3,Engine_Monthly!$D$55:$BK$55)*((1-MIN(0.95,Inputs!$C$50*Inputs!$C$127))*(1+Inputs!$C$49+Inputs!$C$48))^(2-2)*IF(2=2,0.5,1) -> 1003.7682 | F55: =SUMIF(Engine_Monthly!$D$7:$BK$7,3,Engine_Monthly!$D$55:$BK$55)*((1-MIN(0.95,Inputs!$C$50*Inputs!$C$127))*(1+Inputs!$C$49+Inputs!$C$48))^(3-2)*IF(3=2,0.5,1) -> 2100.8868 | G55: =SUMIF(Engine_Monthly!$D$7:$BK$7,3,Engine_Monthly!$D$55:$BK$55)*((1-MIN(0.95,Inputs!$C$50*Inputs!$C$127))*(1+Inputs!$C$49+Inputs!$C$48))^(4-2)*IF(4=2,0.5,1) -> 2198.578
A56: FY30 cohort | B56: ₹ lakh | C56: =0 -> 0 | D56: =0 -> 0 | E56: =0 -> 0 | F56: =SUMIF(Engine_Monthly!$D$7:$BK$7,4,Engine_Monthly!$D$55:$BK$55)*((1-MIN(0.95,Inputs!$C$50*Inputs!$C$127))*(1+Inputs!$C$49+Inputs!$C$48))^(3-3)*IF(3=3,0.5,1) -> 2300.8571 | G56: =SUMIF(Engine_Monthly!$D$7:$BK$7,4,Engine_Monthly!$D$55:$BK$55)*((1-MIN(0.95,Inputs!$C$50*Inputs!$C$127))*(1+Inputs!$C$49+Inputs!$C$48))^(4-3)*IF(4=3,0.5,1) -> 4815.694
A57: FY31 cohort | B57: ₹ lakh | C57: =0 -> 0 | D57: =0 -> 0 | E57: =0 -> 0 | F57: =0 -> 0 | G57: =SUMIF(Engine_Monthly!$D$7:$BK$7,5,Engine_Monthly!$D$55:$BK$55)*((1-MIN(0.95,Inputs!$C$50*Inputs!$C$127))*(1+Inputs!$C$49+Inputs!$C$48))^(4-4)*IF(4=4,0.5,1) -> 3908.2179
A58: Sum of cohorts (approximate) | B58: ₹ lakh | C58: =SUM(C53:C57) -> 15.417188 | D58: =SUM(D53:D57) -> 289.45953 | E58: =SUM(E53:E57) -> 1575.8383 | F58: =SUM(F53:F57) -> 5000.4153 | G58: =SUM(G53:G57) -> 11549 | H58: Differs slightly from recognised revenue because of monthly timing; for illustration.

Sheet 5_Cost_of_Service
A1: 5. COST OF SERVICE & GROSS MARGIN
A2: Recurring cost to serve vs one-time implementation cost, shown separately.
A3: ₹ lakh | B3: Unit | C3: =INDEX(Engine_Monthly!$D$10:$BK$10,1,12) -> FY27 | D3: =INDEX(Engine_Monthly!$D$10:$BK$10,1,24) -> FY28 | E3: =INDEX(Engine_Monthly!$D$10:$BK$10,1,36) -> FY29 | F3: =INDEX(Engine_Monthly!$D$10:$BK$10,1,48) -> FY30 | G3: =INDEX(Engine_Monthly!$D$10:$BK$10,1,60) -> FY31
A4: Fiscal-year index | C4: 1 | D4: 2 | E4: 3 | F4: 4 | G4: 5
A6: RECURRING COST TO SERVE (cost of SaaS revenue)
A7: Cloud hosting & compute | B7: ₹ lakh | C7: =SUMIF(Engine_Monthly!$D$7:$BK$7,C$4,Engine_Monthly!$D$70:$BK$70) -> 1.416674 | D7: =SUMIF(Engine_Monthly!$D$7:$BK$7,D$4,Engine_Monthly!$D$70:$BK$70) -> 16.248708 | E7: =SUMIF(Engine_Monthly!$D$7:$BK$7,E$4,Engine_Monthly!$D$70:$BK$70) -> 63.630216 | F7: =SUMIF(Engine_Monthly!$D$7:$BK$7,F$4,Engine_Monthly!$D$70:$BK$70) -> 155.08739 | G7: =SUMIF(Engine_Monthly!$D$7:$BK$7,G$4,Engine_Monthly!$D$70:$BK$70) -> 286.31337
A8: AI inference & solver | B8: ₹ lakh | C8: =SUMIF(Engine_Monthly!$D$7:$BK$7,C$4,Engine_Monthly!$D$71:$BK$71) -> 0.60714601 | D8: =SUMIF(Engine_Monthly!$D$7:$BK$7,D$4,Engine_Monthly!$D$71:$BK$71) -> 6.9637318 | E8: =SUMIF(Engine_Monthly!$D$7:$BK$7,E$4,Engine_Monthly!$D$71:$BK$71) -> 27.270093 | F8: =SUMIF(Engine_Monthly!$D$7:$BK$7,F$4,Engine_Monthly!$D$71:$BK$71) -> 66.466026 | G8: =SUMIF(Engine_Monthly!$D$7:$BK$7,G$4,Engine_Monthly!$D$71:$BK$71) -> 122.70573
A9: Industrial data ingestion & storage | B9: ₹ lakh | C9: =SUMIF(Engine_Monthly!$D$7:$BK$7,C$4,Engine_Monthly!$D$72:$BK$72) -> 0.40476401 | D9: =SUMIF(Engine_Monthly!$D$7:$BK$7,D$4,Engine_Monthly!$D$72:$BK$72) -> 4.6424879 | E9: =SUMIF(Engine_Monthly!$D$7:$BK$7,E$4,Engine_Monthly!$D$72:$BK$72) -> 18.180062 | F9: =SUMIF(Engine_Monthly!$D$7:$BK$7,F$4,Engine_Monthly!$D$72:$BK$72) -> 44.310684 | G9: =SUMIF(Engine_Monthly!$D$7:$BK$7,G$4,Engine_Monthly!$D$72:$BK$72) -> 81.803821
A10: Third-party software licences | B10: ₹ lakh | C10: =SUMIF(Engine_Monthly!$D$7:$BK$7,C$4,Engine_Monthly!$D$73:$BK$73) -> 0.50595501 | D10: =SUMIF(Engine_Monthly!$D$7:$BK$7,D$4,Engine_Monthly!$D$73:$BK$73) -> 5.8031099 | E10: =SUMIF(Engine_Monthly!$D$7:$BK$7,E$4,Engine_Monthly!$D$73:$BK$73) -> 22.725077 | F10: =SUMIF(Engine_Monthly!$D$7:$BK$7,F$4,Engine_Monthly!$D$73:$BK$73) -> 55.388355 | G10: =SUMIF(Engine_Monthly!$D$7:$BK$7,G$4,Engine_Monthly!$D$73:$BK$73) -> 102.25478
A11: Model monitoring & retraining | B11: ₹ lakh | C11: =SUMIF(Engine_Monthly!$D$7:$BK$7,C$4,Engine_Monthly!$D$74:$BK$74) -> 0.50595501 | D11: =SUMIF(Engine_Monthly!$D$7:$BK$7,D$4,Engine_Monthly!$D$74:$BK$74) -> 5.8031099 | E11: =SUMIF(Engine_Monthly!$D$7:$BK$7,E$4,Engine_Monthly!$D$74:$BK$74) -> 22.725077 | F11: =SUMIF(Engine_Monthly!$D$7:$BK$7,F$4,Engine_Monthly!$D$74:$BK$74) -> 55.388355 | G11: =SUMIF(Engine_Monthly!$D$7:$BK$7,G$4,Engine_Monthly!$D$74:$BK$74) -> 102.25478
A12: Cybersecurity & data management (fixed) | B12: ₹ lakh | C12: =SUMIF(Engine_Monthly!$D$7:$BK$7,C$4,Engine_Monthly!$D$75:$BK$75) -> 15 | D12: =SUMIF(Engine_Monthly!$D$7:$BK$7,D$4,Engine_Monthly!$D$75:$BK$75) -> 18.9 | E12: =SUMIF(Engine_Monthly!$D$7:$BK$7,E$4,Engine_Monthly!$D$75:$BK$75) -> 19.845 | F12: =SUMIF(Engine_Monthly!$D$7:$BK$7,F$4,Engine_Monthly!$D$75:$BK$75) -> 20.83725 | G12: =SUMIF(Engine_Monthly!$D$7:$BK$7,G$4,Engine_Monthly!$D$75:$BK$75) -> 21.879113
A13: Customer success | B13: ₹ lakh | C13: =SUMIF(Engine_Monthly!$D$7:$BK$7,C$4,Engine_Monthly!$D$78:$BK$78) -> 3.36 | D13: =SUMIF(Engine_Monthly!$D$7:$BK$7,D$4,Engine_Monthly!$D$78:$BK$78) -> 10.8864 | E13: =SUMIF(Engine_Monthly!$D$7:$BK$7,E$4,Engine_Monthly!$D$78:$BK$78) -> 26.453952 | F13: =SUMIF(Engine_Monthly!$D$7:$BK$7,F$4,Engine_Monthly!$D$78:$BK$78) -> 77.24554 | G13: =SUMIF(Engine_Monthly!$D$7:$BK$7,G$4,Engine_Monthly!$D$78:$BK$78) -> 173.70723
A14: Technical support | B14: ₹ lakh | C14: =SUMIF(Engine_Monthly!$D$7:$BK$7,C$4,Engine_Monthly!$D$79:$BK$79) -> 2.24 | D14: =SUMIF(Engine_Monthly!$D$7:$BK$7,D$4,Engine_Monthly!$D$79:$BK$79) -> 7.2576 | E14: =SUMIF(Engine_Monthly!$D$7:$BK$7,E$4,Engine_Monthly!$D$79:$BK$79) -> 15.676416 | F14: =SUMIF(Engine_Monthly!$D$7:$BK$7,F$4,Engine_Monthly!$D$79:$BK$79) -> 43.031762 | G14: =SUMIF(Engine_Monthly!$D$7:$BK$7,G$4,Engine_Monthly!$D$79:$BK$79) -> 97.519849
A15: Total cost of SaaS revenue | B15: ₹ lakh | C15: =SUMIF(Engine_Monthly!$D$7:$BK$7,C$4,Engine_Monthly!$D$80:$BK$80) -> 24.040494 | D15: =SUMIF(Engine_Monthly!$D$7:$BK$7,D$4,Engine_Monthly!$D$80:$BK$80) -> 76.505147 | E15: =SUMIF(Engine_Monthly!$D$7:$BK$7,E$4,Engine_Monthly!$D$80:$BK$80) -> 216.50589 | F15: =SUMIF(Engine_Monthly!$D$7:$BK$7,F$4,Engine_Monthly!$D$80:$BK$80) -> 517.75536 | G15: =SUMIF(Engine_Monthly!$D$7:$BK$7,G$4,Engine_Monthly!$D$80:$BK$80) -> 988.43867
A16: SaaS revenue (subscription only; gain-share excluded) | B16: ₹ lakh | C16: =SUMIF(Engine_Monthly!$D$7:$BK$7,C$4,Engine_Monthly!$D$60:$BK$60) -> 4.8583551 | D16: =SUMIF(Engine_Monthly!$D$7:$BK$7,D$4,Engine_Monthly!$D$60:$BK$60) -> 187.88507 | E16: =SUMIF(Engine_Monthly!$D$7:$BK$7,E$4,Engine_Monthly!$D$60:$BK$60) -> 1385.3103 | F16: =SUMIF(Engine_Monthly!$D$7:$BK$7,F$4,Engine_Monthly!$D$60:$BK$60) -> 4773.9397 | G16: =SUMIF(Engine_Monthly!$D$7:$BK$7,G$4,Engine_Monthly!$D$60:$BK$60) -> 11320.283
A17: SaaS gross margin | B17: % | C17: =IFERROR(1-C15/C16,0) -> -3.9482785 | D17: =IFERROR(1-D15/D16,0) -> 0.59280881 | E17: =IFERROR(1-E15/E16,0) -> 0.84371307 | F17: =IFERROR(1-F15/F16,0) -> 0.89154548 | G17: =IFERROR(1-G15/G16,0) -> 0.91268428
A18: Recurring cost to serve per average live plant | B18: ₹ lakh | C18: =IF(AVERAGEIF(Engine_Monthly!$D$7:$BK$7,C$4,Engine_Monthly!$D$49:$BK$49)<3,"n.m.",C15/AVERAGEIF(Engine_Monthly!$D$7:$BK$7,C$4,Engine_Monthly!$D$49:$BK$49)) -> n.m. | D18: =IF(AVERAGEIF(Engine_Monthly!$D$7:$BK$7,D$4,Engine_Monthly!$D$49:$BK$49)<3,"n.m.",D15/AVERAGEIF(Engine_Monthly!$D$7:$BK$7,D$4,Engine_Monthly!$D$49:$BK$49)) -> 11.382578 | E18: =IF(AVERAGEIF(Engine_Monthly!$D$7:$BK$7,E$4,Engine_Monthly!$D$49:$BK$49)<3,"n.m.",E15/AVERAGEIF(Engine_Monthly!$D$7:$BK$7,E$4,Engine_Monthly!$D$49:$BK$49)) -> 4.8992194 | F18: =IF(AVERAGEIF(Engine_Monthly!$D$7:$BK$7,F$4,Engine_Monthly!$D$49:$BK$49)<3,"n.m.",F15/AVERAGEIF(Engine_Monthly!$D$7:$BK$7,F$4,Engine_Monthly!$D$49:$BK$49)) -> 3.7121112 | G18: =IF(AVERAGEIF(Engine_Monthly!$D$7:$BK$7,G$4,Engine_Monthly!$D$49:$BK$49)<3,"n.m.",G15/AVERAGEIF(Engine_Monthly!$D$7:$BK$7,G$4,Engine_Monthly!$D$49:$BK$49)) -> 3.2452957
A20: ONE-TIME DEPLOYMENT COST (implementation & pilots)
A21: Implementation engineers (salaries) | B21: ₹ lakh | C21: =SUMIF(Engine_Monthly!$D$7:$BK$7,C$4,Engine_Monthly!$D$81:$BK$81) -> 9.3333333 | D21: =SUMIF(Engine_Monthly!$D$7:$BK$7,D$4,Engine_Monthly!$D$81:$BK$81) -> 47.376 | E21: =SUMIF(Engine_Monthly!$D$7:$BK$7,E$4,Engine_Monthly!$D$81:$BK$81) -> 141.5232 | F21: =SUMIF(Engine_Monthly!$D$7:$BK$7,F$4,Engine_Monthly!$D$81:$BK$81) -> 296.28426 | G21: =SUMIF(Engine_Monthly!$D$7:$BK$7,G$4,Engine_Monthly!$D$81:$BK$81) -> 487.59924
A22: On-site deployment, integration, travel, pilot costs | B22: ₹ lakh | C22: =SUMIF(Engine_Monthly!$D$7:$BK$7,C$4,Engine_Monthly!$D$82:$BK$82) -> 9.88125 | D22: =SUMIF(Engine_Monthly!$D$7:$BK$7,D$4,Engine_Monthly!$D$82:$BK$82) -> 107.99923 | E22: =SUMIF(Engine_Monthly!$D$7:$BK$7,E$4,Engine_Monthly!$D$82:$BK$82) -> 362.02986 | F22: =SUMIF(Engine_Monthly!$D$7:$BK$7,F$4,Engine_Monthly!$D$82:$BK$82) -> 766.58896 | G22: =SUMIF(Engine_Monthly!$D$7:$BK$7,G$4,Engine_Monthly!$D$82:$BK$82) -> 1248.2808
A23: Total cost of implementation & pilot revenue | B23: ₹ lakh | C23: =SUMIF(Engine_Monthly!$D$7:$BK$7,C$4,Engine_Monthly!$D$83:$BK$83) -> 19.214583 | D23: =SUMIF(Engine_Monthly!$D$7:$BK$7,D$4,Engine_Monthly!$D$83:$BK$83) -> 155.37523 | E23: =SUMIF(Engine_Monthly!$D$7:$BK$7,E$4,Engine_Monthly!$D$83:$BK$83) -> 503.55306 | F23: =SUMIF(Engine_Monthly!$D$7:$BK$7,F$4,Engine_Monthly!$D$83:$BK$83) -> 1062.8732 | G23: =SUMIF(Engine_Monthly!$D$7:$BK$7,G$4,Engine_Monthly!$D$83:$BK$83) -> 1735.8801
A24: Implementation + pilot revenue | B24: ₹ lakh | C24: =SUMIF(Engine_Monthly!$D$7:$BK$7,C$4,Engine_Monthly!$D$61:$BK$61)+SUMIF(Engine_Monthly!$D$7:$BK$7,C$4,Engine_Monthly!$D$62:$BK$62) -> 21.345875 | D24: =SUMIF(Engine_Monthly!$D$7:$BK$7,D$4,Engine_Monthly!$D$61:$BK$61)+SUMIF(Engine_Monthly!$D$7:$BK$7,D$4,Engine_Monthly!$D$62:$BK$62) -> 246.43856 | E24: =SUMIF(Engine_Monthly!$D$7:$BK$7,E$4,Engine_Monthly!$D$61:$BK$61)+SUMIF(Engine_Monthly!$D$7:$BK$7,E$4,Engine_Monthly!$D$62:$BK$62) -> 826.85708 | F24: =SUMIF(Engine_Monthly!$D$7:$BK$7,F$4,Engine_Monthly!$D$61:$BK$61)+SUMIF(Engine_Monthly!$D$7:$BK$7,F$4,Engine_Monthly!$D$62:$BK$62) -> 1743.0018 | G24: =SUMIF(Engine_Monthly!$D$7:$BK$7,G$4,Engine_Monthly!$D$61:$BK$61)+SUMIF(Engine_Monthly!$D$7:$BK$7,G$4,Engine_Monthly!$D$62:$BK$62) -> 2811.0138
A25: Services gross margin | B25: % | C25: =IFERROR(1-C23/C24,0) -> 0.099845599 | D25: =IFERROR(1-D23/D24,0) -> 0.36951739 | E25: =IFERROR(1-E23/E24,0) -> 0.39100351 | F25: =IFERROR(1-F23/F24,0) -> 0.3902053 | G25: =IFERROR(1-G23/G24,0) -> 0.38247188
A26: Deployment cost per plant gone live | B26: ₹ lakh | C26: =IFERROR(C23/SUMIF(Engine_Monthly!$D$7:$BK$7,C$4,Engine_Monthly!$D$42:$BK$42),0) -> 17.915695 | D26: =IFERROR(D23/SUMIF(Engine_Monthly!$D$7:$BK$7,D$4,Engine_Monthly!$D$42:$BK$42),0) -> 9.1184824 | E26: =IFERROR(E23/SUMIF(Engine_Monthly!$D$7:$BK$7,E$4,Engine_Monthly!$D$42:$BK$42),0) -> 7.9505701 | F26: =IFERROR(F23/SUMIF(Engine_Monthly!$D$7:$BK$7,F$4,Engine_Monthly!$D$42:$BK$42),0) -> 7.6871891 | G26: =IFERROR(G23/SUMIF(Engine_Monthly!$D$7:$BK$7,G$4,Engine_Monthly!$D$42:$BK$42),0) -> 7.7607912 | H26: Includes pilot costs of prospects that did not convert.
A27: Implementation fee per plant gone live | B27: ₹ lakh | C27: =IFERROR(SUMIF(Engine_Monthly!$D$7:$BK$7,C$4,Engine_Monthly!$D$61:$BK$61)/SUMIF(Engine_Monthly!$D$7:$BK$7,C$4,Engine_Monthly!$D$42:$BK$42),0) -> 6.15 | D27: =IFERROR(SUMIF(Engine_Monthly!$D$7:$BK$7,D$4,Engine_Monthly!$D$61:$BK$61)/SUMIF(Engine_Monthly!$D$7:$BK$7,D$4,Engine_Monthly!$D$42:$BK$42),0) -> 6.4575 | E27: =IFERROR(SUMIF(Engine_Monthly!$D$7:$BK$7,E$4,Engine_Monthly!$D$61:$BK$61)/SUMIF(Engine_Monthly!$D$7:$BK$7,E$4,Engine_Monthly!$D$42:$BK$42),0) -> 6.780375 | F27: =IFERROR(SUMIF(Engine_Monthly!$D$7:$BK$7,F$4,Engine_Monthly!$D$61:$BK$61)/SUMIF(Engine_Monthly!$D$7:$BK$7,F$4,Engine_Monthly!$D$42:$BK$42),0) -> 7.1193938 | G27: =IFERROR(SUMIF(Engine_Monthly!$D$7:$BK$7,G$4,Engine_Monthly!$D$61:$BK$61)/SUMIF(Engine_Monthly!$D$7:$BK$7,G$4,Engine_Monthly!$D$42:$BK$42),0) -> 7.4753634
A29: HARDWARE (optional IoT kit)
A30: IoT kit revenue | B30: ₹ lakh | C30: =SUMIF(Engine_Monthly!$D$7:$BK$7,C$4,Engine_Monthly!$D$63:$BK$63) -> 2.0645625 | D30: =SUMIF(Engine_Monthly!$D$7:$BK$7,D$4,Engine_Monthly!$D$63:$BK$63) -> 32.801217 | E30: =SUMIF(Engine_Monthly!$D$7:$BK$7,E$4,Engine_Monthly!$D$63:$BK$63) -> 121.92077 | F30: =SUMIF(Engine_Monthly!$D$7:$BK$7,F$4,Engine_Monthly!$D$63:$BK$63) -> 266.16113 | G30: =SUMIF(Engine_Monthly!$D$7:$BK$7,G$4,Engine_Monthly!$D$63:$BK$63) -> 430.57068
A31: IoT kit cost | B31: ₹ lakh | C31: =SUMIF(Engine_Monthly!$D$7:$BK$7,C$4,Engine_Monthly!$D$84:$BK$84) -> 1.876875 | D31: =SUMIF(Engine_Monthly!$D$7:$BK$7,D$4,Engine_Monthly!$D$84:$BK$84) -> 29.819288 | E31: =SUMIF(Engine_Monthly!$D$7:$BK$7,E$4,Engine_Monthly!$D$84:$BK$84) -> 110.83706 | F31: =SUMIF(Engine_Monthly!$D$7:$BK$7,F$4,Engine_Monthly!$D$84:$BK$84) -> 241.96467 | G31: =SUMIF(Engine_Monthly!$D$7:$BK$7,G$4,Engine_Monthly!$D$84:$BK$84) -> 391.4279
A32: IoT kit margin | B32: % | C32: =IFERROR(1-C31/C30,0) -> 0.090909091 | D32: =IFERROR(1-D31/D30,0) -> 0.090909091 | E32: =IFERROR(1-E31/E30,0) -> 0.090909091 | F32: =IFERROR(1-F31/F30,0) -> 0.090909091 | G32: =IFERROR(1-G31/G30,0) -> 0.090909091
A34: TOTAL
A35: Total revenue | B35: ₹ lakh | C35: =7_Financials!C11 -> 28.637625 | D35: =7_Financials!D11 -> 478.84504 | E35: =7_Financials!E11 -> 2411.1478 | F35: =7_Financials!F11 -> 7026.3162 | G35: =7_Financials!G11 -> 15092.972
A36: Total cost of revenue | B36: ₹ lakh | C36: =C15+C23+C31 -> 45.131952 | D36: =D15+D23+D31 -> 261.69966 | E36: =E15+E23+E31 -> 830.89601 | F36: =F15+F23+F31 -> 1822.5933 | G36: =G15+G23+G31 -> 3115.7467
A37: Total gross margin | B37: % | C37: =IFERROR(1-C36/C35,0) -> -0.57596702 | D37: =IFERROR(1-D36/D35,0) -> 0.45347733 | E37: =IFERROR(1-E36/E35,0) -> 0.65539399 | F37: =IFERROR(1-F36/F35,0) -> 0.74060472 | G37: =IFERROR(1-G36/G35,0) -> 0.79356308
A38: Check vs P&L cost of revenue (should be 0) | B38: ₹ lakh | C38: =ROUND(C36+7_Financials!C13,3) -> 0 | D38: =ROUND(D36+7_Financials!D13,3) -> 0 | E38: =ROUND(E36+7_Financials!E13,3) -> 0 | F38: =ROUND(F36+7_Financials!F13,3) -> 0 | G38: =ROUND(G36+7_Financials!G13,3) -> 0
A39: Software-like benchmark for SaaS gross margin | B39: % | C39: =0.75 -> 0.75 | D39: =0.75 -> 0.75 | E39: =0.75 -> 0.75 | F39: =0.75 -> 0.75 | G39: =0.75 -> 0.75 | H39: Common investor reference point for B2B SaaS (~75%+); industrial SaaS often lands lower.

Sheet 6_Personnel_Opex
A1: 6. PERSONNEL & OPERATING EXPENSES
A2: Fixed roles follow the hiring plan (Inputs J); implementation, CS, support and pre-sales are driven by workload.
A3: ₹ lakh | B3: Unit | C3: =INDEX(Engine_Monthly!$D$10:$BK$10,1,12) -> FY27 | D3: =INDEX(Engine_Monthly!$D$10:$BK$10,1,24) -> FY28 | E3: =INDEX(Engine_Monthly!$D$10:$BK$10,1,36) -> FY29 | F3: =INDEX(Engine_Monthly!$D$10:$BK$10,1,48) -> FY30 | G3: =INDEX(Engine_Monthly!$D$10:$BK$10,1,60) -> FY31
A4: Fiscal-year index | C4: 1 | D4: 2 | E4: 3 | F4: 4 | G4: 5
A6: YEAR-END HEADCOUNT BY ROLE
A7: Founder: CEO | B7: G&A | C7: =INDEX(Engine_Monthly!$D$89:$BK$89,1,C$4*12) -> 1 | D7: =INDEX(Engine_Monthly!$D$89:$BK$89,1,D$4*12) -> 1 | E7: =INDEX(Engine_Monthly!$D$89:$BK$89,1,E$4*12) -> 1 | F7: =INDEX(Engine_Monthly!$D$89:$BK$89,1,F$4*12) -> 1 | G7: =INDEX(Engine_Monthly!$D$89:$BK$89,1,G$4*12) -> 1
A8: Founder: CTO | B8: R&D | C8: =INDEX(Engine_Monthly!$D$90:$BK$90,1,C$4*12) -> 1 | D8: =INDEX(Engine_Monthly!$D$90:$BK$90,1,D$4*12) -> 1 | E8: =INDEX(Engine_Monthly!$D$90:$BK$90,1,E$4*12) -> 1 | F8: =INDEX(Engine_Monthly!$D$90:$BK$90,1,F$4*12) -> 1 | G8: =INDEX(Engine_Monthly!$D$90:$BK$90,1,G$4*12) -> 1
A9: Founder: Commercial | B9: S&M | C9: =INDEX(Engine_Monthly!$D$91:$BK$91,1,C$4*12) -> 1 | D9: =INDEX(Engine_Monthly!$D$91:$BK$91,1,D$4*12) -> 1 | E9: =INDEX(Engine_Monthly!$D$91:$BK$91,1,E$4*12) -> 1 | F9: =INDEX(Engine_Monthly!$D$91:$BK$91,1,F$4*12) -> 1 | G9: =INDEX(Engine_Monthly!$D$91:$BK$91,1,G$4*12) -> 1
A10: AI/ML engineers | B10: R&D | C10: =INDEX(Engine_Monthly!$D$92:$BK$92,1,C$4*12) -> 1 | D10: =INDEX(Engine_Monthly!$D$92:$BK$92,1,D$4*12) -> 2 | E10: =INDEX(Engine_Monthly!$D$92:$BK$92,1,E$4*12) -> 3 | F10: =INDEX(Engine_Monthly!$D$92:$BK$92,1,F$4*12) -> 4 | G10: =INDEX(Engine_Monthly!$D$92:$BK$92,1,G$4*12) -> 5
A11: Software developers | B11: R&D | C11: =INDEX(Engine_Monthly!$D$93:$BK$93,1,C$4*12) -> 1 | D11: =INDEX(Engine_Monthly!$D$93:$BK$93,1,D$4*12) -> 2 | E11: =INDEX(Engine_Monthly!$D$93:$BK$93,1,E$4*12) -> 3 | F11: =INDEX(Engine_Monthly!$D$93:$BK$93,1,F$4*12) -> 4 | G11: =INDEX(Engine_Monthly!$D$93:$BK$93,1,G$4*12) -> 5
A12: Data engineers | B12: R&D | C12: =INDEX(Engine_Monthly!$D$94:$BK$94,1,C$4*12) -> 0 | D12: =INDEX(Engine_Monthly!$D$94:$BK$94,1,D$4*12) -> 1 | E12: =INDEX(Engine_Monthly!$D$94:$BK$94,1,E$4*12) -> 1 | F12: =INDEX(Engine_Monthly!$D$94:$BK$94,1,F$4*12) -> 2 | G12: =INDEX(Engine_Monthly!$D$94:$BK$94,1,G$4*12) -> 2
A13: Industrial automation engineers | B13: R&D | C13: =INDEX(Engine_Monthly!$D$95:$BK$95,1,C$4*12) -> 1 | D13: =INDEX(Engine_Monthly!$D$95:$BK$95,1,D$4*12) -> 1 | E13: =INDEX(Engine_Monthly!$D$95:$BK$95,1,E$4*12) -> 2 | F13: =INDEX(Engine_Monthly!$D$95:$BK$95,1,F$4*12) -> 2 | G13: =INDEX(Engine_Monthly!$D$95:$BK$95,1,G$4*12) -> 3
A14: Product managers | B14: R&D | C14: =INDEX(Engine_Monthly!$D$96:$BK$96,1,C$4*12) -> 0 | D14: =INDEX(Engine_Monthly!$D$96:$BK$96,1,D$4*12) -> 1 | E14: =INDEX(Engine_Monthly!$D$96:$BK$96,1,E$4*12) -> 1 | F14: =INDEX(Engine_Monthly!$D$96:$BK$96,1,F$4*12) -> 1 | G14: =INDEX(Engine_Monthly!$D$96:$BK$96,1,G$4*12) -> 2
A15: Account executives | B15: S&M | C15: =INDEX(Engine_Monthly!$D$97:$BK$97,1,C$4*12) -> 1 | D15: =INDEX(Engine_Monthly!$D$97:$BK$97,1,D$4*12) -> 4 | E15: =INDEX(Engine_Monthly!$D$97:$BK$97,1,E$4*12) -> 10 | F15: =INDEX(Engine_Monthly!$D$97:$BK$97,1,F$4*12) -> 18 | G15: =INDEX(Engine_Monthly!$D$97:$BK$97,1,G$4*12) -> 25
A16: Pre-sales engineers | B16: S&M | C16: =INDEX(Engine_Monthly!$D$98:$BK$98,1,C$4*12) -> 1 | D16: =INDEX(Engine_Monthly!$D$98:$BK$98,1,D$4*12) -> 2 | E16: =INDEX(Engine_Monthly!$D$98:$BK$98,1,E$4*12) -> 4 | F16: =INDEX(Engine_Monthly!$D$98:$BK$98,1,F$4*12) -> 6 | G16: =INDEX(Engine_Monthly!$D$98:$BK$98,1,G$4*12) -> 9
A17: Marketing | B17: S&M | C17: =INDEX(Engine_Monthly!$D$99:$BK$99,1,C$4*12) -> 0 | D17: =INDEX(Engine_Monthly!$D$99:$BK$99,1,D$4*12) -> 0 | E17: =INDEX(Engine_Monthly!$D$99:$BK$99,1,E$4*12) -> 1 | F17: =INDEX(Engine_Monthly!$D$99:$BK$99,1,F$4*12) -> 1 | G17: =INDEX(Engine_Monthly!$D$99:$BK$99,1,G$4*12) -> 2
A18: Enterprise account managers | B18: S&M | C18: =INDEX(Engine_Monthly!$D$100:$BK$100,1,C$4*12) -> 0 | D18: =INDEX(Engine_Monthly!$D$100:$BK$100,1,D$4*12) -> 0 | E18: =INDEX(Engine_Monthly!$D$100:$BK$100,1,E$4*12) -> 0 | F18: =INDEX(Engine_Monthly!$D$100:$BK$100,1,F$4*12) -> 1 | G18: =INDEX(Engine_Monthly!$D$100:$BK$100,1,G$4*12) -> 1
A19: Finance, HR & admin | B19: G&A | C19: =INDEX(Engine_Monthly!$D$101:$BK$101,1,C$4*12) -> 0 | D19: =INDEX(Engine_Monthly!$D$101:$BK$101,1,D$4*12) -> 1 | E19: =INDEX(Engine_Monthly!$D$101:$BK$101,1,E$4*12) -> 1 | F19: =INDEX(Engine_Monthly!$D$101:$BK$101,1,F$4*12) -> 2 | G19: =INDEX(Engine_Monthly!$D$101:$BK$101,1,G$4*12) -> 2
A20: Cybersecurity & IT | B20: G&A | C20: =INDEX(Engine_Monthly!$D$102:$BK$102,1,C$4*12) -> 0 | D20: =INDEX(Engine_Monthly!$D$102:$BK$102,1,D$4*12) -> 0 | E20: =INDEX(Engine_Monthly!$D$102:$BK$102,1,E$4*12) -> 1 | F20: =INDEX(Engine_Monthly!$D$102:$BK$102,1,F$4*12) -> 1 | G20: =INDEX(Engine_Monthly!$D$102:$BK$102,1,G$4*12) -> 1
A21: Implementation engineers | B21: COGS | C21: =INDEX(Engine_Monthly!$D$38:$BK$38,1,C$4*12) -> 1 | D21: =INDEX(Engine_Monthly!$D$38:$BK$38,1,D$4*12) -> 6 | E21: =INDEX(Engine_Monthly!$D$38:$BK$38,1,E$4*12) -> 16 | F21: =INDEX(Engine_Monthly!$D$38:$BK$38,1,F$4*12) -> 27 | G21: =INDEX(Engine_Monthly!$D$38:$BK$38,1,G$4*12) -> 37 | H21: Sized to pilots + implementations in progress.
A22: Customer success managers | B22: COGS | C22: =INDEX(Engine_Monthly!$D$76:$BK$76,1,C$4*12) -> 1 | D22: =INDEX(Engine_Monthly!$D$76:$BK$76,1,D$4*12) -> 1 | E22: =INDEX(Engine_Monthly!$D$76:$BK$76,1,E$4*12) -> 4 | F22: =INDEX(Engine_Monthly!$D$76:$BK$76,1,F$4*12) -> 9 | G22: =INDEX(Engine_Monthly!$D$76:$BK$76,1,G$4*12) -> 17
A23: Technical support engineers | B23: COGS | C23: =INDEX(Engine_Monthly!$D$77:$BK$77,1,C$4*12) -> 1 | D23: =INDEX(Engine_Monthly!$D$77:$BK$77,1,D$4*12) -> 1 | E23: =INDEX(Engine_Monthly!$D$77:$BK$77,1,E$4*12) -> 3 | F23: =INDEX(Engine_Monthly!$D$77:$BK$77,1,F$4*12) -> 7 | G23: =INDEX(Engine_Monthly!$D$77:$BK$77,1,G$4*12) -> 14
A24: Total headcount | B24: heads | C24: =INDEX(Engine_Monthly!$D$104:$BK$104,1,C$4*12) -> 11 | D24: =INDEX(Engine_Monthly!$D$104:$BK$104,1,D$4*12) -> 25 | E24: =INDEX(Engine_Monthly!$D$104:$BK$104,1,E$4*12) -> 53 | F24: =INDEX(Engine_Monthly!$D$104:$BK$104,1,F$4*12) -> 88 | G24: =INDEX(Engine_Monthly!$D$104:$BK$104,1,G$4*12) -> 128
A25: Net hires in year | B25: heads | C25: =SUMIF(Engine_Monthly!$D$7:$BK$7,C$4,Engine_Monthly!$D$105:$BK$105) -> 11 | D25: =SUMIF(Engine_Monthly!$D$7:$BK$7,D$4,Engine_Monthly!$D$105:$BK$105) -> 14 | E25: =SUMIF(Engine_Monthly!$D$7:$BK$7,E$4,Engine_Monthly!$D$105:$BK$105) -> 28 | F25: =SUMIF(Engine_Monthly!$D$7:$BK$7,F$4,Engine_Monthly!$D$105:$BK$105) -> 35 | G25: =SUMIF(Engine_Monthly!$D$7:$BK$7,G$4,Engine_Monthly!$D$105:$BK$105) -> 40
A27: COMPENSATION ASSUMPTIONS (FY27 CTC, ₹ lakh; on-cost and increments applied in engine)
A28: Founder: CEO | B28: ₹ lakh | C28: =Inputs!$C$68*(1+Inputs!$C$12)^(C$4-1) -> 12 | D28: =Inputs!$C$68*(1+Inputs!$C$12)^(D$4-1) -> 12.96 | E28: =Inputs!$C$68*(1+Inputs!$C$12)^(E$4-1) -> 13.9968 | F28: =Inputs!$C$68*(1+Inputs!$C$12)^(F$4-1) -> 15.116544 | G28: =Inputs!$C$68*(1+Inputs!$C$12)^(G$4-1) -> 16.325868
A29: Founder: CTO | B29: ₹ lakh | C29: =Inputs!$C$68*(1+Inputs!$C$12)^(C$4-1) -> 12 | D29: =Inputs!$C$68*(1+Inputs!$C$12)^(D$4-1) -> 12.96 | E29: =Inputs!$C$68*(1+Inputs!$C$12)^(E$4-1) -> 13.9968 | F29: =Inputs!$C$68*(1+Inputs!$C$12)^(F$4-1) -> 15.116544 | G29: =Inputs!$C$68*(1+Inputs!$C$12)^(G$4-1) -> 16.325868
A30: Founder: Commercial | B30: ₹ lakh | C30: =Inputs!$C$68*(1+Inputs!$C$12)^(C$4-1) -> 12 | D30: =Inputs!$C$68*(1+Inputs!$C$12)^(D$4-1) -> 12.96 | E30: =Inputs!$C$68*(1+Inputs!$C$12)^(E$4-1) -> 13.9968 | F30: =Inputs!$C$68*(1+Inputs!$C$12)^(F$4-1) -> 15.116544 | G30: =Inputs!$C$68*(1+Inputs!$C$12)^(G$4-1) -> 16.325868
A31: AI/ML engineers | B31: ₹ lakh | C31: =Inputs!$C$69*(1+Inputs!$C$12)^(C$4-1) -> 18 | D31: =Inputs!$C$69*(1+Inputs!$C$12)^(D$4-1) -> 19.44 | E31: =Inputs!$C$69*(1+Inputs!$C$12)^(E$4-1) -> 20.9952 | F31: =Inputs!$C$69*(1+Inputs!$C$12)^(F$4-1) -> 22.674816 | G31: =Inputs!$C$69*(1+Inputs!$C$12)^(G$4-1) -> 24.488801
A32: Software developers | B32: ₹ lakh | C32: =Inputs!$C$70*(1+Inputs!$C$12)^(C$4-1) -> 14 | D32: =Inputs!$C$70*(1+Inputs!$C$12)^(D$4-1) -> 15.12 | E32: =Inputs!$C$70*(1+Inputs!$C$12)^(E$4-1) -> 16.3296 | F32: =Inputs!$C$70*(1+Inputs!$C$12)^(F$4-1) -> 17.635968 | G32: =Inputs!$C$70*(1+Inputs!$C$12)^(G$4-1) -> 19.046845
A33: Data engineers | B33: ₹ lakh | C33: =Inputs!$C$71*(1+Inputs!$C$12)^(C$4-1) -> 15 | D33: =Inputs!$C$71*(1+Inputs!$C$12)^(D$4-1) -> 16.2 | E33: =Inputs!$C$71*(1+Inputs!$C$12)^(E$4-1) -> 17.496 | F33: =Inputs!$C$71*(1+Inputs!$C$12)^(F$4-1) -> 18.89568 | G33: =Inputs!$C$71*(1+Inputs!$C$12)^(G$4-1) -> 20.407334
A34: Industrial automation engineers | B34: ₹ lakh | C34: =Inputs!$C$72*(1+Inputs!$C$12)^(C$4-1) -> 12 | D34: =Inputs!$C$72*(1+Inputs!$C$12)^(D$4-1) -> 12.96 | E34: =Inputs!$C$72*(1+Inputs!$C$12)^(E$4-1) -> 13.9968 | F34: =Inputs!$C$72*(1+Inputs!$C$12)^(F$4-1) -> 15.116544 | G34: =Inputs!$C$72*(1+Inputs!$C$12)^(G$4-1) -> 16.325868
A35: Product managers | B35: ₹ lakh | C35: =Inputs!$C$73*(1+Inputs!$C$12)^(C$4-1) -> 24 | D35: =Inputs!$C$73*(1+Inputs!$C$12)^(D$4-1) -> 25.92 | E35: =Inputs!$C$73*(1+Inputs!$C$12)^(E$4-1) -> 27.9936 | F35: =Inputs!$C$73*(1+Inputs!$C$12)^(F$4-1) -> 30.233088 | G35: =Inputs!$C$73*(1+Inputs!$C$12)^(G$4-1) -> 32.651735
A36: Account executives | B36: ₹ lakh | C36: =Inputs!$C$77*(1+Inputs!$C$12)^(C$4-1) -> 14 | D36: =Inputs!$C$77*(1+Inputs!$C$12)^(D$4-1) -> 15.12 | E36: =Inputs!$C$77*(1+Inputs!$C$12)^(E$4-1) -> 16.3296 | F36: =Inputs!$C$77*(1+Inputs!$C$12)^(F$4-1) -> 17.635968 | G36: =Inputs!$C$77*(1+Inputs!$C$12)^(G$4-1) -> 19.046845
A37: Pre-sales engineers | B37: ₹ lakh | C37: =Inputs!$C$78*(1+Inputs!$C$12)^(C$4-1) -> 15 | D37: =Inputs!$C$78*(1+Inputs!$C$12)^(D$4-1) -> 16.2 | E37: =Inputs!$C$78*(1+Inputs!$C$12)^(E$4-1) -> 17.496 | F37: =Inputs!$C$78*(1+Inputs!$C$12)^(F$4-1) -> 18.89568 | G37: =Inputs!$C$78*(1+Inputs!$C$12)^(G$4-1) -> 20.407334
A38: Marketing | B38: ₹ lakh | C38: =Inputs!$C$80*(1+Inputs!$C$12)^(C$4-1) -> 12 | D38: =Inputs!$C$80*(1+Inputs!$C$12)^(D$4-1) -> 12.96 | E38: =Inputs!$C$80*(1+Inputs!$C$12)^(E$4-1) -> 13.9968 | F38: =Inputs!$C$80*(1+Inputs!$C$12)^(F$4-1) -> 15.116544 | G38: =Inputs!$C$80*(1+Inputs!$C$12)^(G$4-1) -> 16.325868
A39: Enterprise account managers | B39: ₹ lakh | C39: =Inputs!$C$79*(1+Inputs!$C$12)^(C$4-1) -> 20 | D39: =Inputs!$C$79*(1+Inputs!$C$12)^(D$4-1) -> 21.6 | E39: =Inputs!$C$79*(1+Inputs!$C$12)^(E$4-1) -> 23.328 | F39: =Inputs!$C$79*(1+Inputs!$C$12)^(F$4-1) -> 25.19424 | G39: =Inputs!$C$79*(1+Inputs!$C$12)^(G$4-1) -> 27.209779
A40: Finance, HR & admin | B40: ₹ lakh | C40: =Inputs!$C$81*(1+Inputs!$C$12)^(C$4-1) -> 8 | D40: =Inputs!$C$81*(1+Inputs!$C$12)^(D$4-1) -> 8.64 | E40: =Inputs!$C$81*(1+Inputs!$C$12)^(E$4-1) -> 9.3312 | F40: =Inputs!$C$81*(1+Inputs!$C$12)^(F$4-1) -> 10.077696 | G40: =Inputs!$C$81*(1+Inputs!$C$12)^(G$4-1) -> 10.883912
A41: Cybersecurity & IT | B41: ₹ lakh | C41: =Inputs!$C$82*(1+Inputs!$C$12)^(C$4-1) -> 20 | D41: =Inputs!$C$82*(1+Inputs!$C$12)^(D$4-1) -> 21.6 | E41: =Inputs!$C$82*(1+Inputs!$C$12)^(E$4-1) -> 23.328 | F41: =Inputs!$C$82*(1+Inputs!$C$12)^(F$4-1) -> 25.19424 | G41: =Inputs!$C$82*(1+Inputs!$C$12)^(G$4-1) -> 27.209779
A42: Hiring timing | H42: Founders from month 1; other FY27 hires from Inputs 'hire_start'; later hires at the start of each FY.
A44: OPERATING EXPENSES BY FUNCTION
A45: R&D people | B45: ₹ lakh | C45: =SUMIF(Engine_Monthly!$D$7:$BK$7,C$4,Engine_Monthly!$D$120:$BK$120) -> 54.506667 | D45: =SUMIF(Engine_Monthly!$D$7:$BK$7,D$4,Engine_Monthly!$D$120:$BK$120) -> 153.6192 | E45: =SUMIF(Engine_Monthly!$D$7:$BK$7,E$4,Engine_Monthly!$D$120:$BK$120) -> 223.38893 | F45: =SUMIF(Engine_Monthly!$D$7:$BK$7,F$4,Engine_Monthly!$D$120:$BK$120) -> 307.57128 | G45: =SUMIF(Engine_Monthly!$D$7:$BK$7,G$4,Engine_Monthly!$D$120:$BK$120) -> 435.79182
A46: R&D tools & dev cloud | B46: ₹ lakh | C46: =SUMIF(Engine_Monthly!$D$7:$BK$7,C$4,Engine_Monthly!$D$130:$BK$130) -> 15.3 | D46: =SUMIF(Engine_Monthly!$D$7:$BK$7,D$4,Engine_Monthly!$D$130:$BK$130) -> 24.57 | E46: =SUMIF(Engine_Monthly!$D$7:$BK$7,E$4,Engine_Monthly!$D$130:$BK$130) -> 31.752 | F46: =SUMIF(Engine_Monthly!$D$7:$BK$7,F$4,Engine_Monthly!$D$130:$BK$130) -> 39.590775 | G46: =SUMIF(Engine_Monthly!$D$7:$BK$7,G$4,Engine_Monthly!$D$130:$BK$130) -> 50.321959
A47: Research & development | B47: ₹ lakh | C47: =SUMIF(Engine_Monthly!$D$7:$BK$7,C$4,Engine_Monthly!$D$131:$BK$131) -> 69.806667 | D47: =SUMIF(Engine_Monthly!$D$7:$BK$7,D$4,Engine_Monthly!$D$131:$BK$131) -> 178.1892 | E47: =SUMIF(Engine_Monthly!$D$7:$BK$7,E$4,Engine_Monthly!$D$131:$BK$131) -> 255.14093 | F47: =SUMIF(Engine_Monthly!$D$7:$BK$7,F$4,Engine_Monthly!$D$131:$BK$131) -> 347.16206 | G47: =SUMIF(Engine_Monthly!$D$7:$BK$7,G$4,Engine_Monthly!$D$131:$BK$131) -> 486.11378
A48: S&M people | B48: ₹ lakh | C48: =SUMIF(Engine_Monthly!$D$7:$BK$7,C$4,Engine_Monthly!$D$121:$BK$121) -> 37.8 | D48: =SUMIF(Engine_Monthly!$D$7:$BK$7,D$4,Engine_Monthly!$D$121:$BK$121) -> 118.5408 | E48: =SUMIF(Engine_Monthly!$D$7:$BK$7,E$4,Engine_Monthly!$D$121:$BK$121) -> 292.62643 | F48: =SUMIF(Engine_Monthly!$D$7:$BK$7,F$4,Engine_Monthly!$D$121:$BK$121) -> 544.59869 | G48: =SUMIF(Engine_Monthly!$D$7:$BK$7,G$4,Engine_Monthly!$D$121:$BK$121) -> 824.34747
A49: Marketing programmes | B49: ₹ lakh | C49: =SUMIF(Engine_Monthly!$D$7:$BK$7,C$4,Engine_Monthly!$D$125:$BK$125) -> 12 | D49: =SUMIF(Engine_Monthly!$D$7:$BK$7,D$4,Engine_Monthly!$D$125:$BK$125) -> 24 | E49: =SUMIF(Engine_Monthly!$D$7:$BK$7,E$4,Engine_Monthly!$D$125:$BK$125) -> 42 | F49: =SUMIF(Engine_Monthly!$D$7:$BK$7,F$4,Engine_Monthly!$D$125:$BK$125) -> 60 | G49: =SUMIF(Engine_Monthly!$D$7:$BK$7,G$4,Engine_Monthly!$D$125:$BK$125) -> 72
A50: Sales travel | B50: ₹ lakh | C50: =SUMIF(Engine_Monthly!$D$7:$BK$7,C$4,Engine_Monthly!$D$126:$BK$126) -> 18 | D50: =SUMIF(Engine_Monthly!$D$7:$BK$7,D$4,Engine_Monthly!$D$126:$BK$126) -> 52.92 | E50: =SUMIF(Engine_Monthly!$D$7:$BK$7,E$4,Engine_Monthly!$D$126:$BK$126) -> 119.07 | F50: =SUMIF(Engine_Monthly!$D$7:$BK$7,F$4,Engine_Monthly!$D$126:$BK$126) -> 216.7074 | G50: =SUMIF(Engine_Monthly!$D$7:$BK$7,G$4,Engine_Monthly!$D$126:$BK$126) -> 315.05922
A51: Commissions (sales + channel) | B51: ₹ lakh | C51: =SUMIF(Engine_Monthly!$D$7:$BK$7,C$4,Engine_Monthly!$D$127:$BK$127) -> 4.554 | D51: =SUMIF(Engine_Monthly!$D$7:$BK$7,D$4,Engine_Monthly!$D$127:$BK$127) -> 92.152715 | E51: =SUMIF(Engine_Monthly!$D$7:$BK$7,E$4,Engine_Monthly!$D$127:$BK$127) -> 338.71635 | F51: =SUMIF(Engine_Monthly!$D$7:$BK$7,F$4,Engine_Monthly!$D$127:$BK$127) -> 716.57616 | G51: =SUMIF(Engine_Monthly!$D$7:$BK$7,G$4,Engine_Monthly!$D$127:$BK$127) -> 1152.133
A52: Partner programme | B52: ₹ lakh | C52: =SUMIF(Engine_Monthly!$D$7:$BK$7,C$4,Engine_Monthly!$D$128:$BK$128) -> 0 | D52: =SUMIF(Engine_Monthly!$D$7:$BK$7,D$4,Engine_Monthly!$D$128:$BK$128) -> 18.9 | E52: =SUMIF(Engine_Monthly!$D$7:$BK$7,E$4,Engine_Monthly!$D$128:$BK$128) -> 19.845 | F52: =SUMIF(Engine_Monthly!$D$7:$BK$7,F$4,Engine_Monthly!$D$128:$BK$128) -> 20.83725 | G52: =SUMIF(Engine_Monthly!$D$7:$BK$7,G$4,Engine_Monthly!$D$128:$BK$128) -> 21.879113
A53: Sales & marketing | B53: ₹ lakh | C53: =SUMIF(Engine_Monthly!$D$7:$BK$7,C$4,Engine_Monthly!$D$129:$BK$129) -> 72.354 | D53: =SUMIF(Engine_Monthly!$D$7:$BK$7,D$4,Engine_Monthly!$D$129:$BK$129) -> 306.51352 | E53: =SUMIF(Engine_Monthly!$D$7:$BK$7,E$4,Engine_Monthly!$D$129:$BK$129) -> 812.25778 | F53: =SUMIF(Engine_Monthly!$D$7:$BK$7,F$4,Engine_Monthly!$D$129:$BK$129) -> 1558.7195 | G53: =SUMIF(Engine_Monthly!$D$7:$BK$7,G$4,Engine_Monthly!$D$129:$BK$129) -> 2385.4188
A54: G&A people | B54: ₹ lakh | C54: =SUMIF(Engine_Monthly!$D$7:$BK$7,C$4,Engine_Monthly!$D$122:$BK$122) -> 13.44 | D54: =SUMIF(Engine_Monthly!$D$7:$BK$7,D$4,Engine_Monthly!$D$122:$BK$122) -> 24.192 | E54: =SUMIF(Engine_Monthly!$D$7:$BK$7,E$4,Engine_Monthly!$D$122:$BK$122) -> 52.25472 | F54: =SUMIF(Engine_Monthly!$D$7:$BK$7,F$4,Engine_Monthly!$D$122:$BK$122) -> 67.722117 | G54: =SUMIF(Engine_Monthly!$D$7:$BK$7,G$4,Engine_Monthly!$D$122:$BK$122) -> 73.139886
A55: Office | B55: ₹ lakh | C55: =SUMIF(Engine_Monthly!$D$7:$BK$7,C$4,Engine_Monthly!$D$132:$BK$132) -> 12.24 | D55: =SUMIF(Engine_Monthly!$D$7:$BK$7,D$4,Engine_Monthly!$D$132:$BK$132) -> 34.65 | E55: =SUMIF(Engine_Monthly!$D$7:$BK$7,E$4,Engine_Monthly!$D$132:$BK$132) -> 71.5743 | F55: =SUMIF(Engine_Monthly!$D$7:$BK$7,F$4,Engine_Monthly!$D$132:$BK$132) -> 128.63529 | G55: =SUMIF(Engine_Monthly!$D$7:$BK$7,G$4,Engine_Monthly!$D$132:$BK$132) -> 201.87128
A56: Legal, compliance, audit | B56: ₹ lakh | C56: =SUMIF(Engine_Monthly!$D$7:$BK$7,C$4,Engine_Monthly!$D$133:$BK$133) -> 9 | D56: =SUMIF(Engine_Monthly!$D$7:$BK$7,D$4,Engine_Monthly!$D$133:$BK$133) -> 9.45 | E56: =SUMIF(Engine_Monthly!$D$7:$BK$7,E$4,Engine_Monthly!$D$133:$BK$133) -> 9.9225 | F56: =SUMIF(Engine_Monthly!$D$7:$BK$7,F$4,Engine_Monthly!$D$133:$BK$133) -> 10.418625 | G56: =SUMIF(Engine_Monthly!$D$7:$BK$7,G$4,Engine_Monthly!$D$133:$BK$133) -> 10.939556
A57: Insurance | B57: ₹ lakh | C57: =SUMIF(Engine_Monthly!$D$7:$BK$7,C$4,Engine_Monthly!$D$134:$BK$134) -> 1.75 | D57: =SUMIF(Engine_Monthly!$D$7:$BK$7,D$4,Engine_Monthly!$D$134:$BK$134) -> 3.15 | E57: =SUMIF(Engine_Monthly!$D$7:$BK$7,E$4,Engine_Monthly!$D$134:$BK$134) -> 3.3075 | F57: =SUMIF(Engine_Monthly!$D$7:$BK$7,F$4,Engine_Monthly!$D$134:$BK$134) -> 3.472875 | G57: =SUMIF(Engine_Monthly!$D$7:$BK$7,G$4,Engine_Monthly!$D$134:$BK$134) -> 3.6465187
A58: Recruitment | B58: ₹ lakh | C58: =SUMIF(Engine_Monthly!$D$7:$BK$7,C$4,Engine_Monthly!$D$135:$BK$135) -> 8.25 | D58: =SUMIF(Engine_Monthly!$D$7:$BK$7,D$4,Engine_Monthly!$D$135:$BK$135) -> 10.5 | E58: =SUMIF(Engine_Monthly!$D$7:$BK$7,E$4,Engine_Monthly!$D$135:$BK$135) -> 21 | F58: =SUMIF(Engine_Monthly!$D$7:$BK$7,F$4,Engine_Monthly!$D$135:$BK$135) -> 26.25 | G58: =SUMIF(Engine_Monthly!$D$7:$BK$7,G$4,Engine_Monthly!$D$135:$BK$135) -> 30
A59: General & administrative | B59: ₹ lakh | C59: =SUMIF(Engine_Monthly!$D$7:$BK$7,C$4,Engine_Monthly!$D$136:$BK$136) -> 44.68 | D59: =SUMIF(Engine_Monthly!$D$7:$BK$7,D$4,Engine_Monthly!$D$136:$BK$136) -> 81.942 | E59: =SUMIF(Engine_Monthly!$D$7:$BK$7,E$4,Engine_Monthly!$D$136:$BK$136) -> 158.05902 | F59: =SUMIF(Engine_Monthly!$D$7:$BK$7,F$4,Engine_Monthly!$D$136:$BK$136) -> 236.49891 | G59: =SUMIF(Engine_Monthly!$D$7:$BK$7,G$4,Engine_Monthly!$D$136:$BK$136) -> 319.59724
A60: Total operating expenses | B60: ₹ lakh | C60: =SUMIF(Engine_Monthly!$D$7:$BK$7,C$4,Engine_Monthly!$D$137:$BK$137) -> 186.84067 | D60: =SUMIF(Engine_Monthly!$D$7:$BK$7,D$4,Engine_Monthly!$D$137:$BK$137) -> 566.64472 | E60: =SUMIF(Engine_Monthly!$D$7:$BK$7,E$4,Engine_Monthly!$D$137:$BK$137) -> 1225.4577 | F60: =SUMIF(Engine_Monthly!$D$7:$BK$7,F$4,Engine_Monthly!$D$137:$BK$137) -> 2142.3805 | G60: =SUMIF(Engine_Monthly!$D$7:$BK$7,G$4,Engine_Monthly!$D$137:$BK$137) -> 3191.1298
A61: Memo: people cost inside cost of revenue | B61: ₹ lakh | C61: =SUMIF(Engine_Monthly!$D$7:$BK$7,C$4,Engine_Monthly!$D$81:$BK$81)+SUMIF(Engine_Monthly!$D$7:$BK$7,C$4,Engine_Monthly!$D$78:$BK$78)+SUMIF(Engine_Monthly!$D$7:$BK$7,C$4,Engine_Monthly!$D$79:$BK$79) -> 14.933333 | D61: =SUMIF(Engine_Monthly!$D$7:$BK$7,D$4,Engine_Monthly!$D$81:$BK$81)+SUMIF(Engine_Monthly!$D$7:$BK$7,D$4,Engine_Monthly!$D$78:$BK$78)+SUMIF(Engine_Monthly!$D$7:$BK$7,D$4,Engine_Monthly!$D$79:$BK$79) -> 65.52 | E61: =SUMIF(Engine_Monthly!$D$7:$BK$7,E$4,Engine_Monthly!$D$81:$BK$81)+SUMIF(Engine_Monthly!$D$7:$BK$7,E$4,Engine_Monthly!$D$78:$BK$78)+SUMIF(Engine_Monthly!$D$7:$BK$7,E$4,Engine_Monthly!$D$79:$BK$79) -> 183.65357 | F61: =SUMIF(Engine_Monthly!$D$7:$BK$7,F$4,Engine_Monthly!$D$81:$BK$81)+SUMIF(Engine_Monthly!$D$7:$BK$7,F$4,Engine_Monthly!$D$78:$BK$78)+SUMIF(Engine_Monthly!$D$7:$BK$7,F$4,Engine_Monthly!$D$79:$BK$79) -> 416.56156 | G61: =SUMIF(Engine_Monthly!$D$7:$BK$7,G$4,Engine_Monthly!$D$81:$BK$81)+SUMIF(Engine_Monthly!$D$7:$BK$7,G$4,Engine_Monthly!$D$78:$BK$78)+SUMIF(Engine_Monthly!$D$7:$BK$7,G$4,Engine_Monthly!$D$79:$BK$79) -> 758.82632
A62: Opex as % of revenue | B62: % | C62: =IFERROR(C60/7_Financials!C11,0) -> 6.5243074 | D62: =IFERROR(D60/7_Financials!D11,0) -> 1.1833572 | E62: =IFERROR(E60/7_Financials!E11,0) -> 0.50824662 | F62: =IFERROR(F60/7_Financials!F11,0) -> 0.30490806 | G62: =IFERROR(G60/7_Financials!G11,0) -> 0.21143151

Sheet 7_Financials
A1: 7. INTEGRATED FINANCIAL STATEMENTS (₹ lakh; ₹1 crore = ₹100 lakh)
A2: All figures aggregate the monthly engine. Active scenario shown on Inputs!C3.
A3: ₹ lakh | B3: Unit | C3: =INDEX(Engine_Monthly!$D$10:$BK$10,1,12) -> FY27 | D3: =INDEX(Engine_Monthly!$D$10:$BK$10,1,24) -> FY28 | E3: =INDEX(Engine_Monthly!$D$10:$BK$10,1,36) -> FY29 | F3: =INDEX(Engine_Monthly!$D$10:$BK$10,1,48) -> FY30 | G3: =INDEX(Engine_Monthly!$D$10:$BK$10,1,60) -> FY31
A4: Fiscal-year index | C4: 1 | D4: 2 | E4: 3 | F4: 4 | G4: 5
A6: PROFIT & LOSS
A7: Subscription (SaaS) revenue | B7: ₹ lakh | C7: =SUMIF(Engine_Monthly!$D$7:$BK$7,C$4,Engine_Monthly!$D$60:$BK$60) -> 4.8583551 | D7: =SUMIF(Engine_Monthly!$D$7:$BK$7,D$4,Engine_Monthly!$D$60:$BK$60) -> 187.88507 | E7: =SUMIF(Engine_Monthly!$D$7:$BK$7,E$4,Engine_Monthly!$D$60:$BK$60) -> 1385.3103 | F7: =SUMIF(Engine_Monthly!$D$7:$BK$7,F$4,Engine_Monthly!$D$60:$BK$60) -> 4773.9397 | G7: =SUMIF(Engine_Monthly!$D$7:$BK$7,G$4,Engine_Monthly!$D$60:$BK$60) -> 11320.283
A8: Implementation revenue | B8: ₹ lakh | C8: =SUMIF(Engine_Monthly!$D$7:$BK$7,C$4,Engine_Monthly!$D$61:$BK$61) -> 6.595875 | D8: =SUMIF(Engine_Monthly!$D$7:$BK$7,D$4,Engine_Monthly!$D$61:$BK$61) -> 110.03317 | E8: =SUMIF(Engine_Monthly!$D$7:$BK$7,E$4,Engine_Monthly!$D$61:$BK$61) -> 429.43821 | F8: =SUMIF(Engine_Monthly!$D$7:$BK$7,F$4,Engine_Monthly!$D$61:$BK$61) -> 984.36671 | G8: =SUMIF(Engine_Monthly!$D$7:$BK$7,G$4,Engine_Monthly!$D$61:$BK$61) -> 1672.0376
A9: Other operating revenue (paid pilots, IoT kits) | B9: ₹ lakh | C9: =SUMIF(Engine_Monthly!$D$7:$BK$7,C$4,Engine_Monthly!$D$62:$BK$62)+SUMIF(Engine_Monthly!$D$7:$BK$7,C$4,Engine_Monthly!$D$63:$BK$63) -> 16.814563 | D9: =SUMIF(Engine_Monthly!$D$7:$BK$7,D$4,Engine_Monthly!$D$62:$BK$62)+SUMIF(Engine_Monthly!$D$7:$BK$7,D$4,Engine_Monthly!$D$63:$BK$63) -> 169.20661 | E9: =SUMIF(Engine_Monthly!$D$7:$BK$7,E$4,Engine_Monthly!$D$62:$BK$62)+SUMIF(Engine_Monthly!$D$7:$BK$7,E$4,Engine_Monthly!$D$63:$BK$63) -> 519.33964 | F9: =SUMIF(Engine_Monthly!$D$7:$BK$7,F$4,Engine_Monthly!$D$62:$BK$62)+SUMIF(Engine_Monthly!$D$7:$BK$7,F$4,Engine_Monthly!$D$63:$BK$63) -> 1024.7962 | G9: =SUMIF(Engine_Monthly!$D$7:$BK$7,G$4,Engine_Monthly!$D$62:$BK$62)+SUMIF(Engine_Monthly!$D$7:$BK$7,G$4,Engine_Monthly!$D$63:$BK$63) -> 1569.5469
A10: Gain-share revenue (performance-linked; not ARR, not guaranteed) | B10: ₹ lakh | C10: =SUMIF(Engine_Monthly!$D$7:$BK$7,C$4,Engine_Monthly!$D$64:$BK$64) -> 0.36883224 | D10: =SUMIF(Engine_Monthly!$D$7:$BK$7,D$4,Engine_Monthly!$D$64:$BK$64) -> 11.720179 | E10: =SUMIF(Engine_Monthly!$D$7:$BK$7,E$4,Engine_Monthly!$D$64:$BK$64) -> 77.059653 | F10: =SUMIF(Engine_Monthly!$D$7:$BK$7,F$4,Engine_Monthly!$D$64:$BK$64) -> 243.2136 | G10: =SUMIF(Engine_Monthly!$D$7:$BK$7,G$4,Engine_Monthly!$D$64:$BK$64) -> 531.10413 | H10: Expected value after the participation and collection haircuts on Inputs section K. Zero in bear.
A11: Total revenue | B11: ₹ lakh | C11: =C7+C8+C9+C10 -> 28.637625 | D11: =D7+D8+D9+D10 -> 478.84504 | E11: =E7+E8+E9+E10 -> 2411.1478 | F11: =F7+F8+F9+F10 -> 7026.3162 | G11: =G7+G8+G9+G10 -> 15092.972
A12: Revenue growth | B12: % | D12: =IFERROR(D11/C11-1,0) -> 15.720836 | E12: =IFERROR(E11/D11-1,0) -> 4.0353405 | F12: =IFERROR(F11/E11-1,0) -> 1.914096 | G12: =IFERROR(G11/F11-1,0) -> 1.1480633
A13: Cost of revenue | B13: ₹ lakh | C13: =-SUMIF(Engine_Monthly!$D$7:$BK$7,C$4,Engine_Monthly!$D$85:$BK$85) -> -45.131952 | D13: =-SUMIF(Engine_Monthly!$D$7:$BK$7,D$4,Engine_Monthly!$D$85:$BK$85) -> -261.69966 | E13: =-SUMIF(Engine_Monthly!$D$7:$BK$7,E$4,Engine_Monthly!$D$85:$BK$85) -> -830.89601 | F13: =-SUMIF(Engine_Monthly!$D$7:$BK$7,F$4,Engine_Monthly!$D$85:$BK$85) -> -1822.5933 | G13: =-SUMIF(Engine_Monthly!$D$7:$BK$7,G$4,Engine_Monthly!$D$85:$BK$85) -> -3115.7467
A14: Gross profit | B14: ₹ lakh | C14: =C11+C13 -> -16.494328 | D14: =D11+D13 -> 217.14537 | E14: =E11+E13 -> 1580.2518 | F14: =F11+F13 -> 5203.723 | G14: =G11+G13 -> 11977.225
A15: Gross margin | B15: % | C15: =IFERROR(C14/C11,0) -> -0.57596702 | D15: =IFERROR(D14/D11,0) -> 0.45347733 | E15: =IFERROR(E14/E11,0) -> 0.65539399 | F15: =IFERROR(F14/F11,0) -> 0.74060472 | G15: =IFERROR(G14/G11,0) -> 0.79356308
A16: Research & development | B16: ₹ lakh | C16: =-SUMIF(Engine_Monthly!$D$7:$BK$7,C$4,Engine_Monthly!$D$131:$BK$131) -> -69.806667 | D16: =-SUMIF(Engine_Monthly!$D$7:$BK$7,D$4,Engine_Monthly!$D$131:$BK$131) -> -178.1892 | E16: =-SUMIF(Engine_Monthly!$D$7:$BK$7,E$4,Engine_Monthly!$D$131:$BK$131) -> -255.14093 | F16: =-SUMIF(Engine_Monthly!$D$7:$BK$7,F$4,Engine_Monthly!$D$131:$BK$131) -> -347.16206 | G16: =-SUMIF(Engine_Monthly!$D$7:$BK$7,G$4,Engine_Monthly!$D$131:$BK$131) -> -486.11378
A17: Sales & marketing | B17: ₹ lakh | C17: =-SUMIF(Engine_Monthly!$D$7:$BK$7,C$4,Engine_Monthly!$D$129:$BK$129) -> -72.354 | D17: =-SUMIF(Engine_Monthly!$D$7:$BK$7,D$4,Engine_Monthly!$D$129:$BK$129) -> -306.51352 | E17: =-SUMIF(Engine_Monthly!$D$7:$BK$7,E$4,Engine_Monthly!$D$129:$BK$129) -> -812.25778 | F17: =-SUMIF(Engine_Monthly!$D$7:$BK$7,F$4,Engine_Monthly!$D$129:$BK$129) -> -1558.7195 | G17: =-SUMIF(Engine_Monthly!$D$7:$BK$7,G$4,Engine_Monthly!$D$129:$BK$129) -> -2385.4188
A18: General & administrative | B18: ₹ lakh | C18: =-SUMIF(Engine_Monthly!$D$7:$BK$7,C$4,Engine_Monthly!$D$136:$BK$136) -> -44.68 | D18: =-SUMIF(Engine_Monthly!$D$7:$BK$7,D$4,Engine_Monthly!$D$136:$BK$136) -> -81.942 | E18: =-SUMIF(Engine_Monthly!$D$7:$BK$7,E$4,Engine_Monthly!$D$136:$BK$136) -> -158.05902 | F18: =-SUMIF(Engine_Monthly!$D$7:$BK$7,F$4,Engine_Monthly!$D$136:$BK$136) -> -236.49891 | G18: =-SUMIF(Engine_Monthly!$D$7:$BK$7,G$4,Engine_Monthly!$D$136:$BK$136) -> -319.59724
A19: EBITDA | B19: ₹ lakh | C19: =C14+C16+C17+C18 -> -203.33499 | D19: =D14+D16+D17+D18 -> -349.49934 | E19: =E14+E16+E17+E18 -> 354.79406 | F19: =F14+F16+F17+F18 -> 3061.3425 | G19: =G14+G16+G17+G18 -> 8786.0955
A20: EBITDA margin | B20: % | C20: =IFERROR(C19/C11,0) -> -7.1002744 | D20: =IFERROR(D19/D11,0) -> -0.72987986 | E20: =IFERROR(E19/E11,0) -> 0.14714737 | F20: =IFERROR(F19/F11,0) -> 0.43569666 | G20: =IFERROR(G19/G11,0) -> 0.58213157
A21: Depreciation & amortisation | B21: ₹ lakh | C21: =-SUMIF(Engine_Monthly!$D$7:$BK$7,C$4,Engine_Monthly!$D$142:$BK$142) -> -6.1777778 | D21: =-SUMIF(Engine_Monthly!$D$7:$BK$7,D$4,Engine_Monthly!$D$142:$BK$142) -> -12.5 | E21: =-SUMIF(Engine_Monthly!$D$7:$BK$7,E$4,Engine_Monthly!$D$142:$BK$142) -> -21.366667 | F21: =-SUMIF(Engine_Monthly!$D$7:$BK$7,F$4,Engine_Monthly!$D$142:$BK$142) -> -28.022222 | G21: =-SUMIF(Engine_Monthly!$D$7:$BK$7,G$4,Engine_Monthly!$D$142:$BK$142) -> -36.966667
A22: EBIT | B22: ₹ lakh | C22: =C19+C21 -> -209.51277 | D22: =D19+D21 -> -361.99934 | E22: =E19+E21 -> 333.42739 | F22: =F19+F21 -> 3033.3203 | G22: =G19+G21 -> 8749.1289
A23: Interest expense (net of interest income) | B23: ₹ lakh | C23: =-SUMIF(Engine_Monthly!$D$7:$BK$7,C$4,Engine_Monthly!$D$147:$BK$147)+SUMIF(Engine_Monthly!$D$7:$BK$7,C$4,Engine_Monthly!$D$148:$BK$148) -> 0 | D23: =-SUMIF(Engine_Monthly!$D$7:$BK$7,D$4,Engine_Monthly!$D$147:$BK$147)+SUMIF(Engine_Monthly!$D$7:$BK$7,D$4,Engine_Monthly!$D$148:$BK$148) -> 0 | E23: =-SUMIF(Engine_Monthly!$D$7:$BK$7,E$4,Engine_Monthly!$D$147:$BK$147)+SUMIF(Engine_Monthly!$D$7:$BK$7,E$4,Engine_Monthly!$D$148:$BK$148) -> 0 | F23: =-SUMIF(Engine_Monthly!$D$7:$BK$7,F$4,Engine_Monthly!$D$147:$BK$147)+SUMIF(Engine_Monthly!$D$7:$BK$7,F$4,Engine_Monthly!$D$148:$BK$148) -> 0 | G23: =-SUMIF(Engine_Monthly!$D$7:$BK$7,G$4,Engine_Monthly!$D$147:$BK$147)+SUMIF(Engine_Monthly!$D$7:$BK$7,G$4,Engine_Monthly!$D$148:$BK$148) -> 0
A24: Profit before tax | B24: ₹ lakh | C24: =C22+C23 -> -209.51277 | D24: =D22+D23 -> -361.99934 | E24: =E22+E23 -> 333.42739 | F24: =F22+F23 -> 3033.3203 | G24: =G22+G23 -> 8749.1289
A25: Income tax | B25: ₹ lakh | C25: =-SUMIF(Engine_Monthly!$D$7:$BK$7,C$4,Engine_Monthly!$D$151:$BK$151) -> 0 | D25: =-SUMIF(Engine_Monthly!$D$7:$BK$7,D$4,Engine_Monthly!$D$151:$BK$151) -> 0 | E25: =-SUMIF(Engine_Monthly!$D$7:$BK$7,E$4,Engine_Monthly!$D$151:$BK$151) -> 0 | F25: =-SUMIF(Engine_Monthly!$D$7:$BK$7,F$4,Engine_Monthly!$D$151:$BK$151) -> -703.50489 | G25: =-SUMIF(Engine_Monthly!$D$7:$BK$7,G$4,Engine_Monthly!$D$151:$BK$151) -> -2201.9808 | H25: Nil until cumulative tax losses are absorbed. No deferred tax asset recognised (prudence).
A26: Net profit / (loss) | B26: ₹ lakh | C26: =C24+C25 -> -209.51277 | D26: =D24+D25 -> -361.99934 | E26: =E24+E25 -> 333.42739 | F26: =F24+F25 -> 2329.8154 | G26: =G24+G25 -> 6547.1481
A28: CASH FLOW STATEMENT
A29: EBITDA | B29: ₹ lakh | C29: =C19 -> -203.33499 | D29: =D19 -> -349.49934 | E29: =E19 -> 354.79406 | F29: =F19 -> 3061.3425 | G29: =G19 -> 8786.0955
A30: Working-capital movement (receivables, payables, deferred revenue) | B30: ₹ lakh | C30: =(INDEX(Engine_Monthly!$D$158:$BK$158,1,C$4*12)-IF(C$4=1,0,INDEX(Engine_Monthly!$D$158:$BK$158,1,(C$4-1)*12)))+(INDEX(Engine_Monthly!$D$155:$BK$155,1,C$4*12)-IF(C$4=1,0,INDEX(Engine_Monthly!$D$155:$BK$155,1,(C$4-1)*12)))-(INDEX(Engine_Monthly!$D$157:$BK$157,1,C$4*12)-IF(C$4=1,0,INDEX(Engine_Monthly!$D$157:$BK$157,1,(C$4-1)*12))) -> 2.7288814 | D30: =(INDEX(Engine_Monthly!$D$158:$BK$158,1,D$4*12)-IF(D$4=1,0,INDEX(Engine_Monthly!$D$158:$BK$158,1,(D$4-1)*12)))+(INDEX(Engine_Monthly!$D$155:$BK$155,1,D$4*12)-IF(D$4=1,0,INDEX(Engine_Monthly!$D$155:$BK$155,1,(D$4-1)*12)))-(INDEX(Engine_Monthly!$D$157:$BK$157,1,D$4*12)-IF(D$4=1,0,INDEX(Engine_Monthly!$D$157:$BK$157,1,(D$4-1)*12))) -> -28.602638 | E30: =(INDEX(Engine_Monthly!$D$158:$BK$158,1,E$4*12)-IF(E$4=1,0,INDEX(Engine_Monthly!$D$158:$BK$158,1,(E$4-1)*12)))+(INDEX(Engine_Monthly!$D$155:$BK$155,1,E$4*12)-IF(E$4=1,0,INDEX(Engine_Monthly!$D$155:$BK$155,1,(E$4-1)*12)))-(INDEX(Engine_Monthly!$D$157:$BK$157,1,E$4*12)-IF(E$4=1,0,INDEX(Engine_Monthly!$D$157:$BK$157,1,(E$4-1)*12))) -> -58.973221 | F30: =(INDEX(Engine_Monthly!$D$158:$BK$158,1,F$4*12)-IF(F$4=1,0,INDEX(Engine_Monthly!$D$158:$BK$158,1,(F$4-1)*12)))+(INDEX(Engine_Monthly!$D$155:$BK$155,1,F$4*12)-IF(F$4=1,0,INDEX(Engine_Monthly!$D$155:$BK$155,1,(F$4-1)*12)))-(INDEX(Engine_Monthly!$D$157:$BK$157,1,F$4*12)-IF(F$4=1,0,INDEX(Engine_Monthly!$D$157:$BK$157,1,(F$4-1)*12))) -> -84.440133 | G30: =(INDEX(Engine_Monthly!$D$158:$BK$158,1,G$4*12)-IF(G$4=1,0,INDEX(Engine_Monthly!$D$158:$BK$158,1,(G$4-1)*12)))+(INDEX(Engine_Monthly!$D$155:$BK$155,1,G$4*12)-IF(G$4=1,0,INDEX(Engine_Monthly!$D$155:$BK$155,1,(G$4-1)*12)))-(INDEX(Engine_Monthly!$D$157:$BK$157,1,G$4*12)-IF(G$4=1,0,INDEX(Engine_Monthly!$D$157:$BK$157,1,(G$4-1)*12))) -> -96.054754
A31: Net interest paid | B31: ₹ lakh | C31: =C23 -> 0 | D31: =D23 -> 0 | E31: =E23 -> 0 | F31: =F23 -> 0 | G31: =G23 -> 0
A32: Cash taxes | B32: ₹ lakh | C32: =C25 -> 0 | D32: =D25 -> 0 | E32: =E25 -> 0 | F32: =F25 -> -703.50489 | G32: =G25 -> -2201.9808
A33: Cash flow from operations | B33: ₹ lakh | C33: =SUM(C29:C32) -> -200.60611 | D33: =SUM(D29:D32) -> -378.10198 | E33: =SUM(E29:E32) -> 295.82084 | F33: =SUM(F29:F32) -> 2273.3975 | G33: =SUM(G29:G32) -> 6488.06
A34: Capital expenditure | B34: ₹ lakh | C34: =-SUMIF(Engine_Monthly!$D$7:$BK$7,C$4,Engine_Monthly!$D$141:$BK$141) -> -23.2 | D34: =-SUMIF(Engine_Monthly!$D$7:$BK$7,D$4,Engine_Monthly!$D$141:$BK$141) -> -16.8 | E34: =-SUMIF(Engine_Monthly!$D$7:$BK$7,E$4,Engine_Monthly!$D$141:$BK$141) -> -33.6 | F34: =-SUMIF(Engine_Monthly!$D$7:$BK$7,F$4,Engine_Monthly!$D$141:$BK$141) -> -42 | G34: =-SUMIF(Engine_Monthly!$D$7:$BK$7,G$4,Engine_Monthly!$D$141:$BK$141) -> -48
A35: Capitalised software development | B35: ₹ lakh | C35: =0 -> 0 | D35: =0 -> 0 | E35: =0 -> 0 | F35: =0 -> 0 | G35: =0 -> 0 | H35: Policy: R&D expensed. Capitalise only once Ind AS 38 criteria (feasibility, intent, measurable cost) are documented.
A36: Cash flow from investing | B36: ₹ lakh | C36: =C34+C35 -> -23.2 | D36: =D34+D35 -> -16.8 | E36: =E34+E35 -> -33.6 | F36: =F34+F35 -> -42 | G36: =G34+G35 -> -48
A37: Equity raised | B37: ₹ lakh | C37: =SUMIF(Engine_Monthly!$D$7:$BK$7,C$4,Engine_Monthly!$D$161:$BK$161) -> 900 | D37: =SUMIF(Engine_Monthly!$D$7:$BK$7,D$4,Engine_Monthly!$D$161:$BK$161) -> 900 | E37: =SUMIF(Engine_Monthly!$D$7:$BK$7,E$4,Engine_Monthly!$D$161:$BK$161) -> 0 | F37: =SUMIF(Engine_Monthly!$D$7:$BK$7,F$4,Engine_Monthly!$D$161:$BK$161) -> 0 | G37: =SUMIF(Engine_Monthly!$D$7:$BK$7,G$4,Engine_Monthly!$D$161:$BK$161) -> 0
A38: Debt drawn | B38: ₹ lakh | C38: =SUMIF(Engine_Monthly!$D$7:$BK$7,C$4,Engine_Monthly!$D$144:$BK$144) -> 0 | D38: =SUMIF(Engine_Monthly!$D$7:$BK$7,D$4,Engine_Monthly!$D$144:$BK$144) -> 0 | E38: =SUMIF(Engine_Monthly!$D$7:$BK$7,E$4,Engine_Monthly!$D$144:$BK$144) -> 0 | F38: =SUMIF(Engine_Monthly!$D$7:$BK$7,F$4,Engine_Monthly!$D$144:$BK$144) -> 0 | G38: =SUMIF(Engine_Monthly!$D$7:$BK$7,G$4,Engine_Monthly!$D$144:$BK$144) -> 0
A39: Debt repaid | B39: ₹ lakh | C39: =-SUMIF(Engine_Monthly!$D$7:$BK$7,C$4,Engine_Monthly!$D$145:$BK$145) -> 0 | D39: =-SUMIF(Engine_Monthly!$D$7:$BK$7,D$4,Engine_Monthly!$D$145:$BK$145) -> 0 | E39: =-SUMIF(Engine_Monthly!$D$7:$BK$7,E$4,Engine_Monthly!$D$145:$BK$145) -> 0 | F39: =-SUMIF(Engine_Monthly!$D$7:$BK$7,F$4,Engine_Monthly!$D$145:$BK$145) -> 0 | G39: =-SUMIF(Engine_Monthly!$D$7:$BK$7,G$4,Engine_Monthly!$D$145:$BK$145) -> 0
A40: Cash flow from financing | B40: ₹ lakh | C40: =SUM(C37:C39) -> 900 | D40: =SUM(D37:D39) -> 900 | E40: =SUM(E37:E39) -> 0 | F40: =SUM(F37:F39) -> 0 | G40: =SUM(G37:G39) -> 0
A41: Net change in cash | B41: ₹ lakh | C41: =C33+C36+C40 -> 676.19389 | D41: =D33+D36+D40 -> 505.09802 | E41: =E33+E36+E40 -> 262.22084 | F41: =F33+F36+F40 -> 2231.3975 | G41: =G33+G36+G40 -> 6440.06
A42: Opening cash | B42: ₹ lakh | C42: =0 -> 0 | D42: =C43 -> 676.19389 | E42: =D43 -> 1181.2919 | F42: =E43 -> 1443.5127 | G42: =F43 -> 3674.9102
A43: Closing cash | B43: ₹ lakh | C43: =C42+C41 -> 676.19389 | D43: =D42+D41 -> 1181.2919 | E43: =E42+E41 -> 1443.5127 | F43: =F42+F41 -> 3674.9102 | G43: =G42+G41 -> 10114.97
A44: Check: closing cash vs monthly engine (should be 0) | B44: ₹ lakh | C44: =ROUND(C43-INDEX(Engine_Monthly!$D$165:$BK$165,1,C$4*12),3) -> 0 | D44: =ROUND(D43-INDEX(Engine_Monthly!$D$165:$BK$165,1,D$4*12),3) -> 0 | E44: =ROUND(E43-INDEX(Engine_Monthly!$D$165:$BK$165,1,E$4*12),3) -> 0 | F44: =ROUND(F43-INDEX(Engine_Monthly!$D$165:$BK$165,1,F$4*12),3) -> 0 | G44: =ROUND(G43-INDEX(Engine_Monthly!$D$165:$BK$165,1,G$4*12),3) -> 0
A46: BALANCE SHEET (fiscal year end)
A47: Cash & cash equivalents | B47: ₹ lakh | C47: =INDEX(Engine_Monthly!$D$165:$BK$165,1,C$4*12) -> 676.19389 | D47: =INDEX(Engine_Monthly!$D$165:$BK$165,1,D$4*12) -> 1181.2919 | E47: =INDEX(Engine_Monthly!$D$165:$BK$165,1,E$4*12) -> 1443.5127 | F47: =INDEX(Engine_Monthly!$D$165:$BK$165,1,F$4*12) -> 3674.9102 | G47: =INDEX(Engine_Monthly!$D$165:$BK$165,1,G$4*12) -> 10114.97
A48: Trade receivables | B48: ₹ lakh | C48: =INDEX(Engine_Monthly!$D$157:$BK$157,1,C$4*12) -> 13.799077 | D48: =INDEX(Engine_Monthly!$D$157:$BK$157,1,D$4*12) -> 154.20208 | E48: =INDEX(Engine_Monthly!$D$157:$BK$157,1,E$4*12) -> 565.3444 | F48: =INDEX(Engine_Monthly!$D$157:$BK$157,1,F$4*12) -> 1373.4359 | G48: =INDEX(Engine_Monthly!$D$157:$BK$157,1,G$4*12) -> 2643.9358
A49: Prepayments & other assets | B49: ₹ lakh | C49: =0 -> 0 | D49: =0 -> 0 | E49: =0 -> 0 | F49: =0 -> 0 | G49: =0 -> 0 | H49: Not modelled separately (immaterial).
A50: Property, plant & equipment (net) | B50: ₹ lakh | C50: =INDEX(Engine_Monthly!$D$168:$BK$168,1,C$4*12) -> 17.022222 | D50: =INDEX(Engine_Monthly!$D$168:$BK$168,1,D$4*12) -> 21.322222 | E50: =INDEX(Engine_Monthly!$D$168:$BK$168,1,E$4*12) -> 33.555556 | F50: =INDEX(Engine_Monthly!$D$168:$BK$168,1,F$4*12) -> 47.533333 | G50: =INDEX(Engine_Monthly!$D$168:$BK$168,1,G$4*12) -> 58.566667
A51: Capitalised intangible assets | B51: ₹ lakh | C51: =0 -> 0 | D51: =0 -> 0 | E51: =0 -> 0 | F51: =0 -> 0 | G51: =0 -> 0 | H51: Nil by policy (see cash flow note).
A52: Total assets | B52: ₹ lakh | C52: =SUM(C47:C51) -> 707.01519 | D52: =SUM(D47:D51) -> 1356.8162 | E52: =SUM(E47:E51) -> 2042.4127 | F52: =SUM(F47:F51) -> 5095.8795 | G52: =SUM(G47:G51) -> 12817.473
A53: Trade payables & accrued expenses | B53: ₹ lakh | C53: =INDEX(Engine_Monthly!$D$158:$BK$158,1,C$4*12) -> 12.653359 | D53: =INDEX(Engine_Monthly!$D$158:$BK$158,1,D$4*12) -> 59.210204 | E53: =INDEX(Engine_Monthly!$D$158:$BK$158,1,E$4*12) -> 153.04199 | F53: =INDEX(Engine_Monthly!$D$158:$BK$158,1,F$4*12) -> 275.44575 | G53: =INDEX(Engine_Monthly!$D$158:$BK$158,1,G$4*12) -> 410.37171
A54: Deferred revenue | B54: ₹ lakh | C54: =INDEX(Engine_Monthly!$D$155:$BK$155,1,C$4*12) -> 3.8745999 | D54: =INDEX(Engine_Monthly!$D$155:$BK$155,1,D$4*12) -> 69.118123 | E54: =INDEX(Engine_Monthly!$D$155:$BK$155,1,E$4*12) -> 327.45543 | F54: =INDEX(Engine_Monthly!$D$155:$BK$155,1,F$4*12) -> 928.70305 | G54: =INDEX(Engine_Monthly!$D$155:$BK$155,1,G$4*12) -> 1968.2223
A55: Debt | B55: ₹ lakh | C55: =INDEX(Engine_Monthly!$D$146:$BK$146,1,C$4*12) -> 0 | D55: =INDEX(Engine_Monthly!$D$146:$BK$146,1,D$4*12) -> 0 | E55: =INDEX(Engine_Monthly!$D$146:$BK$146,1,E$4*12) -> 0 | F55: =INDEX(Engine_Monthly!$D$146:$BK$146,1,F$4*12) -> 0 | G55: =INDEX(Engine_Monthly!$D$146:$BK$146,1,G$4*12) -> 0
A56: Total liabilities | B56: ₹ lakh | C56: =SUM(C53:C55) -> 16.527959 | D56: =SUM(D53:D55) -> 128.32833 | E56: =SUM(E53:E55) -> 480.49742 | F56: =SUM(F53:F55) -> 1204.1488 | G56: =SUM(G53:G55) -> 2378.594
A57: Share capital & premium | B57: ₹ lakh | C57: =INDEX(Engine_Monthly!$D$169:$BK$169,1,C$4*12) -> 900 | D57: =INDEX(Engine_Monthly!$D$169:$BK$169,1,D$4*12) -> 1800 | E57: =INDEX(Engine_Monthly!$D$169:$BK$169,1,E$4*12) -> 1800 | F57: =INDEX(Engine_Monthly!$D$169:$BK$169,1,F$4*12) -> 1800 | G57: =INDEX(Engine_Monthly!$D$169:$BK$169,1,G$4*12) -> 1800
A58: Retained earnings / (accumulated losses) | B58: ₹ lakh | C58: =INDEX(Engine_Monthly!$D$170:$BK$170,1,C$4*12) -> -209.51277 | D58: =INDEX(Engine_Monthly!$D$170:$BK$170,1,D$4*12) -> -571.51212 | E58: =INDEX(Engine_Monthly!$D$170:$BK$170,1,E$4*12) -> -238.08472 | F58: =INDEX(Engine_Monthly!$D$170:$BK$170,1,F$4*12) -> 2091.7307 | G58: =INDEX(Engine_Monthly!$D$170:$BK$170,1,G$4*12) -> 8638.8788
A59: Total equity | B59: ₹ lakh | C59: =C57+C58 -> 690.48723 | D59: =D57+D58 -> 1228.4879 | E59: =E57+E58 -> 1561.9153 | F59: =F57+F58 -> 3891.7307 | G59: =G57+G58 -> 10438.879
A60: Total liabilities & equity | B60: ₹ lakh | C60: =C56+C59 -> 707.01519 | D60: =D56+D59 -> 1356.8162 | E60: =E56+E59 -> 2042.4127 | F60: =F56+F59 -> 5095.8795 | G60: =G56+G59 -> 12817.473
A61: Balance check (should be 0) | B61: ₹ lakh | C61: =ROUND(C52-C60,3) -> 0 | D61: =ROUND(D52-D60,3) -> 0 | E61: =ROUND(E52-E60,3) -> 0 | F61: =ROUND(F52-F60,3) -> 0 | G61: =ROUND(G52-G60,3) -> 0

Sheet 8_Unit_Economics
A1: 8. UNIT ECONOMICS (ESTIMATES: no customer history exists; every ratio below is model-derived, not proven)
A3: ₹ lakh | B3: Unit | C3: =INDEX(Engine_Monthly!$D$10:$BK$10,1,12) -> FY27 | D3: =INDEX(Engine_Monthly!$D$10:$BK$10,1,24) -> FY28 | E3: =INDEX(Engine_Monthly!$D$10:$BK$10,1,36) -> FY29 | F3: =INDEX(Engine_Monthly!$D$10:$BK$10,1,48) -> FY30 | G3: =INDEX(Engine_Monthly!$D$10:$BK$10,1,60) -> FY31
A4: Fiscal-year index | C4: 1 | D4: 2 | E4: 3 | F4: 4 | G4: 5
A6: PER PLANT
A7: Average ARR per live plant | B7: ₹ lakh | C7: =IFERROR(SUMIF(Engine_Monthly!$D$7:$BK$7,C$4,Engine_Monthly!$D$60:$BK$60)/AVERAGEIF(Engine_Monthly!$D$7:$BK$7,C$4,Engine_Monthly!$D$49:$BK$49),0) -> 22.969133 | D7: =IFERROR(SUMIF(Engine_Monthly!$D$7:$BK$7,D$4,Engine_Monthly!$D$60:$BK$60)/AVERAGEIF(Engine_Monthly!$D$7:$BK$7,D$4,Engine_Monthly!$D$49:$BK$49),0) -> 27.953889 | E7: =IFERROR(SUMIF(Engine_Monthly!$D$7:$BK$7,E$4,Engine_Monthly!$D$60:$BK$60)/AVERAGEIF(Engine_Monthly!$D$7:$BK$7,E$4,Engine_Monthly!$D$49:$BK$49),0) -> 31.347596 | F7: =IFERROR(SUMIF(Engine_Monthly!$D$7:$BK$7,F$4,Engine_Monthly!$D$60:$BK$60)/AVERAGEIF(Engine_Monthly!$D$7:$BK$7,F$4,Engine_Monthly!$D$49:$BK$49),0) -> 34.227352 | G7: =IFERROR(SUMIF(Engine_Monthly!$D$7:$BK$7,G$4,Engine_Monthly!$D$60:$BK$60)/AVERAGEIF(Engine_Monthly!$D$7:$BK$7,G$4,Engine_Monthly!$D$49:$BK$49),0) -> 37.167371 | H7: Subscription revenue ÷ average live plants.
A8: Implementation revenue per new plant | B8: ₹ lakh | C8: =5_Cost_of_Service!C27 -> 6.15 | D8: =5_Cost_of_Service!D27 -> 6.4575 | E8: =5_Cost_of_Service!E27 -> 6.780375 | F8: =5_Cost_of_Service!F27 -> 7.1193938 | G8: =5_Cost_of_Service!G27 -> 7.4753634
A9: Direct deployment cost per new plant (incl. failed-pilot cost) | B9: ₹ lakh | C9: =5_Cost_of_Service!C26 -> 17.915695 | D9: =5_Cost_of_Service!D26 -> 9.1184824 | E9: =5_Cost_of_Service!E26 -> 7.9505701 | F9: =5_Cost_of_Service!F26 -> 7.6871891 | G9: =5_Cost_of_Service!G26 -> 7.7607912
A10: Recurring cost to serve per plant | B10: ₹ lakh | C10: =IF(AVERAGEIF(Engine_Monthly!$D$7:$BK$7,C$4,Engine_Monthly!$D$49:$BK$49)<3,"n.m.",5_Cost_of_Service!C18) -> n.m. | D10: =IF(AVERAGEIF(Engine_Monthly!$D$7:$BK$7,D$4,Engine_Monthly!$D$49:$BK$49)<3,"n.m.",5_Cost_of_Service!D18) -> 11.382578 | E10: =IF(AVERAGEIF(Engine_Monthly!$D$7:$BK$7,E$4,Engine_Monthly!$D$49:$BK$49)<3,"n.m.",5_Cost_of_Service!E18) -> 4.8992194 | F10: =IF(AVERAGEIF(Engine_Monthly!$D$7:$BK$7,F$4,Engine_Monthly!$D$49:$BK$49)<3,"n.m.",5_Cost_of_Service!F18) -> 3.7121112 | G10: =IF(AVERAGEIF(Engine_Monthly!$D$7:$BK$7,G$4,Engine_Monthly!$D$49:$BK$49)<3,"n.m.",5_Cost_of_Service!G18) -> 3.2452957
A11: SaaS gross profit per plant per year | B11: ₹ lakh | C11: =IF(AVERAGEIF(Engine_Monthly!$D$7:$BK$7,C$4,Engine_Monthly!$D$49:$BK$49)<3,"n.m.",C7-C10) -> n.m. | D11: =IF(AVERAGEIF(Engine_Monthly!$D$7:$BK$7,D$4,Engine_Monthly!$D$49:$BK$49)<3,"n.m.",D7-D10) -> 16.571312 | E11: =IF(AVERAGEIF(Engine_Monthly!$D$7:$BK$7,E$4,Engine_Monthly!$D$49:$BK$49)<3,"n.m.",E7-E10) -> 26.448376 | F11: =IF(AVERAGEIF(Engine_Monthly!$D$7:$BK$7,F$4,Engine_Monthly!$D$49:$BK$49)<3,"n.m.",F7-F10) -> 30.515241 | G11: =IF(AVERAGEIF(Engine_Monthly!$D$7:$BK$7,G$4,Engine_Monthly!$D$49:$BK$49)<3,"n.m.",G7-G10) -> 33.922075
A12: SaaS gross margin per plant | B12: % | C12: =IF(AVERAGEIF(Engine_Monthly!$D$7:$BK$7,C$4,Engine_Monthly!$D$49:$BK$49)<3,"n.m.",IFERROR(C11/C7,0)) -> n.m. | D12: =IF(AVERAGEIF(Engine_Monthly!$D$7:$BK$7,D$4,Engine_Monthly!$D$49:$BK$49)<3,"n.m.",IFERROR(D11/D7,0)) -> 0.59280881 | E12: =IF(AVERAGEIF(Engine_Monthly!$D$7:$BK$7,E$4,Engine_Monthly!$D$49:$BK$49)<3,"n.m.",IFERROR(E11/E7,0)) -> 0.84371307 | F12: =IF(AVERAGEIF(Engine_Monthly!$D$7:$BK$7,F$4,Engine_Monthly!$D$49:$BK$49)<3,"n.m.",IFERROR(F11/F7,0)) -> 0.89154548 | G12: =IF(AVERAGEIF(Engine_Monthly!$D$7:$BK$7,G$4,Engine_Monthly!$D$49:$BK$49)<3,"n.m.",IFERROR(G11/G7,0)) -> 0.91268428
A14: ACQUISITION
A15: New paying customers (contracts signed) | B15: # | C15: =SUMIF(Engine_Monthly!$D$7:$BK$7,C$4,Engine_Monthly!$D$32:$BK$32) -> 1.98 | D15: =SUMIF(Engine_Monthly!$D$7:$BK$7,D$4,Engine_Monthly!$D$32:$BK$32) -> 23.57939 | E15: =SUMIF(Engine_Monthly!$D$7:$BK$7,E$4,Engine_Monthly!$D$32:$BK$32) -> 75.260059 | F15: =SUMIF(Engine_Monthly!$D$7:$BK$7,F$4,Engine_Monthly!$D$32:$BK$32) -> 152.50012 | G15: =SUMIF(Engine_Monthly!$D$7:$BK$7,G$4,Engine_Monthly!$D$32:$BK$32) -> 237.16518
A16: Sales & marketing expense | B16: ₹ lakh | C16: =SUMIF(Engine_Monthly!$D$7:$BK$7,C$4,Engine_Monthly!$D$129:$BK$129) -> 72.354 | D16: =SUMIF(Engine_Monthly!$D$7:$BK$7,D$4,Engine_Monthly!$D$129:$BK$129) -> 306.51352 | E16: =SUMIF(Engine_Monthly!$D$7:$BK$7,E$4,Engine_Monthly!$D$129:$BK$129) -> 812.25778 | F16: =SUMIF(Engine_Monthly!$D$7:$BK$7,F$4,Engine_Monthly!$D$129:$BK$129) -> 1558.7195 | G16: =SUMIF(Engine_Monthly!$D$7:$BK$7,G$4,Engine_Monthly!$D$129:$BK$129) -> 2385.4188
A17: CAC, fully loaded (S&M ÷ new paying customers) | B17: ₹ lakh | C17: =IF(AVERAGEIF(Engine_Monthly!$D$7:$BK$7,C$4,Engine_Monthly!$D$49:$BK$49)<3,"n.m.",IFERROR(C16/C15,0)) -> n.m. | D17: =IF(AVERAGEIF(Engine_Monthly!$D$7:$BK$7,D$4,Engine_Monthly!$D$49:$BK$49)<3,"n.m.",IFERROR(D16/D15,0)) -> 12.999213 | E17: =IF(AVERAGEIF(Engine_Monthly!$D$7:$BK$7,E$4,Engine_Monthly!$D$49:$BK$49)<3,"n.m.",IFERROR(E16/E15,0)) -> 10.792681 | F17: =IF(AVERAGEIF(Engine_Monthly!$D$7:$BK$7,F$4,Engine_Monthly!$D$49:$BK$49)<3,"n.m.",IFERROR(F16/F15,0)) -> 10.221104 | G17: =IF(AVERAGEIF(Engine_Monthly!$D$7:$BK$7,G$4,Engine_Monthly!$D$49:$BK$49)<3,"n.m.",IFERROR(G16/G15,0)) -> 10.058048 | H17: All S&M attributed to new logos (conservative). Early years are distorted by spend ahead of the sales cycle.
A18: CAC incl. net deployment loss per plant | B18: ₹ lakh | C18: =IF(AVERAGEIF(Engine_Monthly!$D$7:$BK$7,C$4,Engine_Monthly!$D$49:$BK$49)<3,"n.m.",C17+MAX(0,C9-C8)) -> n.m. | D18: =IF(AVERAGEIF(Engine_Monthly!$D$7:$BK$7,D$4,Engine_Monthly!$D$49:$BK$49)<3,"n.m.",D17+MAX(0,D9-D8)) -> 15.660196 | E18: =IF(AVERAGEIF(Engine_Monthly!$D$7:$BK$7,E$4,Engine_Monthly!$D$49:$BK$49)<3,"n.m.",E17+MAX(0,E9-E8)) -> 11.962876 | F18: =IF(AVERAGEIF(Engine_Monthly!$D$7:$BK$7,F$4,Engine_Monthly!$D$49:$BK$49)<3,"n.m.",F17+MAX(0,F9-F8)) -> 10.788899 | G18: =IF(AVERAGEIF(Engine_Monthly!$D$7:$BK$7,G$4,Engine_Monthly!$D$49:$BK$49)<3,"n.m.",G17+MAX(0,G9-G8)) -> 10.343476
A20: RETENTION
A21: Annual logo churn | B21: % | C21: =MIN(0.95,Inputs!$C$50*Inputs!$C$127) -> 0.09 | D21: =MIN(0.95,Inputs!$C$50*Inputs!$C$127) -> 0.09 | E21: =MIN(0.95,Inputs!$C$50*Inputs!$C$127) -> 0.09 | F21: =MIN(0.95,Inputs!$C$50*Inputs!$C$127) -> 0.09 | G21: =MIN(0.95,Inputs!$C$50*Inputs!$C$127) -> 0.09 | H21: Unvalidated input.
A22: Gross revenue churn | B22: % | C22: =C21 -> 0.09 | D22: =D21 -> 0.09 | E22: =E21 -> 0.09 | F22: =F21 -> 0.09 | G22: =G21 -> 0.09 | H22: Equal to logo churn (no size bias assumed).
A23: Net revenue retention | B23: % | C23: =(1-C21)*(1+Inputs!$C$49+Inputs!$C$48) -> 1.0465 | D23: =(1-D21)*(1+Inputs!$C$49+Inputs!$C$48) -> 1.0465 | E23: =(1-E21)*(1+Inputs!$C$49+Inputs!$C$48) -> 1.0465 | F23: =(1-F21)*(1+Inputs!$C$49+Inputs!$C$48) -> 1.0465 | G23: =(1-G21)*(1+Inputs!$C$49+Inputs!$C$48) -> 1.0465
A25: LIFETIME VALUE & PAYBACK
A26: Annual survival ÷ (1 + discount rate) | B26: x | C26: =(1-C21)/(1+Inputs!$C$14) -> 0.75833333 | D26: =(1-D21)/(1+Inputs!$C$14) -> 0.75833333 | E26: =(1-E21)/(1+Inputs!$C$14) -> 0.75833333 | F26: =(1-F21)/(1+Inputs!$C$14) -> 0.75833333 | G26: =(1-G21)/(1+Inputs!$C$14) -> 0.75833333
A27: LTV (discounted SaaS gross profit, capped life + net implementation margin) | B27: ₹ lakh | C27: =IF(AVERAGEIF(Engine_Monthly!$D$7:$BK$7,C$4,Engine_Monthly!$D$49:$BK$49)<3,"n.m.",C11*(1-C26^Inputs!$C$15)/(1-C26)/(1+Inputs!$C$14)+(C8-C9)) -> n.m. | D27: =IF(AVERAGEIF(Engine_Monthly!$D$7:$BK$7,D$4,Engine_Monthly!$D$49:$BK$49)<3,"n.m.",D11*(1-D26^Inputs!$C$15)/(1-D26)/(1+Inputs!$C$14)+(D8-D9)) -> 46.240472 | E27: =IF(AVERAGEIF(Engine_Monthly!$D$7:$BK$7,E$4,Engine_Monthly!$D$49:$BK$49)<3,"n.m.",E11*(1-E26^Inputs!$C$15)/(1-E26)/(1+Inputs!$C$14)+(E8-E9)) -> 76.878186 | F27: =IF(AVERAGEIF(Engine_Monthly!$D$7:$BK$7,F$4,Engine_Monthly!$D$49:$BK$49)<3,"n.m.",F11*(1-F26^Inputs!$C$15)/(1-F26)/(1+Inputs!$C$14)+(F8-F9)) -> 89.481784 | G27: =IF(AVERAGEIF(Engine_Monthly!$D$7:$BK$7,G$4,Engine_Monthly!$D$49:$BK$49)<3,"n.m.",G11*(1-G26^Inputs!$C$15)/(1-G26)/(1+Inputs!$C$14)+(G8-G9)) -> 99.817619 | H27: LTV = GP/plant × Σ (survival/(1+r))^t for t ≤ life cap. No expansion included (prudent).
A28: LTV / CAC | B28: x | C28: =IF(AVERAGEIF(Engine_Monthly!$D$7:$BK$7,C$4,Engine_Monthly!$D$49:$BK$49)<3,"n.m.",IFERROR(C27/C17,0)) -> n.m. | D28: =IF(AVERAGEIF(Engine_Monthly!$D$7:$BK$7,D$4,Engine_Monthly!$D$49:$BK$49)<3,"n.m.",IFERROR(D27/D17,0)) -> 3.5571747 | E28: =IF(AVERAGEIF(Engine_Monthly!$D$7:$BK$7,E$4,Engine_Monthly!$D$49:$BK$49)<3,"n.m.",IFERROR(E27/E17,0)) -> 7.1231781 | F28: =IF(AVERAGEIF(Engine_Monthly!$D$7:$BK$7,F$4,Engine_Monthly!$D$49:$BK$49)<3,"n.m.",IFERROR(F27/F17,0)) -> 8.7546108 | G28: =IF(AVERAGEIF(Engine_Monthly!$D$7:$BK$7,G$4,Engine_Monthly!$D$49:$BK$49)<3,"n.m.",IFERROR(G27/G17,0)) -> 9.924154 | H28: ≥3x is the usual investor bar.
A29: CAC payback | B29: months | C29: =IF(AVERAGEIF(Engine_Monthly!$D$7:$BK$7,C$4,Engine_Monthly!$D$49:$BK$49)<3,"n.m.",IFERROR(C17/(C11/12),0)) -> n.m. | D29: =IF(AVERAGEIF(Engine_Monthly!$D$7:$BK$7,D$4,Engine_Monthly!$D$49:$BK$49)<3,"n.m.",IFERROR(D17/(D11/12),0)) -> 9.4132897 | E29: =IF(AVERAGEIF(Engine_Monthly!$D$7:$BK$7,E$4,Engine_Monthly!$D$49:$BK$49)<3,"n.m.",IFERROR(E17/(E11/12),0)) -> 4.8967909 | F29: =IF(AVERAGEIF(Engine_Monthly!$D$7:$BK$7,F$4,Engine_Monthly!$D$49:$BK$49)<3,"n.m.",IFERROR(F17/(F11/12),0)) -> 4.0194093 | G29: =IF(AVERAGEIF(Engine_Monthly!$D$7:$BK$7,G$4,Engine_Monthly!$D$49:$BK$49)<3,"n.m.",IFERROR(G17/(G11/12),0)) -> 3.5580541 | H29: CAC ÷ monthly SaaS gross profit per plant.
A31: CONTRIBUTION & BREAK-EVEN
A32: Contribution margin (gross profit − S&M) ÷ revenue | B32: % | C32: =IFERROR((7_Financials!C14+7_Financials!C17)/7_Financials!C11,0) -> -3.1025034 | D32: =IFERROR((7_Financials!D14+7_Financials!D17)/7_Financials!D11,0) -> -0.18663271 | E32: =IFERROR((7_Financials!E14+7_Financials!E17)/7_Financials!E11,0) -> 0.31851801 | F32: =IFERROR((7_Financials!F14+7_Financials!F17)/7_Financials!F11,0) -> 0.51876451 | G32: =IFERROR((7_Financials!G14+7_Financials!G17)/7_Financials!G11,0) -> 0.63551477
A33: Live plants needed to cover this year's full cost base | B33: # | C33: =IF(AVERAGEIF(Engine_Monthly!$D$7:$BK$7,C$4,Engine_Monthly!$D$49:$BK$49)<3,"n.m.",IFERROR((SUMIF(Engine_Monthly!$D$7:$BK$7,C$4,Engine_Monthly!$D$137:$BK$137)+SUMIF(Engine_Monthly!$D$7:$BK$7,C$4,Engine_Monthly!$D$75:$BK$75)+SUMIF(Engine_Monthly!$D$7:$BK$7,C$4,Engine_Monthly!$D$83:$BK$83)-SUMIF(Engine_Monthly!$D$7:$BK$7,C$4,Engine_Monthly!$D$61:$BK$61)-SUMIF(Engine_Monthly!$D$7:$BK$7,C$4,Engine_Monthly!$D$62:$BK$62))/(C7-(C10-SUMIF(Engine_Monthly!$D$7:$BK$7,C$4,Engine_Monthly!$D$75:$BK$75)/MAX(1,AVERAGEIF(Engine_Monthly!$D$7:$BK$7,C$4,Engine_Monthly!$D$49:$BK$49)))),0)) -> n.m. | D33: =IF(AVERAGEIF(Engine_Monthly!$D$7:$BK$7,D$4,Engine_Monthly!$D$49:$BK$49)<3,"n.m.",IFERROR((SUMIF(Engine_Monthly!$D$7:$BK$7,D$4,Engine_Monthly!$D$137:$BK$137)+SUMIF(Engine_Monthly!$D$7:$BK$7,D$4,Engine_Monthly!$D$75:$BK$75)+SUMIF(Engine_Monthly!$D$7:$BK$7,D$4,Engine_Monthly!$D$83:$BK$83)-SUMIF(Engine_Monthly!$D$7:$BK$7,D$4,Engine_Monthly!$D$61:$BK$61)-SUMIF(Engine_Monthly!$D$7:$BK$7,D$4,Engine_Monthly!$D$62:$BK$62))/(D7-(D10-SUMIF(Engine_Monthly!$D$7:$BK$7,D$4,Engine_Monthly!$D$75:$BK$75)/MAX(1,AVERAGEIF(Engine_Monthly!$D$7:$BK$7,D$4,Engine_Monthly!$D$49:$BK$49)))),0)) -> 25.510706 | E33: =IF(AVERAGEIF(Engine_Monthly!$D$7:$BK$7,E$4,Engine_Monthly!$D$49:$BK$49)<3,"n.m.",IFERROR((SUMIF(Engine_Monthly!$D$7:$BK$7,E$4,Engine_Monthly!$D$137:$BK$137)+SUMIF(Engine_Monthly!$D$7:$BK$7,E$4,Engine_Monthly!$D$75:$BK$75)+SUMIF(Engine_Monthly!$D$7:$BK$7,E$4,Engine_Monthly!$D$83:$BK$83)-SUMIF(Engine_Monthly!$D$7:$BK$7,E$4,Engine_Monthly!$D$61:$BK$61)-SUMIF(Engine_Monthly!$D$7:$BK$7,E$4,Engine_Monthly!$D$62:$BK$62))/(E7-(E10-SUMIF(Engine_Monthly!$D$7:$BK$7,E$4,Engine_Monthly!$D$75:$BK$75)/MAX(1,AVERAGEIF(Engine_Monthly!$D$7:$BK$7,E$4,Engine_Monthly!$D$49:$BK$49)))),0)) -> 34.278307 | F33: =IF(AVERAGEIF(Engine_Monthly!$D$7:$BK$7,F$4,Engine_Monthly!$D$49:$BK$49)<3,"n.m.",IFERROR((SUMIF(Engine_Monthly!$D$7:$BK$7,F$4,Engine_Monthly!$D$137:$BK$137)+SUMIF(Engine_Monthly!$D$7:$BK$7,F$4,Engine_Monthly!$D$75:$BK$75)+SUMIF(Engine_Monthly!$D$7:$BK$7,F$4,Engine_Monthly!$D$83:$BK$83)-SUMIF(Engine_Monthly!$D$7:$BK$7,F$4,Engine_Monthly!$D$61:$BK$61)-SUMIF(Engine_Monthly!$D$7:$BK$7,F$4,Engine_Monthly!$D$62:$BK$62))/(F7-(F10-SUMIF(Engine_Monthly!$D$7:$BK$7,F$4,Engine_Monthly!$D$75:$BK$75)/MAX(1,AVERAGEIF(Engine_Monthly!$D$7:$BK$7,F$4,Engine_Monthly!$D$49:$BK$49)))),0)) -> 48.364806 | G33: =IF(AVERAGEIF(Engine_Monthly!$D$7:$BK$7,G$4,Engine_Monthly!$D$49:$BK$49)<3,"n.m.",IFERROR((SUMIF(Engine_Monthly!$D$7:$BK$7,G$4,Engine_Monthly!$D$137:$BK$137)+SUMIF(Engine_Monthly!$D$7:$BK$7,G$4,Engine_Monthly!$D$75:$BK$75)+SUMIF(Engine_Monthly!$D$7:$BK$7,G$4,Engine_Monthly!$D$83:$BK$83)-SUMIF(Engine_Monthly!$D$7:$BK$7,G$4,Engine_Monthly!$D$61:$BK$61)-SUMIF(Engine_Monthly!$D$7:$BK$7,G$4,Engine_Monthly!$D$62:$BK$62))/(G7-(G10-SUMIF(Engine_Monthly!$D$7:$BK$7,G$4,Engine_Monthly!$D$75:$BK$75)/MAX(1,AVERAGEIF(Engine_Monthly!$D$7:$BK$7,G$4,Engine_Monthly!$D$49:$BK$49)))),0)) -> 62.889947 | H33: (Opex + fixed platform + net deployment cost) ÷ variable SaaS gross profit per plant.
A34: Live plants at year end (model) | B34: # | C34: =INDEX(Engine_Monthly!$D$49:$BK$49,1,C$4*12) -> 1.0609353 | D34: =INDEX(Engine_Monthly!$D$49:$BK$49,1,D$4*12) -> 17.598591 | E34: =INDEX(Engine_Monthly!$D$49:$BK$49,1,E$4*12) -> 77.249595 | F34: =INDEX(Engine_Monthly!$D$49:$BK$49,1,F$4*12) -> 203.40003 | G34: =INDEX(Engine_Monthly!$D$49:$BK$49,1,G$4*12) -> 400.00001
A35: Customer break-even: months of SaaS gross profit to recover CAC + net deployment | B35: months | C35: =IF(AVERAGEIF(Engine_Monthly!$D$7:$BK$7,C$4,Engine_Monthly!$D$49:$BK$49)<3,"n.m.",IFERROR(C18/(C11/12),0)) -> n.m. | D35: =IF(AVERAGEIF(Engine_Monthly!$D$7:$BK$7,D$4,Engine_Monthly!$D$49:$BK$49)<3,"n.m.",IFERROR(D18/(D11/12),0)) -> 11.340222 | E35: =IF(AVERAGEIF(Engine_Monthly!$D$7:$BK$7,E$4,Engine_Monthly!$D$49:$BK$49)<3,"n.m.",IFERROR(E18/(E11/12),0)) -> 5.4277249 | F35: =IF(AVERAGEIF(Engine_Monthly!$D$7:$BK$7,F$4,Engine_Monthly!$D$49:$BK$49)<3,"n.m.",IFERROR(F18/(F11/12),0)) -> 4.2426926 | G35: =IF(AVERAGEIF(Engine_Monthly!$D$7:$BK$7,G$4,Engine_Monthly!$D$49:$BK$49)<3,"n.m.",IFERROR(G18/(G11/12),0)) -> 3.6590247
A37: n.m. = not meaningful while fewer than 3 plants are live on average.

Sheet 9_Customer_ROI
A1: 9. CUSTOMER ROI & VALUE REALISATION (illustrative ₹200-600 crore auto-component plants, rescaled 11-Oct-2026; all inputs editable)
A2: Rule applied: lost revenue is NOT profit. Only contribution on output that can actually be sold, plus cash costs actually avoided, count as benefit.
A4: Input / calculation | B4: Unit | C4: Low | D4: Base | E4: High | G4: Basis and anti-double-counting note
A6: A. PLANT PROFILE
A7: Plant annual revenue | B7: ₹ lakh | C7: 20000 | D7: 40000 | E7: 60000 | G7: v4: rescaled to ₹200 / 400 / 600 crore plants (was 80 / 120 / 150) so the base case passes the 3x value rule at ₹15-50 lakh pricing (team decision). Cost buckets below scaled by the same ratio. Unvalidated; see 16_SOM_Scenarios flags on plant size.
A8: Annual production hours (plant level) | B8: hours | C8: 4800 | D8: 5000 | E8: 6000 | G8: 2-3 shifts × ~300 days.
A9: Revenue per production hour | B9: ₹ lakh/hr | C9: =C7/C8 -> 4.1666667 | D9: =D7/D8 -> 8 | E9: =E7/E8 -> 10
A10: Plant-level output hours lost to unplanned critical-machine disruption | B10: hours | C10: 100 | D10: 150 | E10: 200 | G10: Only bottleneck downtime that actually stops plant output (2-4% of hours). Validate from plant downtime logs.
A11: Contribution margin on incremental output | B11: % | C11: 0.2 | D11: 0.25 | E11: 0.3 | G11: Price minus material, energy, variable labour. Not EBITDA, not revenue.
A12: Baseline on-time delivery (context) | B12: % | C12: 0.85 | D12: 0.88 | E12: 0.9 | G12: Non-monetary KPI; tracked, not monetised here.
A14: B. BASELINE ANNUAL DISRUPTION COSTS (cash, already net of recovery)
A15: Disruption-related overtime | B15: ₹ lakh | C15: 60 | D15: 135 | E15: 240 | G15: Overtime spent to recover output. Baseline lost hours are AFTER this recovery, so no overlap. v4: scaled with plant revenue.
A16: Expedited freight & customer delivery penalties | B16: ₹ lakh | C16: 40 | D16: 85 | E16: 160 | G16: Costs on orders still delivered (late). Separate from lost sales. v4: scaled with plant revenue.
A17: Scrap & rework caused by failures / restarts | B17: ₹ lakh | C17: 50 | D17: 100 | E17: 180 | G17: Only failure-induced quality loss. v4: scaled with plant revenue.
A18: Subcontracting / alternative production arrangements | B18: ₹ lakh | C18: 25 | D18: 65 | E18: 120 | G18: v4: scaled with plant revenue.
A19: Emergency maintenance premium (vs planned) | B19: ₹ lakh | C19: 75 | D19: 165 | E19: 280 | G19: Rush parts, call-out technicians. v4: scaled with plant revenue.
A21: C. IMPROVEMENT ATTRIBUTABLE TO THE PLATFORM (unproven; the crux of the pitch)
A22: Reduction in lost output hours | B22: % | C22: 0.1 | D22: 0.2 | E22: 0.3 | G22: From better job shifting/resequencing and maintenance timing. Must be proven in pilots.
A23: Share of recovered output that can actually be sold | B23: % | C23: 0.4 | D23: 0.6 | E23: 0.8 | G23: Requires demand, material, labour and quality to be available.
A24: Reduction in disruption overtime | B24: % | C24: 0.1 | D24: 0.2 | E24: 0.3
A25: Reduction in expedite & penalty cost | B25: % | C25: 0.1 | D25: 0.2 | E25: 0.3
A26: Reduction in failure-induced scrap | B26: % | C26: 0.05 | D26: 0.1 | E26: 0.15
A27: Reduction in subcontracting | B27: % | C27: 0.05 | D27: 0.15 | E27: 0.25
A28: Reduction in emergency maintenance premium | B28: % | C28: 0.05 | D28: 0.1 | E28: 0.2 | G28: Predictive signal lets some repairs be planned.
A29: Share of steady-state benefit achieved in year 1 | B29: % | C29: 0.3 | D29: 0.5 | E29: 0.6 | G29: Go-live lag, learning curve, trust building.
A31: D. BENEFITS (kept in separate buckets; only rows marked ✓ are summed)
A32: 1. Lost revenue avoided (memo only, NOT a benefit) | B32: ₹ lakh | C32: =C10*C22*C9*C23 -> 16.666667 | D32: =D10*D22*D9*D23 -> 144 | E32: =E10*E22*E9*E23 -> 480 | G32: Shown to prevent the classic error of counting revenue as savings.
A33: 2. ✓ Incremental contribution on saleable recovered output | B33: ₹ lakh | C33: =C32*C11 -> 3.3333333 | D33: =D32*D11 -> 36 | E33: =E32*E11 -> 144 | G33: Revenue avoided × contribution margin.
A34: 3. ✓ Cash costs avoided | B34: ₹ lakh | C34: =C15*C24+C16*C25+C17*C26+C18*C27+C19*C28 -> 17.5 | D34: =D15*D24+D16*D25+D17*D26+D18*D27+D19*D28 -> 80.25 | E34: =E15*E24+E16*E25+E17*E26+E18*E27+E19*E28 -> 233 | G34: Overtime, expedite/penalties, scrap, subcontracting, emergency maintenance.
A35: 4. Working-capital / inventory benefit | B35: ₹ lakh | C35: 0 | D35: 0 | E35: 0 | G35: Set to zero: not supportable without plant data (could come from lower safety stock).
A36: 5. Non-monetary benefits | B36: text | C36: OTD, planner time, fewer firefights | G36: Real but not monetised.
A37: Gross annual benefit (steady state) | B37: ₹ lakh | C37: =C33+C34+C35 -> 20.833333 | D37: =D33+D34+D35 -> 116.25 | E37: =E33+E34+E35 -> 377
A39: E. CUSTOMER COSTS
A40: Annual subscription (Professional tier, model list price) | B40: ₹ lakh | C40: =3_Pricing!$D$8*Inputs!$C$47 -> 30 | D40: =3_Pricing!$D$8*Inputs!$C$47 -> 30 | E40: =3_Pricing!$D$8*Inputs!$C$47 -> 30 | G40: Linked to 3_Pricing.
A41: One-time implementation fee | B41: ₹ lakh | C41: =3_Pricing!$D$10 -> 6 | D41: =3_Pricing!$D$10 -> 6 | E41: =3_Pricing!$D$10 -> 6
A42: Customer's internal effort (IT, planner time, data clean-up) | B42: ₹ lakh p.a. | C42: 3 | D42: 2 | E42: 1.5 | G42: Often ignored; counts against ROI.
A43: IoT kit (only if machine data not readable) | B43: ₹ lakh | C43: =Inputs!$C$43*(1+Inputs!$C$44) -> 3.85 | D43: 0 | E43: 0 | G43: Low case assumes the plant needs the kit.
A45: F. RETURNS
A46: Net annual benefit, steady state | B46: ₹ lakh | C46: =C37-C40-C42 -> -12.166667 | D46: =D37-D40-D42 -> 84.25 | E46: =E37-E40-E42 -> 345.5
A47: Year-1 benefit (ramped) | B47: ₹ lakh | C47: =C37*C29 -> 6.25 | D47: =D37*D29 -> 58.125 | E47: =E37*E29 -> 226.2
A48: Year-1 total cost | B48: ₹ lakh | C48: =C40+C41+C42+C43 -> 42.85 | D48: =D40+D41+D42+D43 -> 38 | E48: =E40+E41+E42+E43 -> 37.5
A49: First-year ROI | B49: % | C49: =IFERROR(C47/C48-1,0) -> -0.85414236 | D49: =IFERROR(D47/D48-1,0) -> 0.52960526 | E49: =IFERROR(E47/E48-1,0) -> 5.032
A50: Steady-state ROI (on annual recurring cost) | B50: % | C50: =IFERROR(C37/(C40+C42)-1,0) -> -0.36868687 | D50: =IFERROR(D37/(D40+D42)-1,0) -> 2.6328125 | E50: =IFERROR(E37/(E40+E42)-1,0) -> 10.968254
A51: Payback of one-time costs (implementation + kit), with year-1 ramp | B51: months | C51: =IFERROR(IF(C46<=0,"No payback",IF(AND((C47-C40-C42)>0,(C41+C43)/((C47-C40-C42)/12)<=12),(C41+C43)/((C47-C40-C42)/12),12+((C41+C43)-MAX(0,C47-C40-C42))/(C46/12))),"No payback") -> No payback | D51: =IFERROR(IF(D46<=0,"No payback",IF(AND((D47-D40-D42)>0,(D41+D43)/((D47-D40-D42)/12)<=12),(D41+D43)/((D47-D40-D42)/12),12+((D41+D43)-MAX(0,D47-D40-D42))/(D46/12))),"No payback") -> 2.7559809 | E51: =IFERROR(IF(E46<=0,"No payback",IF(AND((E47-E40-E42)>0,(E41+E43)/((E47-E40-E42)/12)<=12),(E41+E43)/((E47-E40-E42)/12),12+((E41+E43)-MAX(0,E47-E40-E42))/(E46/12))),"No payback") -> 0.36979969 | G51: Year-1 net benefit uses the ramp; after month 12 the steady-state net benefit applies.
A52: Gross benefit ÷ subscription price | B52: x | C52: =IFERROR(C37/C40,0) -> 0.69444444 | D52: =IFERROR(D37/D40,0) -> 3.875 | E52: =IFERROR(E37/E40,0) -> 12.566667 | G52: Mid-market buyers typically want ≥3x visible value before a new software line item.
A53: Maximum defensible subscription at a 3x value rule | B53: ₹ lakh p.a. | C53: =C37/3 -> 6.9444444 | D53: =D37/3 -> 38.75 | E53: =E37/3 -> 125.66667
A54: Price test | C54: =IF(C53>=C40,"Price supportable","Price too high for this value") -> Price too high for this value | D54: =IF(D53>=D40,"Price supportable","Price too high for this value") -> Price supportable | E54: =IF(E53>=E40,"Price supportable","Price too high for this value") -> Price supportable
A55: Double-count check: gross = contribution + cash + WC (excludes revenue) | C55: =IF(ABS(C37-(C33+C34+C35))<0.001,"OK","CHECK") -> OK | D55: =IF(ABS(D37-(D33+D34+D35))<0.001,"OK","CHECK") -> OK | E55: =IF(ABS(E37-(E33+E34+E35))<0.001,"OK","CHECK") -> OK

Sheet 10_GTM
A1: 10. SALES CAPACITY & GO-TO-MARKET ECONOMICS
A2: Beachhead: mid-sized auto-component, metal, machinery, plastics and electrical plants in the top-5 manufacturing states (Tamil Nadu, Gujarat, Maharashtra, Uttar Pradesh, Karnataka), starting in 4-5 industrial clusters.
A3: ₹ lakh | B3: Unit | C3: =INDEX(Engine_Monthly!$D$10:$BK$10,1,12) -> FY27 | D3: =INDEX(Engine_Monthly!$D$10:$BK$10,1,24) -> FY28 | E3: =INDEX(Engine_Monthly!$D$10:$BK$10,1,36) -> FY29 | F3: =INDEX(Engine_Monthly!$D$10:$BK$10,1,48) -> FY30 | G3: =INDEX(Engine_Monthly!$D$10:$BK$10,1,60) -> FY31
A4: Fiscal-year index | C4: 1 | D4: 2 | E4: 3 | F4: 4 | G4: 5
A6: SALES CAPACITY
A7: Account executives (year end) | B7: heads | C7: =INDEX(Engine_Monthly!$D$13:$BK$13,1,C$4*12) -> 1 | D7: =INDEX(Engine_Monthly!$D$13:$BK$13,1,D$4*12) -> 4 | E7: =INDEX(Engine_Monthly!$D$13:$BK$13,1,E$4*12) -> 10 | F7: =INDEX(Engine_Monthly!$D$13:$BK$13,1,F$4*12) -> 18 | G7: =INDEX(Engine_Monthly!$D$13:$BK$13,1,G$4*12) -> 25
A8: Average effective selling capacity (ramped AEs + founder) | B8: FTE | C8: =AVERAGEIF(Engine_Monthly!$D$7:$BK$7,C$4,Engine_Monthly!$D$17:$BK$17) -> 1.0416667 | D8: =AVERAGEIF(Engine_Monthly!$D$7:$BK$7,D$4,Engine_Monthly!$D$17:$BK$17) -> 3.875 | E8: =AVERAGEIF(Engine_Monthly!$D$7:$BK$7,E$4,Engine_Monthly!$D$17:$BK$17) -> 9 | F8: =AVERAGEIF(Engine_Monthly!$D$7:$BK$7,F$4,Engine_Monthly!$D$17:$BK$17) -> 16.583333 | G8: =AVERAGEIF(Engine_Monthly!$D$7:$BK$7,G$4,Engine_Monthly!$D$17:$BK$17) -> 23.791667
A9: Leads per effective seller per month | B9: # | C9: =IFERROR(SUMIF(Engine_Monthly!$D$7:$BK$7,C$4,Engine_Monthly!$D$21:$BK$21)*(SUMIF(Engine_Monthly!$D$7:$BK$7,C$4,Engine_Monthly!$D$18:$BK$18)/SUMIF(Engine_Monthly!$D$7:$BK$7,C$4,Engine_Monthly!$D$20:$BK$20))/C8/12,0) -> 15 | D9: =IFERROR(SUMIF(Engine_Monthly!$D$7:$BK$7,D$4,Engine_Monthly!$D$21:$BK$21)*(SUMIF(Engine_Monthly!$D$7:$BK$7,D$4,Engine_Monthly!$D$18:$BK$18)/SUMIF(Engine_Monthly!$D$7:$BK$7,D$4,Engine_Monthly!$D$20:$BK$20))/D8/12,0) -> 15 | E9: =IFERROR(SUMIF(Engine_Monthly!$D$7:$BK$7,E$4,Engine_Monthly!$D$21:$BK$21)*(SUMIF(Engine_Monthly!$D$7:$BK$7,E$4,Engine_Monthly!$D$18:$BK$18)/SUMIF(Engine_Monthly!$D$7:$BK$7,E$4,Engine_Monthly!$D$20:$BK$20))/E8/12,0) -> 15 | F9: =IFERROR(SUMIF(Engine_Monthly!$D$7:$BK$7,F$4,Engine_Monthly!$D$21:$BK$21)*(SUMIF(Engine_Monthly!$D$7:$BK$7,F$4,Engine_Monthly!$D$18:$BK$18)/SUMIF(Engine_Monthly!$D$7:$BK$7,F$4,Engine_Monthly!$D$20:$BK$20))/F8/12,0) -> 15 | G9: =IFERROR(SUMIF(Engine_Monthly!$D$7:$BK$7,G$4,Engine_Monthly!$D$21:$BK$21)*(SUMIF(Engine_Monthly!$D$7:$BK$7,G$4,Engine_Monthly!$D$18:$BK$18)/SUMIF(Engine_Monthly!$D$7:$BK$7,G$4,Engine_Monthly!$D$20:$BK$20))/G8/12,0) -> 15
A10: Qualified opportunities per effective seller per month | B10: # | C10: =IFERROR(SUMIF(Engine_Monthly!$D$7:$BK$7,C$4,Engine_Monthly!$D$18:$BK$18)/C8/12,0) -> 3 | D10: =IFERROR(SUMIF(Engine_Monthly!$D$7:$BK$7,D$4,Engine_Monthly!$D$18:$BK$18)/D8/12,0) -> 3 | E10: =IFERROR(SUMIF(Engine_Monthly!$D$7:$BK$7,E$4,Engine_Monthly!$D$18:$BK$18)/E8/12,0) -> 3 | F10: =IFERROR(SUMIF(Engine_Monthly!$D$7:$BK$7,F$4,Engine_Monthly!$D$18:$BK$18)/F8/12,0) -> 3 | G10: =IFERROR(SUMIF(Engine_Monthly!$D$7:$BK$7,G$4,Engine_Monthly!$D$18:$BK$18)/G8/12,0) -> 3
A11: New contracts per effective seller per year (direct) | B11: # | C11: =IFERROR(SUMIF(Engine_Monthly!$D$7:$BK$7,C$4,Engine_Monthly!$D$30:$BK$30)/C8,0) -> 1.9008 | D11: =IFERROR(SUMIF(Engine_Monthly!$D$7:$BK$7,D$4,Engine_Monthly!$D$30:$BK$30)/D8,0) -> 3.5767742 | E11: =IFERROR(SUMIF(Engine_Monthly!$D$7:$BK$7,E$4,Engine_Monthly!$D$30:$BK$30)/E8,0) -> 4.0425 | F11: =IFERROR(SUMIF(Engine_Monthly!$D$7:$BK$7,F$4,Engine_Monthly!$D$30:$BK$30)/F8,0) -> 4.5072362 | G11: =IFERROR(SUMIF(Engine_Monthly!$D$7:$BK$7,G$4,Engine_Monthly!$D$30:$BK$30)/G8,0) -> 5.0661646 | H11: Lagged: this year's contracts come partly from last year's pipeline.
A13: ROUTE ECONOMICS
A14: Contracts: direct | B14: # | C14: =SUMIF(Engine_Monthly!$D$7:$BK$7,C$4,Engine_Monthly!$D$30:$BK$30) -> 1.98 | D14: =SUMIF(Engine_Monthly!$D$7:$BK$7,D$4,Engine_Monthly!$D$30:$BK$30) -> 13.86 | E14: =SUMIF(Engine_Monthly!$D$7:$BK$7,E$4,Engine_Monthly!$D$30:$BK$30) -> 36.3825 | F14: =SUMIF(Engine_Monthly!$D$7:$BK$7,F$4,Engine_Monthly!$D$30:$BK$30) -> 74.745 | G14: =SUMIF(Engine_Monthly!$D$7:$BK$7,G$4,Engine_Monthly!$D$30:$BK$30) -> 120.5325
A15: Contracts: partner | B15: # | C15: =SUMIF(Engine_Monthly!$D$7:$BK$7,C$4,Engine_Monthly!$D$31:$BK$31) -> 0 | D15: =SUMIF(Engine_Monthly!$D$7:$BK$7,D$4,Engine_Monthly!$D$31:$BK$31) -> 9.7193897 | E15: =SUMIF(Engine_Monthly!$D$7:$BK$7,E$4,Engine_Monthly!$D$31:$BK$31) -> 38.877559 | F15: =SUMIF(Engine_Monthly!$D$7:$BK$7,F$4,Engine_Monthly!$D$31:$BK$31) -> 77.755117 | G15: =SUMIF(Engine_Monthly!$D$7:$BK$7,G$4,Engine_Monthly!$D$31:$BK$31) -> 116.63268
A16: Partner share of new contracts | B16: % | C16: =IFERROR(C15/(C14+C15),0) -> 0 | D16: =IFERROR(D15/(D14+D15),0) -> 0.41219853 | E16: =IFERROR(E15/(E14+E15),0) -> 0.51657625 | F16: =IFERROR(F15/(F14+F15),0) -> 0.50986923 | G16: =IFERROR(G15/(G14+G15),0) -> 0.49177825
A17: Direct acquisition cost (S&M excl. channel cost) | B17: ₹ lakh | C17: =SUMIF(Engine_Monthly!$D$7:$BK$7,C$4,Engine_Monthly!$D$129:$BK$129)-SUMIF(Engine_Monthly!$D$7:$BK$7,C$4,Engine_Monthly!$D$128:$BK$128)-SUMIF(Engine_Monthly!$D$7:$BK$7,C$4,Engine_Monthly!$D$31:$BK$31)*Inputs!$C$89*AVERAGEIF(Engine_Monthly!$D$7:$BK$7,C$4,Engine_Monthly!$D$50:$BK$50) -> 72.354 | D17: =SUMIF(Engine_Monthly!$D$7:$BK$7,D$4,Engine_Monthly!$D$129:$BK$129)-SUMIF(Engine_Monthly!$D$7:$BK$7,D$4,Engine_Monthly!$D$128:$BK$128)-SUMIF(Engine_Monthly!$D$7:$BK$7,D$4,Engine_Monthly!$D$31:$BK$31)*Inputs!$C$89*AVERAGEIF(Engine_Monthly!$D$7:$BK$7,D$4,Engine_Monthly!$D$50:$BK$50) -> 228.9327 | E17: =SUMIF(Engine_Monthly!$D$7:$BK$7,E$4,Engine_Monthly!$D$129:$BK$129)-SUMIF(Engine_Monthly!$D$7:$BK$7,E$4,Engine_Monthly!$D$128:$BK$128)-SUMIF(Engine_Monthly!$D$7:$BK$7,E$4,Engine_Monthly!$D$31:$BK$31)*Inputs!$C$89*AVERAGEIF(Engine_Monthly!$D$7:$BK$7,E$4,Engine_Monthly!$D$50:$BK$50) -> 545.95336 | F17: =SUMIF(Engine_Monthly!$D$7:$BK$7,F$4,Engine_Monthly!$D$129:$BK$129)-SUMIF(Engine_Monthly!$D$7:$BK$7,F$4,Engine_Monthly!$D$128:$BK$128)-SUMIF(Engine_Monthly!$D$7:$BK$7,F$4,Engine_Monthly!$D$31:$BK$31)*Inputs!$C$89*AVERAGEIF(Engine_Monthly!$D$7:$BK$7,F$4,Engine_Monthly!$D$50:$BK$50) -> 1020.3175 | G17: =SUMIF(Engine_Monthly!$D$7:$BK$7,G$4,Engine_Monthly!$D$129:$BK$129)-SUMIF(Engine_Monthly!$D$7:$BK$7,G$4,Engine_Monthly!$D$128:$BK$128)-SUMIF(Engine_Monthly!$D$7:$BK$7,G$4,Engine_Monthly!$D$31:$BK$31)*Inputs!$C$89*AVERAGEIF(Engine_Monthly!$D$7:$BK$7,G$4,Engine_Monthly!$D$50:$BK$50) -> 1548.3751
A18: Cost per acquired customer: direct | B18: ₹ lakh | C18: =IFERROR(C17/C14,0) -> 36.542424 | D18: =IFERROR(D17/D14,0) -> 16.517511 | E18: =IFERROR(E17/E14,0) -> 15.005933 | F18: =IFERROR(F17/F14,0) -> 13.650645 | G18: =IFERROR(G17/G14,0) -> 12.846121
A19: Channel commissions + partner programme | B19: ₹ lakh | C19: =SUMIF(Engine_Monthly!$D$7:$BK$7,C$4,Engine_Monthly!$D$128:$BK$128)+SUMIF(Engine_Monthly!$D$7:$BK$7,C$4,Engine_Monthly!$D$31:$BK$31)*Inputs!$C$89*AVERAGEIF(Engine_Monthly!$D$7:$BK$7,C$4,Engine_Monthly!$D$50:$BK$50) -> 0 | D19: =SUMIF(Engine_Monthly!$D$7:$BK$7,D$4,Engine_Monthly!$D$128:$BK$128)+SUMIF(Engine_Monthly!$D$7:$BK$7,D$4,Engine_Monthly!$D$31:$BK$31)*Inputs!$C$89*AVERAGEIF(Engine_Monthly!$D$7:$BK$7,D$4,Engine_Monthly!$D$50:$BK$50) -> 77.580815 | E19: =SUMIF(Engine_Monthly!$D$7:$BK$7,E$4,Engine_Monthly!$D$128:$BK$128)+SUMIF(Engine_Monthly!$D$7:$BK$7,E$4,Engine_Monthly!$D$31:$BK$31)*Inputs!$C$89*AVERAGEIF(Engine_Monthly!$D$7:$BK$7,E$4,Engine_Monthly!$D$50:$BK$50) -> 266.30442 | F19: =SUMIF(Engine_Monthly!$D$7:$BK$7,F$4,Engine_Monthly!$D$128:$BK$128)+SUMIF(Engine_Monthly!$D$7:$BK$7,F$4,Engine_Monthly!$D$31:$BK$31)*Inputs!$C$89*AVERAGEIF(Engine_Monthly!$D$7:$BK$7,F$4,Engine_Monthly!$D$50:$BK$50) -> 538.40204 | G19: =SUMIF(Engine_Monthly!$D$7:$BK$7,G$4,Engine_Monthly!$D$128:$BK$128)+SUMIF(Engine_Monthly!$D$7:$BK$7,G$4,Engine_Monthly!$D$31:$BK$31)*Inputs!$C$89*AVERAGEIF(Engine_Monthly!$D$7:$BK$7,G$4,Engine_Monthly!$D$50:$BK$50) -> 837.04366
A20: Cost per acquired customer: partner (marginal) | B20: ₹ lakh | C20: =IFERROR(C19/C15,0) -> 0 | D20: =IFERROR(D19/D15,0) -> 7.9820665 | E20: =IFERROR(E19/E15,0) -> 6.8498237 | F20: =IFERROR(F19/F15,0) -> 6.9243293 | G20: =IFERROR(G19/G15,0) -> 7.1767508 | H20: Marginal only: partner deals still use founder/pre-sales time not allocated here.
A21: Partner-generated new ARR | B21: ₹ lakh | C21: =C15*AVERAGEIF(Engine_Monthly!$D$7:$BK$7,C$4,Engine_Monthly!$D$50:$BK$50) -> 0 | D21: =D15*AVERAGEIF(Engine_Monthly!$D$7:$BK$7,D$4,Engine_Monthly!$D$50:$BK$50) -> 293.40408 | E21: =E15*AVERAGEIF(Engine_Monthly!$D$7:$BK$7,E$4,Engine_Monthly!$D$50:$BK$50) -> 1232.2971 | F21: =F15*AVERAGEIF(Engine_Monthly!$D$7:$BK$7,F$4,Engine_Monthly!$D$50:$BK$50) -> 2587.824 | G21: =G15*AVERAGEIF(Engine_Monthly!$D$7:$BK$7,G$4,Engine_Monthly!$D$50:$BK$50) -> 4075.8227
A23: TIME TO SCALE
A24: Closing ARR | B24: ₹ lakh | C24: =INDEX(Engine_Monthly!$D$56:$BK$56,1,C$4*12) -> 30.996799 | D24: =INDEX(Engine_Monthly!$D$56:$BK$56,1,D$4*12) -> 552.94498 | E24: =INDEX(Engine_Monthly!$D$56:$BK$56,1,E$4*12) -> 2619.6435 | F24: =INDEX(Engine_Monthly!$D$56:$BK$56,1,F$4*12) -> 7429.6244 | G24: =INDEX(Engine_Monthly!$D$56:$BK$56,1,G$4*12) -> 15745.778
A25: Month ARR first reaches ₹10 crore | B25: month # | C25: =IF(COUNT(Engine_Monthly!$D$179:$BK$179)=0,"Not in 5 yrs",MIN(Engine_Monthly!$D$179:$BK$179)) -> 28
A28: Channel options compared (qualitative assumptions, to be tested)
A29: Route | B29: Cycle | C29: Conversion | D29: Cost to acquire | E29: Partner economics | F29: Scalability | H29: Verdict
A30: Direct founder + AE sales | B30: Long (6-9 mo) | C30: Medium | D30: High | E30: n/a | F30: Low-medium | H30: Mandatory for first 10-15 reference plants.
A31: Industrial automation integrators (PLC/SCADA SIs) | B31: Medium | C31: Higher (trusted) | D31: Low-medium | E31: 15-25% of yr-1 ACV; may want services | F31: High | H31: BEST second route once a reference site exists.
A32: Machine-tool OEMs (CNC, presses) | B32: Long (OEM product cycles) | C32: Low-medium | D32: Low per deal, high to sign | E32: Revenue share/bundling | F32: High if signed | H32: Pursue for FY29+; slow to negotiate.
A33: ERP/MES implementation partners | B33: Medium | C33: Medium | D33: Medium | E33: Referral fee | F33: Medium | H33: Useful for Enterprise tier only.
A34: Manufacturing associations / clusters (ACMA, local chambers) | B34: Short to first meeting | C34: Low | D34: Low | E34: Event sponsorship | F34: Medium | H34: Lead source, not a sales channel.
A35: Industrial technology distributors | B35: Medium | C35: Low | D35: Low | E35: Margin on resale | F35: Medium | H35: Weak fit: product needs consultative selling.
A37: Recommendation: founder-led direct sales to land 10-15 reference plants in one cluster; from FY28 build an SI and machine-tool OEM partner channel (about 8 active partners by FY29 and 15-20 by FY31, each sourcing ~0.4 qualified opportunities a month). Associations are a lead source only.

Sheet 11_Funding
A1: 11. FUNDING REQUIREMENT & CAPITAL STRUCTURE
A2: Sized from the monthly cash forecast. No valuation or investor return is assumed.
A4: A. CASH NEED (pre-financing)
A5: Peak cumulative cash deficit (operating + investing) | B5: ₹ lakh | C5: =-MIN(0,MIN(Engine_Monthly!$D$166:$BK$166)) -> 692.94953
A6: Month of peak deficit | B6: month # | C6: =MATCH(MIN(Engine_Monthly!$D$166:$BK$166),Engine_Monthly!$D$166:$BK$166,0) -> 28
A7: Peak monthly burn | B7: ₹ lakh | C7: =MAX(Engine_Monthly!$D$167:$BK$167) -> 51.003252
A8: Average monthly burn, first 12 months | B8: ₹ lakh | C8: =SUMIF(Engine_Monthly!$D$6:$BK$6,"<=12",Engine_Monthly!$D$167:$BK$167)/12 -> 18.650509
A9: Minimum cash buffer | B9: ₹ lakh | C9: =Inputs!$C$118*C7 -> 306.01951 | H9: Months of peak burn (Inputs).
A10: Contingency | B10: ₹ lakh | C10: =C5*Inputs!$C$119 -> 103.94243
A11: TOTAL EQUITY REQUIREMENT (5 years) | B11: ₹ lakh | C11: =C5+C9+C10 -> 1102.9115
A12: in ₹ crore | B12: ₹ crore | C12: =C11/100 -> 11.029115
A14: B. STAGING
A15: Seed requirement: deficit to Series A month + buffer + contingency | B15: ₹ lakh | C15: =-MIN(0,MIN(OFFSET(Engine_Monthly!$D$166,0,0,1,Inputs!$C$120)))*(1+Inputs!$C$119)+Inputs!$C$118*MAX(OFFSET(Engine_Monthly!$D$167,0,0,1,Inputs!$C$120)) -> 971.57586 | H15: Buffer here uses the peak burn inside the seed period, not the later, larger burn.
A16: Seed modelled (Inputs) | B16: ₹ lakh | C16: =Inputs!$C$108 -> 900
A17: Runway on seed alone | B17: months | C17: =IF(COUNT(Engine_Monthly!$D$177:$BK$177)=0,60,MIN(Engine_Monthly!$D$177:$BK$177)-1) -> 60 | H17: Months before seed cash runs out if no further capital arrives.
A18: Follow-on requirement (total − seed) | B18: ₹ lakh | C18: =MAX(0,C11-C16) -> 202.91147
A19: Series A modelled (Inputs) | B19: ₹ lakh | C19: =Inputs!$C$110 -> 900
A20: Total equity modelled | B20: ₹ lakh | C20: =Inputs!$C$108+Inputs!$C$110+Inputs!$C$112 -> 1800
A21: Lowest month-end cash in model | B21: ₹ lakh | C21: =MIN(Engine_Monthly!$D$165:$BK$165) -> 321.25535
A22: Funding check: cash never negative | C22: =IF(C21>=0,"OK","SHORTFALL") -> OK
A23: Buffer check: lowest cash ≥ 3 months of peak burn | C23: =IF(C21>=3*C7,"OK","THIN") -> OK
A25: C. USE OF FUNDS DURING SEED PERIOD (months 1 to Series A)
A26: Product development (R&D people + tools) | B26: ₹ lakh | C26: =1*(SUMIF(Engine_Monthly!$D$6:$BK$6,"<="&Inputs!$C$120,Engine_Monthly!$D$131:$BK$131)) -> 203.44857
A27: Customer pilots & industrial integrations (deployment cost) | B27: ₹ lakh | C27: =1*(SUMIF(Engine_Monthly!$D$6:$BK$6,"<="&Inputs!$C$120,Engine_Monthly!$D$83:$BK$83)) -> 109.95964
A28: Cloud infrastructure & cybersecurity (cost to serve) | B28: ₹ lakh | C28: =1*(SUMIF(Engine_Monthly!$D$6:$BK$6,"<="&Inputs!$C$120,Engine_Monthly!$D$80:$BK$80)) -> 74.196793
A29: Sales & marketing | B29: ₹ lakh | C29: =1*(SUMIF(Engine_Monthly!$D$6:$BK$6,"<="&Inputs!$C$120,Engine_Monthly!$D$129:$BK$129)) -> 281.59181
A30: Legal, compliance, admin & other G&A | B30: ₹ lakh | C30: =1*(SUMIF(Engine_Monthly!$D$6:$BK$6,"<="&Inputs!$C$120,Engine_Monthly!$D$136:$BK$136)) -> 107.974
A31: Capex (laptops, test rig) | B31: ₹ lakh | C31: =1*(SUMIF(Engine_Monthly!$D$6:$BK$6,"<="&Inputs!$C$120,Engine_Monthly!$D$141:$BK$141)) -> 40
A32: Memo: operating cash flow in seed period | B32: ₹ lakh | C32: =1*(SUMIF(Engine_Monthly!$D$6:$BK$6,"<="&Inputs!$C$120,Engine_Monthly!$D$159:$BK$159)) -> -538.74465 | H32: Shown as the net of operating items above; see total line.
A33: Working capital tied up at Series A month (receivables − payables − deferred) | B33: ₹ lakh | C33: =INDEX(Engine_Monthly!$D$157:$BK$157,1,Inputs!$C$120)-INDEX(Engine_Monthly!$D$158:$BK$158,1,Inputs!$C$120)-INDEX(Engine_Monthly!$D$155:$BK$155,1,Inputs!$C$120) -> 15.923015
A35: D. ANNUAL CASH VIEW
A36: ₹ lakh | C36: =INDEX(Engine_Monthly!$D$10:$BK$10,1,12) -> FY27 | D36: =INDEX(Engine_Monthly!$D$10:$BK$10,1,24) -> FY28 | E36: =INDEX(Engine_Monthly!$D$10:$BK$10,1,36) -> FY29 | F36: =INDEX(Engine_Monthly!$D$10:$BK$10,1,48) -> FY30 | G36: =INDEX(Engine_Monthly!$D$10:$BK$10,1,60) -> FY31
A37: Average monthly burn | C37: =AVERAGEIF(Engine_Monthly!$D$7:$BK$7,1,Engine_Monthly!$D$167:$BK$167) -> 18.650509 | D37: =AVERAGEIF(Engine_Monthly!$D$7:$BK$7,2,Engine_Monthly!$D$167:$BK$167) -> 32.908499 | E37: =AVERAGEIF(Engine_Monthly!$D$7:$BK$7,3,Engine_Monthly!$D$167:$BK$167) -> 6.1867861 | F37: =AVERAGEIF(Engine_Monthly!$D$7:$BK$7,4,Engine_Monthly!$D$167:$BK$167) -> 0 | G37: =AVERAGEIF(Engine_Monthly!$D$7:$BK$7,5,Engine_Monthly!$D$167:$BK$167) -> 0
A38: Equity raised | C38: =SUMIF(Engine_Monthly!$D$7:$BK$7,1,Engine_Monthly!$D$161:$BK$161) -> 900 | D38: =SUMIF(Engine_Monthly!$D$7:$BK$7,2,Engine_Monthly!$D$161:$BK$161) -> 900 | E38: =SUMIF(Engine_Monthly!$D$7:$BK$7,3,Engine_Monthly!$D$161:$BK$161) -> 0 | F38: =SUMIF(Engine_Monthly!$D$7:$BK$7,4,Engine_Monthly!$D$161:$BK$161) -> 0 | G38: =SUMIF(Engine_Monthly!$D$7:$BK$7,5,Engine_Monthly!$D$161:$BK$161) -> 0
A39: Closing cash | C39: =INDEX(Engine_Monthly!$D$165:$BK$165,1,1*12) -> 676.19389 | D39: =INDEX(Engine_Monthly!$D$165:$BK$165,1,2*12) -> 1181.2919 | E39: =INDEX(Engine_Monthly!$D$165:$BK$165,1,3*12) -> 1443.5127 | F39: =INDEX(Engine_Monthly!$D$165:$BK$165,1,4*12) -> 3674.9102 | G39: =INDEX(Engine_Monthly!$D$165:$BK$165,1,5*12) -> 10114.97
A41: E. FINANCING OPTIONS
A42: Option | C42: Fit | H42: Comment
A43: Bootstrapping (founder capital, grants, paid pilots) | C43: Low | H43: Paid pilots and services could fund a 3-4 person team, but not the 18-30 month lag to recurring revenue at this hiring plan.
A44: Equity: seed then Series A | C44: High | H44: Matches a long pre-revenue build. Raise seed against pilot evidence, Series A against renewals and ARR.
A45: Government startup programmes and grants | C45: Medium | H45: Non-dilutive top-up for R&D; eligibility and timing uncertain. Verify current schemes before relying on them.
A46: Venture debt | C46: Low until ARR is recurring | H46: Lenders want recurring revenue and an equity sponsor; consider alongside Series A, not before.
A47: Working-capital / receivables finance | C47: Medium later | H47: Useful once receivables are material (DSO 60-90 days).
A49: Valuation: see 14_Valuation. Section H turns enterprise value into equity value and shows an illustrative pre-/post-money for the seed; it is not a price, because there is no validated round valuation.

Sheet 12_Scenarios
A1: 12. SCENARIO & SENSITIVITY ANALYSIS
A2: Change Inputs!C3 to run any scenario live through every statement. Tables marked SNAPSHOT were produced by re-running the full model for each case.
A4: A. SCENARIO DEFINITIONS (linked to Inputs)
A5: Lever | B5: Unit | C5: Bear | D5: Base | E5: Bull
A6: =Inputs!A22 -> Qualified opportunities per ramped AE per month | B6: =Inputs!B22 -> # | C6: =Inputs!D22 -> 2 | D6: =Inputs!E22 -> 3 | E6: =Inputs!F22 -> 4
A7: =Inputs!A19 -> AE ramp to full productivity | B7: =Inputs!B19 -> months | C7: =Inputs!D19 -> 6 | D7: =Inputs!E19 -> 6 | E7: =Inputs!F19 -> 4
A8: =Inputs!A25 -> Opportunity to pilot (direct) | B8: =Inputs!B25 -> % | C8: =Inputs!D25 -> 0.25 | D8: =Inputs!E25 -> 0.3 | E8: =Inputs!F25 -> 0.35
A9: =Inputs!A27 -> Sales cycle: qualified opportunity to pilot start | B9: =Inputs!B27 -> months | C9: =Inputs!D27 -> 4 | D9: =Inputs!E27 -> 3 | E9: =Inputs!F27 -> 2
A10: =Inputs!A29 -> Pilot to paid annual contract | B10: =Inputs!B29 -> % | C10: =Inputs!D29 -> 0.4 | D10: =Inputs!E29 -> 0.55 | E10: =Inputs!F29 -> 0.65
A11: =Inputs!A33 -> Contract signature to go-live (implementation time) | B11: =Inputs!B33 -> months | C11: =Inputs!D33 -> 3 | D11: =Inputs!E33 -> 2 | E11: =Inputs!F33 -> 2
A12: =Inputs!A34 -> Concurrent implementations per implementation engineer | B12: =Inputs!B34 -> # | C12: =Inputs!D34 -> 2 | D12: =Inputs!E34 -> 3 | E12: =Inputs!F34 -> 3.5
A13: =Inputs!A39 -> Implementation direct-cost multiplier | B13: =Inputs!B39 -> x | C13: =Inputs!D39 -> 1.3 | D13: =Inputs!E39 -> 1 | E13: =Inputs!F39 -> 0.85
A14: =Inputs!A47 -> Scenario price multiplier on tier list prices | B14: =Inputs!B47 -> x | C14: =Inputs!D47 -> 1 | D14: =Inputs!E47 -> 1 | E14: =Inputs!F47 -> 1
A15: =Inputs!A48 -> Annual list-price escalation | B15: =Inputs!B48 -> % p.a. | C15: =Inputs!D48 -> 0.03 | D15: =Inputs!E48 -> 0.05 | E15: =Inputs!F48 -> 0.05
A16: =Inputs!A49 -> Expansion ARR from existing plants (upsell, lines, modules) | B16: =Inputs!B49 -> % of ARR p.a. | C16: =Inputs!D49 -> 0.05 | D16: =Inputs!E49 -> 0.1 | E16: =Inputs!F49 -> 0.15
A17: =Inputs!A50 -> Annual logo churn | B17: =Inputs!B50 -> % p.a. | C17: =Inputs!D50 -> 0.15 | D17: =Inputs!E50 -> 0.09 | E17: =Inputs!F50 -> 0.06
A18: =Inputs!A51 -> Paid pilot fee (whole pilot) | B18: =Inputs!B51 -> ₹ lakh | C18: =Inputs!D51 -> 1.5 | D18: =Inputs!E51 -> 2.5 | E18: =Inputs!F51 -> 3
A19: =Inputs!A60 -> Cloud & AI cost multiplier | B19: =Inputs!B60 -> x | C19: =Inputs!D60 -> 1.25 | D19: =Inputs!E60 -> 1 | E19: =Inputs!F60 -> 0.9
A20: =Inputs!A61 -> Change in cloud/AI cost per plant each year | B20: =Inputs!B61 -> % p.a. | C20: =Inputs!D61 -> 0 | D20: =Inputs!E61 -> -0.05 | E20: =Inputs!F61 -> -0.1
A21: =Inputs!A64 -> Live plants per customer success manager | B21: =Inputs!B64 -> # | C21: =Inputs!D64 -> 20 | D21: =Inputs!E64 -> 25 | E21: =Inputs!F64 -> 30
A22: =Inputs!A41 -> Share of new plants needing the optional IoT kit | B22: =Inputs!B41 -> % | C22: =Inputs!D41 -> 0.6 | D22: =Inputs!E41 -> 0.5 | E22: =Inputs!F41 -> 0.4
A23: =Inputs!A30 -> Partner channel productivity multiplier | B23: =Inputs!B30 -> x plan | C23: =Inputs!D30 -> 0.5 | D23: =Inputs!E30 -> 1 | E23: =Inputs!F30 -> 1.5
A24: =Inputs!A102 -> Receivable days (DSO) | B24: =Inputs!B102 -> days | C24: =Inputs!D102 -> 75 | D24: =Inputs!E102 -> 45 | E24: =Inputs!F102 -> 30
A26: B. SCENARIO OUTPUTS
A27: Output | B27: Unit | C27: Bear (SNAPSHOT) | D27: Base (SNAPSHOT) | E27: Bull (SNAPSHOT) | F27: LIVE: active scenario
A28: FY31 revenue | B28: ₹ lakh | C28: 4938.4899 | D28: 15092.972 | E28: 31192.844 | F28: =7_Financials!$G$11 -> 15092.972
A29: FY31 closing ARR | B29: ₹ lakh | C29: 4678.5326 | D29: 15745.778 | E29: 33677.888 | F29: =4_Revenue_Build!G30 -> 15745.778
A30: FY31 live paying plants | B30: # | C30: 200 | D30: 400.00001 | E30: 600.00001 | F30: =4_Revenue_Build!G21 -> 400.00001
A31: FY31 EBITDA | B31: ₹ lakh | C31: -160.22956 | D31: 8786.0955 | E31: 23770.269 | F31: =7_Financials!$G$19 -> 8786.0955
A32: FY31 EBITDA margin | B32: % | C32: -0.032445051 | D32: 0.58213157 | E32: 0.76204237 | F32: =7_Financials!$G$20 -> 0.58213157
A33: Cumulative EBITDA FY27-FY31 | B33: ₹ lakh | C33: -2660.6051 | D33: 11649.398 | E33: 36128.171 | F33: =SUM(Engine_Monthly!$D$138:$BK$138) -> 11649.398
A34: FY31 gross margin | B34: % | C34: 0.47505498 | D34: 0.79356308 | E34: 0.88601109 | F34: =7_Financials!$G$15 -> 0.79356308
A35: Peak cumulative cash deficit | B35: ₹ lakh | C35: 3391.8626 | D35: 692.94953 | E35: 285.76047 | F35: =11_Funding!C5 -> 692.94953
A36: Total equity requirement (incl. buffer & contingency) | B36: ₹ lakh | C36: 4666.7394 | D36: 1102.9115 | E36: 508.94275 | F36: =11_Funding!C11 -> 1102.9115
A37: EBITDA break-even month (trailing 3 months > 0) | B37: month # | C37: 57 | D37: 29 | E37: 20 | F37: =IF(COUNT(Engine_Monthly!$D$176:$BK$176)=0,"None",MIN(Engine_Monthly!$D$176:$BK$176)) -> 29
A38: Lowest month-end cash (with modelled funding) | B38: ₹ lakh | C38: -1591.8626 | D38: 321.25535 | E38: 614.23953 | F38: =11_Funding!C21 -> 321.25535
A39: Runway on seed alone | B39: months | C39: 24 | D39: 60 | E39: 60 | F39: =11_Funding!C17 -> 60
A40: FY31 LTV / CAC (estimate) | B40: x | C40: 3.0196987 | D40: 9.924154 | E40: 17.583292 | F40: =8_Unit_Economics!G28 -> 9.924154
A41: FY31 CAC payback (estimate) | B41: months | C41: 8.8029791 | D41: 3.5580541 | E41: 2.1790484 | F41: =8_Unit_Economics!G29 -> 3.5580541
A42: Enterprise value @ 12% (two-stage DCF, steady-state terminal value) | B42: ₹ crore | C42: 41.597272 | D42: 367.69834 | E42: 2140.1683 | F42: =14_Valuation!C75 -> 367.69834
A43: EV, 5-year horizon (FY31 EBIT as steady state, plus tax losses) | B43: ₹ crore | C43: -23.400626 | D43: 465.38421 | E43: 1299.8031 | F43: =14_Valuation!C84 -> 465.38421
A44: EV without terminal value (FY27-FY36) | B44: ₹ crore | C44: -16.460797 | D44: 198.49494 | E44: 1080.363 | F44: =14_Valuation!C85 -> 198.49494
A45: FY31 free cash flow to the firm | B45: ₹ lakh | C45: -449.55057 | D45: 6440.06 | E45: 18322.432 | F45: =14_Valuation!G33 -> 6440.06
A46: Snapshot: each column is the full model re-run with Inputs!C3 set to that scenario (v4, 11-Oct-2026), each landing on its Year-5 plant target via the solved partner scale, with identical funding inputs. Bear cash goes negative with base funding: its own equity need is row 36.
A48: C. SENSITIVITY: one lever at a time around the BASE case (SNAPSHOT)
A49: Lever | B49: Low setting | C49: High setting | D49: FY31 ARR low | E49: FY31 ARR high | F49: FY31 EBITDA low | G49: FY31 EBITDA high | H49: Equity need low | I49: Equity need high | J49: Break-even month low / high | K49: EV low (₹ crore) | L49: EV high (₹ crore)
A50: Subscription price ±15% | B50: 0.85 | C50: 1.15 | D50: 13383.911 | E50: 18107.645 | F50: 7010.0673 | G50: 10562.124 | H50: 1197.1861 | I50: 1040.144 | J50: 31 / 28 | K50: 638.58689 | L50: 906.14823
A51: Opportunity volume (new customers) ±25% | B51: 0.75 | C51: 1.25 | D51: 11809.334 | E51: 19682.223 | F51: 6093.0101 | G51: 11469.283 | H51: 1221.0088 | I51: 1043.2623 | J51: 33 / 28 | K51: 551.63989 | L51: 992.62691
A52: Pilot-to-paid conversion ±20% | B52: 0.8 | C52: 1.2 | D52: 12596.622 | E52: 18894.934 | F52: 6649.1167 | G52: 10921.532 | H52: 1181.0036 | I52: 1052.6979 | J52: 32 / 28 | K52: 601.55174 | L52: 943.10237
A53: Sales cycle +2 / −1 months | B53: 2 | C53: -1 | D53: 14166.41 | E53: 16566.38 | F53: 7578.2866 | G53: 9417.423 | H53: 1278.0991 | I53: 1021.0508 | J53: 31 / 28 | K53: 675.52104 | L53: 823.11893
A54: Churn ×1.5 / ×0.5 | B54: 1.5 | C54: 0.5 | D54: 14885.152 | E54: 16641.44 | F54: 8249.9627 | G54: 9338.6973 | H54: 1112.5598 | I54: 1094.7293 | J54: 29 / 29 | K54: 732.77956 | L54: 813.12178
A55: Marketing & sales-travel spend ×1.5 / ×0.5 (CAC) | B55: 1.5 | C55: 0.5 | D55: 15745.778 | E55: 15745.778 | F55: 8592.5659 | G55: 8979.6251 | H55: 1210.5554 | I55: 1003.3521 | J55: 30 / 29 | K55: 762.00082 | L55: 782.73722
A56: Cloud/AI cost ×1.5 / ×0.7 (gross margin) | B56: 1.5 | C56: 0.7 | D56: 15745.778 | E56: 15745.778 | F56: 8438.4293 | G56: 8994.6953 | H56: 1152.7598 | I56: 1073.7937 | J56: 30 / 29 | K56: 755.04285 | L56: 782.76472
A57: Implementation effort & cost ×1.3 / ×0.8 | B57: 1.3 | C57: 0.8 | D57: 15745.778 | E57: 15745.778 | F57: 8245.8115 | G57: 9143.4255 | H57: 1223.4432 | I57: 1022.4836 | J57: 30 / 29 | K57: 744.53137 | L57: 790.82507
A59: D. RANKING: the variables that most determine value (largest EV swing first)
A60: Lever | B60: EV swing (₹ crore) | C60: EBITDA swing (₹ lakh) | D60: Equity-need swing (₹ lakh)
A61: 1. Opportunity volume (new customers) ±25% | B61: 216.6768 | C61: 5376.2731 | D61: 177.74652
A62: 2. Pilot-to-paid conversion ±20% | B62: 168.65679 | C62: 4272.415 | D62: 128.30576
A63: 3. Subscription price ±15% | B63: 134.09162 | C63: 3552.0564 | D63: 157.04216
A64: 4. Sales cycle +2 / −1 months | B64: 74.874271 | C64: 1839.1364 | D64: 257.04828
A65: 5. Churn ×1.5 / ×0.5 | B65: 39.778468 | C65: 1088.7346 | D65: 17.830499
A66: 6. Implementation effort & cost ×1.3 / ×0.8 | B66: 26.666216 | C66: 897.614 | D66: 200.95954
A67: 7. Cloud/AI cost ×1.5 / ×0.7 (gross margin) | B67: 15.756266 | C67: 556.26599 | D67: 78.96606
A68: 8. Marketing & sales-travel spend ×1.5 / ×0.5 (CAC) | B68: 12.320269 | C68: 387.05922 | D68: 207.20328
A70: Lowest single-lever enterprise value: ₹259 crore. Every one-lever move keeps EV far above the ₹10 crore target; the risk sits in the Year-5 targets themselves (16_SOM_Scenarios flags), not in single levers. Re-run 11-Oct-2026 with base FY32 growth 11%.

Sheet 13_Risks_Checks
A1: 13. RISK ANALYSIS & MODEL INTEGRITY CHECKS
A3: A. MODEL INTEGRITY CHECKS (all should read TRUE)
A4: Check | B4: Result | C4: Test
A5: Balance sheet balances every month | B5: =SUMPRODUCT(ABS(Engine_Monthly!$D$173:$BK$173))<0.01 -> TRUE | C5: Max |assets − (liabilities + equity)| over 60 months
A6: Balance sheet balances every year end | B6: =SUMPRODUCT(ABS(7_Financials!C61:G61))<0.01 -> TRUE | C6: Annual balance check row
A7: Closing cash reconciles (annual CF vs engine) | B7: =SUMPRODUCT(ABS(7_Financials!C44:G44))<0.01 -> TRUE | C7: Opening + net cash flow = engine cash
A8: Revenue reconciles to build-up and P&L | B8: =SUMPRODUCT(ABS(4_Revenue_Build!C44:G44))<0.01 -> TRUE | C8: Sum of streams = P&L revenue
A9: Customer roll-forward holds (opening − churn + go-lives = closing) | B9: =SUMPRODUCT(ABS(Engine_Monthly!$D$180:$BK$180))<0.0001 -> TRUE | C9: Every month
A10: ARR excludes one-time revenue (ARR bridge reconciles) | B10: =SUMPRODUCT(ABS(4_Revenue_Build!C31:G31))<0.01 -> TRUE | C10: ARR = opening + new subscriptions + expansion − churn; implementation, pilot and hardware revenue never enter ARR
A11: Go-lives never exceed implementation capacity | B11: =MAX(Engine_Monthly!$D$178:$BK$178)<=0.0001 -> TRUE | C11: Go-live ≤ capacity every month
A12: Gross margin reconciles to cost of revenue | B12: =SUMPRODUCT(ABS(5_Cost_of_Service!C38:G38))<0.01 -> TRUE | C12: Cost build = P&L cost of revenue
A13: Funding covers the cash deficit (cash never negative) | B13: =11_Funding!C21>=0 -> TRUE | C13: Lowest month-end cash ≥ 0
A14: Customer ROI excludes double counting | B14: =AND(9_Customer_ROI!C55="OK",9_Customer_ROI!D55="OK",9_Customer_ROI!E55="OK") -> TRUE | C14: Gross benefit = contribution + cash costs + WC; lost revenue excluded
A15: Pricing tier mix sums to 100% | B15: =3_Pricing!C18="OK" -> TRUE
A16: Scenario flows through statements and valuation (live = snapshot for active case) | B16: =AND(ABS(12_Scenarios!F28-INDEX(12_Scenarios!C28:E28,1,Inputs!$C$3))<1,ABS(12_Scenarios!F42-INDEX(12_Scenarios!C42:E42,1,Inputs!$C$3))<0.05) -> TRUE | C16: FALSE only means inputs changed after the snapshot was taken; re-run snapshots
A17: Valuation ties to the balance sheet; WACC > g; terminal-value conditions; scenario probabilities sum to 100%; NPV bridge ends at the live base case | B17: =AND(14_Valuation!C90,IF(Inputs!$C$3=2,15_Change_Log!B20,TRUE())) -> TRUE | C17: 14_Valuation row 34 (FCFF ties), section C check, section F probability and block checks. If inputs change, re-run the snapshots (Cover).
A18: Year-5 live plants hit the active scenario's target (within 0.5 plant) | B18: =ABS(INDEX(Engine_Monthly!$D$49:$BK$49,1,60)-Inputs!C151)<0.5 -> TRUE | C18: Engine FY31 closing live plants vs Inputs K. Re-solve the partner scale if funnel inputs change.
A19: Tier prices sit inside the stated ranges; scenario mixes sum to 100% | B19: =3_Pricing!C57="OK" -> TRUE | C19: 3_Pricing scenario table.
A20: Gain-share kept out of ARR and zero in bear | B20: =AND(Inputs!D153=0,SUMPRODUCT(ABS(4_Revenue_Build!C31:G31))<0.01) -> TRUE | C20: ARR bridge excludes gain-share by construction.
A21: Scenario snapshots on 16_SOM_Scenarios match the live model | B21: =AND(16_SOM_Scenarios!F104,16_SOM_Scenarios!F105) -> TRUE | C21: Filled below once the sheet exists.
A22: ALL CHECKS PASS | B22: =AND(B5:B21) -> TRUE
A23: B. RISK REGISTER (financial impact expressed against the base case)
A24: Risk | B24: Probability | C24: Financial impact | D24: Early-warning indicator | E24: Mitigation | F24: Owner | G24: Contingency in model
A25: Customers unwilling to pay for a new decision-support layer | B25: High | C25: Fewer contracts; see pilot-to-paid sensitivity | D25: Pilot-to-paid < 40%; 'free trial' requests | E25: Paid pilots with pre-agreed success metrics; Essential tier as entry | F25: CEO | G25: Bear pilot-to-paid 40%
A26: ERP/MES/APS vendors bundle similar features | B26: Medium | C26: Price pressure, higher churn | D26: Lost deals citing incumbent roadmap | E26: Stay a thin layer on top; integrate rather than compete | F26: CTO | G26: Bear: low-end tier prices (₹12 / 24 / 40 lakh)
A27: Long enterprise sales cycles | B27: High | C27: Revenue delayed 3-6 months; bigger funding need | D27: Opportunity age > 6 months | E27: Cluster focus; referrals; partner channel | F27: Commercial founder | G27: Bear cycle +1 month
A28: Poor industrial data quality | B28: High | C28: Longer implementations; services margin falls | D28: Data audit fails at > 30% of pilots | E28: Readiness checklist before pilot; IoT kit option | F28: CTO | G28: Bear implementation cost ×1.3
A29: Integration complexity across PLC/CNC brands | B29: High | C29: Engineer load per plant rises | D29: Implementations > 3 months | E29: Standard connector library; test rig | F29: Head of implementation | G29: Bear go-live lag 3 months
A30: Recommendations ignore real shop-floor constraints | B30: Medium | C30: Low adoption → churn | D30: Planner override rate > 50% | E30: Human approval loop; constraint capture during onboarding | F30: Product | G30: Bear churn 18%
A31: Claimed customer savings cannot be verified | B31: High | C31: Weak renewals; no performance fee | D31: Customer cannot reproduce ROI numbers | E31: Baseline measurement in pilot; conservative ROI method (sheet 9) | F31: CS lead | G31: Performance fee = 0
A32: Cybersecurity / OT network risk | B32: Medium | C32: Deal blockers; liability | D32: Security questionnaires failing | E32: Read-only connectors, ISO 27001 path, cyber insurance | F32: Security lead | G32: Fixed platform cost ₹1.5 lakh/month
A33: Excessive customisation | B33: High | C33: Becomes a services business | D33: Custom work > 20% of engineering time | E33: Productised tiers; charge for custom work | F33: CEO | G33: Implementation fee covers direct cost
A34: Hardware & deployment cost overruns | B34: Medium | C34: Gross margin hit | D34: Kit attach > 60% | E34: Pass-through pricing on kits | F34: Ops | G34: Bear attach 60%
A35: Customer concentration | B35: Medium early | C35: Revenue volatility | D35: Top 3 plants > 40% of ARR | E35: Multi-cluster pipeline | F35: CEO | G35: Not modelled
... A39: Valuation depends on long-run assumptions | B39: Medium | C39: Terminal value is most of the NPV | D39: Actuals fall behind the FY32-FY36 fade | E39: Terminal value charged for reinvestment (g ÷ RONIC); report the probability-weighted value, the comps range and the WACC × growth grid alongside the headline | F39: CFO | G39: Terminal value set to 0 if FY36 FCFF ≤ 0

Sheet 14_Valuation
A1: 14. VALUATION: DCF, SCENARIO-WEIGHTED VALUE, COMPARABLES AND EQUITY BRIDGE (₹ lakh unless stated)
A2: Structure: A inputs · B FCFF build · C steady-state terminal value · D base DCF summary · E WACC × growth sensitivity · F probability-weighted scenarios · G comparable-company cross-check · H equity bridge · I reconciliation · J notes. Values are at the model start date (1-Apr-2026), end-of-year discounting, before any financing.
A4: A. VALUATION INPUTS
A5: Parameter | B5: Unit | C5: Value | D5: Type | E5: Source / rationale
A6: Discount rate (WACC) | B6: % | C6: 0.12 | D6: Given | E6: Set by the team for the case. An early-stage venture investor would use 25-40%; see the grid in section E.
A7: Terminal growth after FY36 | B7: % | C7: 0.05 | D7: Assumption | E7: Long-run nominal growth = RBI's 4% CPI target (Apr-2026 to Mar-2031) plus ~1% real growth; below the 10-year G-sec yield (~7.2%, Oct-2026) and India's nominal GDP trend. See section C.
A8: Revenue growth in FY32 (first fade year) | B8: % | C8: =INDEX($C$120:$E$120,1,Inputs!$C$3) -> 0.11 | D8: Scenario link | E8: Active scenario's value from section F (base 11%: team decision on 11-Oct-2026, replacing 57% = half of FY31 engine growth).
A9: Revenue growth in FY36 (last fade year) | B9: % | C9: =INDEX($C$121:$E$121,1,Inputs!$C$3) -> 0.12 | D9: Scenario link | E9: Section F. Straight-line fade from FY32; a mature vertical SaaS still growing above GDP.
A10: Steady-state EBITDA margin | B10: % | C10: =INDEX($C$122:$E$122,1,Inputs!$C$3) -> 0.25 | D10: Scenario link | E10: Section F. Base 25%, below the 30%+ that mature software firms report.
A11: Maximum EBITDA-margin change per year | B11: pts | C11: =INDEX($C$123:$E$123,1,Inputs!$C$3) -> 0.03 | D11: Scenario link | E11: Section F. Margin moves towards the steady state by at most this much a year, up or down.
A12: Capex (= D&A) in FY32-FY36 | B12: % of revenue | C12: 0.01 | D12: Assumption | E12: Asset-light: laptops and test rigs. FY31 engine capex is under 1% of revenue.
A13: Tax rate | B13: % | C13: =Inputs!C10 -> 0.25168 | D13: Link | E13: Concessional regime incl. surcharge and cess (Inputs).
A14: Net working capital, FY31 | B14: % of revenue | C14: =IFERROR((7_Financials!G48-7_Financials!G53-7_Financials!G54)/7_Financials!G11,0) -> 0.017580492 | D14: Calculated | E14: Receivables less payables and deferred revenue at FY31, held as a share of revenue in the fade.
A15: Target NPV | B15: ₹ crore | C15: 10 | D15: Given | E15: Team's hurdle for the pitch.
A17: B. FREE CASH FLOW TO THE FIRM
A18: ₹ lakh | B18: Unit | C18: ="FY"&TEXT(MOD(YEAR(Inputs!$C$8)+C19,100),"00") -> FY27 | D18: ="FY"&TEXT(MOD(YEAR(Inputs!$C$8)+D19,100),"00") -> FY28 | E18: ="FY"&TEXT(MOD(YEAR(Inputs!$C$8)+E19,100),"00") -> FY29 | F18: ="FY"&TEXT(MOD(YEAR(Inputs!$C$8)+F19,100),"00") -> FY30 | G18: ="FY"&TEXT(MOD(YEAR(Inputs!$C$8)+G19,100),"00") -> FY31 | H18: ="FY"&TEXT(MOD(YEAR(Inputs!$C$8)+H19,100),"00") -> FY32 | I18: ="FY"&TEXT(MOD(YEAR(Inputs!$C$8)+I19,100),"00") -> FY33 | J18: ="FY"&TEXT(MOD(YEAR(Inputs!$C$8)+J19,100),"00") -> FY34 | ... L18: ="FY"&TEXT(MOD(YEAR(Inputs!$C$8)+L19,100),"00") -> FY36 | M18: Notes
A19: Year number (t) | B19: # | C19: 1 | D19: 2 | E19: 3 | F19: 4 | G19: 5 | H19: 6 | I19: 7 | J19: 8 | K19: 9 | L19: 10
A20: Phase | C20: Engine | D20: Engine | E20: Engine | F20: Engine | G20: Engine | H20: Fade | I20: Fade | J20: Fade | K20: Fade | L20: Fade
A21: Revenue | B21: ₹ lakh | C21: =7_Financials!C11 -> 28.637625 | D21: =7_Financials!D11 -> 478.84504 | E21: =7_Financials!E11 -> 2411.1478 | F21: =7_Financials!F11 -> 7026.3162 | G21: =7_Financials!G11 -> 15092.972 | H21: =G21*(1+H22) -> 16753.199 | I21: =H21*(1+I22) -> 18637.934 | J21: =I21*(1+J22) -> 20781.296 | K21: =J21*(1+K22) -> 23223.098 | L21: =K21*(1+L22) -> 26009.87 | M21: FY27-FY31 link to 7_Financials; fade years grow at row 22.
A22: Revenue growth | B22: % | D22: =IFERROR(D21/C21-1,0) -> 15.720836 | E22: =IFERROR(E21/D21-1,0) -> 4.0353405 | F22: =IFERROR(F21/E21-1,0) -> 1.914096 | G22: =IFERROR(G21/F21-1,0) -> 1.1480633 | H22: =$C$8+($C$9-$C$8)*(H$19-6)/4 -> 0.11 | I22: =$C$8+($C$9-$C$8)*(I$19-6)/4 -> 0.1125 | J22: =$C$8+($C$9-$C$8)*(J$19-6)/4 -> 0.115 | K22: =$C$8+($C$9-$C$8)*(K$19-6)/4 -> 0.1175 | L22: =$C$8+($C$9-$C$8)*(L$19-6)/4 -> 0.12 | M22: Fade: straight line from the FY32 rate to the FY36 rate.
A23: EBITDA | B23: ₹ lakh | C23: =7_Financials!C19 -> -203.33499 | D23: =7_Financials!D19 -> -349.49934 | E23: =7_Financials!E19 -> 354.79406 | F23: =7_Financials!F19 -> 3061.3425 | G23: =7_Financials!G19 -> 8786.0955 | H23: =H21*H24 -> 9249.9701 | I23: =I21*I24 -> 9731.4537 | J23: =J21*J24 -> 10227.132 | K23: =K21*K24 -> 10732.127 | L23: =L21*L24 -> 11239.686
A24: EBITDA margin | B24: % | C24: =IFERROR(C23/C21,0) -> -7.1002744 | D24: =IFERROR(D23/D21,0) -> -0.72987986 | E24: =IFERROR(E23/E21,0) -> 0.14714737 | F24: =IFERROR(F23/F21,0) -> 0.43569666 | G24: =IFERROR(G23/G21,0) -> 0.58213157 | H24: =G24+MAX(-$C$11,MIN($C$11,$C$10-G24)) -> 0.55213157 | I24: =H24+MAX(-$C$11,MIN($C$11,$C$10-H24)) -> 0.52213157 | J24: =I24+MAX(-$C$11,MIN($C$11,$C$10-I24)) -> 0.49213157 | K24: =J24+MAX(-$C$11,MIN($C$11,$C$10-J24)) -> 0.46213157 | L24: =K24+MAX(-$C$11,MIN($C$11,$C$10-K24)) -> 0.43213157 | M24: Fade: margin moves towards the steady-state margin by at most the yearly step, up or down.
A25: Depreciation & amortisation | B25: ₹ lakh | C25: =7_Financials!C21 -> -6.1777778 | D25: =7_Financials!D21 -> -12.5 | E25: =7_Financials!E21 -> -21.366667 | F25: =7_Financials!F21 -> -28.022222 | G25: =7_Financials!G21 -> -36.966667 | H25: =H27 -> -167.53199 | I25: =I27 -> -186.37934 | J25: =J27 -> -207.81296 | K25: =K27 -> -232.23098 | L25: =L27 -> -260.0987 | M25: Fade: D&A set equal to capex (steady state).
A26: EBIT | B26: ₹ lakh | C26: =C23+C25 -> -209.51277 | D26: =D23+D25 -> -361.99934 | E26: =E23+E25 -> 333.42739 | F26: =F23+F25 -> 3033.3203 | G26: =G23+G25 -> 8749.1289 | H26: =H23+H25 -> 9082.4381 | I26: =I23+I25 -> 9545.0744 | J26: =J23+J25 -> 10019.319 | ... L26: =L23+L25 -> 10979.587
A27: Capital expenditure (incl. capitalised software) | B27: ₹ lakh | C27: =7_Financials!C34+7_Financials!C35 -> -23.2 | D27: =7_Financials!D34+7_Financials!D35 -> -16.8 | E27: =7_Financials!E34+7_Financials!E35 -> -33.6 | F27: =7_Financials!F34+7_Financials!F35 -> -42 | G27: =7_Financials!G34+7_Financials!G35 -> -48 | H27: =-H21*$C$12 -> -167.53199 | I27: =-I21*$C$12 -> -186.37934 | J27: =-J21*$C$12 -> -207.81296 | K27: =-K21*$C$12 -> -232.23098 | L27: =-L21*$C$12 -> -260.0987
A28: Tax losses available: opening | B28: ₹ lakh | H28: =MAX(0,-SUM(7_Financials!$C$24:$G$24)) -> 0 | I28: =H30 -> 0 | J28: =I30 -> 0 | K28: =J30 -> 0 | L28: =K30 -> 0 | M28: Unused losses at FY31 = −(sum of FY27-FY31 profit before tax) if negative.
A29: Tax losses used | B29: ₹ lakh | H29: =MIN(H28,MAX(0,H26)) -> 0 | I29: =MIN(I28,MAX(0,I26)) -> 0 | J29: =MIN(J28,MAX(0,J26)) -> 0 | K29: =MIN(K28,MAX(0,K26)) -> 0 | L29: =MIN(L28,MAX(0,L26)) -> 0
A30: Tax losses available: closing | B30: ₹ lakh | H30: =H28-H29 -> 0 | I30: =I28-I29 -> 0 | J30: =J28-J29 -> 0 | K30: =K28-K29 -> 0 | L30: =L28-L29 -> 0
A31: Cash taxes | B31: ₹ lakh | C31: =7_Financials!C32 -> 0 | D31: =7_Financials!D32 -> 0 | E31: =7_Financials!E32 -> 0 | F31: =7_Financials!F32 -> -703.50489 | G31: =7_Financials!G32 -> -2201.9808 | H31: =-(MAX(0,H26)-H29)*$C$13 -> -2285.868 | I31: =-(MAX(0,I26)-I29)*$C$13 -> -2402.3043 | J31: =-(MAX(0,J26)-J29)*$C$13 -> -2521.6622 | K31: =-(MAX(0,K26)-K29)*$C$13 -> -2642.6138 | L31: =-(MAX(0,L26)-L29)*$C$13 -> -2763.3426 | M31: Engine years: as computed monthly. Fade: tax on EBIT after using carried-forward losses.
A32: Working-capital movement | B32: ₹ lakh | C32: =7_Financials!C30 -> 2.7288814 | D32: =7_Financials!D30 -> -28.602638 | E32: =7_Financials!E30 -> -58.973221 | F32: =7_Financials!F30 -> -84.440133 | G32: =7_Financials!G30 -> -96.054754 | H32: =-$C$14*(H21-G21) -> -29.187605 | I32: =-$C$14*(I21-H21) -> -33.134566 | J32: =-$C$14*(J21-I21) -> -37.681364 | K32: =-$C$14*(K21-J21) -> -42.928085 | L32: =-$C$14*(L21-K21) -> -48.992818 | M32: Fade: −(NWC % of revenue × revenue increase).
A33: Free cash flow to the firm (FCFF) | B33: ₹ lakh | C33: =C23+C27+C31+C32 -> -223.80611 | D33: =D23+D27+D31+D32 -> -394.90198 | E33: =E23+E27+E31+E32 -> 262.22084 | F33: =F23+F27+F31+F32 -> 2231.3975 | G33: =G23+G27+G31+G32 -> 6440.06 | H33: =H23+H27+H31+H32 -> 6767.3825 | I33: =I23+I27+I31+I32 -> 7109.6355 | J33: =J23+J27+J31+J32 -> 7459.9754 | ... L33: =L23+L27+L31+L32 -> 8167.2521 | M33: EBITDA + capex + cash taxes + working-capital movement (costs negative).
A34: Check: FCFF = Δ balance-sheet cash − financing flows; WC = Δ balance-sheet WC (should be 0) | B34: ₹ lakh | C34: =ROUND(ABS(C33-((7_Financials!C47-0)-7_Financials!C40-7_Financials!C31))+ABS(C32-(-(7_Financials!C48-0)-(7_Financials!C49-0)+(7_Financials!C53-0)+(7_Financials!C54-0))),4) -> 0 | D34: =ROUND(ABS(D33-((7_Financials!D47-7_Financials!C47)-7_Financials!D40-7_Financials!D31))+ABS(D32-(-(7_Financials!D48-7_Financials!C48)-(7_Financials!D49-7_Financials!C49)+(7_Financials!D53-7_Financials!C53)+(7_Financials!D54-7_Financials!C54))),4) -> 0 | E34: =ROUND(ABS(E33-((7_Financials!E47-7_Financials!D47)-7_Financials!E40-7_Financials!E31))+ABS(E32-(-(7_Financials!E48-7_Financials!D48)-(7_Financials!E49-7_Financials!D49)+(7_Financials!E53-7_Financials!D53)+(7_Financials!E54-7_Financials!D54))),4) -> 0 | F34: =ROUND(ABS(F33-((7_Financials!F47-7_Financials!E47)-7_Financials!F40-7_Financials!F31))+ABS(F32-(-(7_Financials!F48-7_Financials!E48)-(7_Financials!F49-7_Financials!E49)+(7_Financials!F53-7_Financials!E53)+(7_Financials!F54-7_Financials!E54))),4) -> 0 | G34: =ROUND(ABS(G33-((7_Financials!G47-7_Financials!F47)-7_Financials!G40-7_Financials!G31))+ABS(G32-(-(7_Financials!G48-7_Financials!F48)-(7_Financials!G49-7_Financials!F49)+(7_Financials!G53-7_Financials!F53)+(7_Financials!G54-7_Financials!F54))),4) -> 0 | M34: Independent tie to the balance sheet: FCFF = change in cash − equity/debt flows − interest; WC = change in receivables, prepayments, payables, deferred revenue.
A35: Discount factor | B35: x | C35: =1/(1+$C$6)^C19 -> 0.89285714 | D35: =1/(1+$C$6)^D19 -> 0.79719388 | E35: =1/(1+$C$6)^E19 -> 0.71178025 | F35: =1/(1+$C$6)^F19 -> 0.63551808 | G35: =1/(1+$C$6)^G19 -> 0.56742686 | H35: =1/(1+$C$6)^H19 -> 0.50663112 | I35: =1/(1+$C$6)^I19 -> 0.45234922 | J35: =1/(1+$C$6)^J19 -> 0.40388323 | ... L35: =1/(1+$C$6)^L19 -> 0.32197324
A36: PV of FCFF | B36: ₹ lakh | C36: =C33*C35 -> -199.82689 | D36: =D33*D35 -> -314.81344 | E36: =E33*E35 -> 186.64361 | F36: =F33*F35 -> 1418.0934 | G36: =G33*G35 -> 3654.263 | H36: =H33*H35 -> 3428.5666 | I36: =I33*I35 -> 3216.038 | J36: =J33*J35 -> 3012.959 | ... L36: =L33*L35 -> 2629.6366
A37: Cumulative FCFF | B37: ₹ lakh | C37: =C33 -> -223.80611 | D37: =C37+D33 -> -618.7081 | E37: =D37+E33 -> -356.48726 | F37: =E37+F33 -> 1874.9102 | G37: =F37+G33 -> 8314.9703 | H37: =G37+H33 -> 15082.353 | I37: =H37+I33 -> 22191.988 | J37: =I37+J33 -> 29651.964 | K37: =J37+K33 -> 37466.318 | L37: =K37+L33 -> 45633.57
A38: Terminal value at FY36 (steady-state value-driver method, section C) | B38: ₹ lakh | L38: =C60 -> 52552.006 | M38: Zero when the business is not profitable at the end of the fade. See section C.
A39: PV of terminal value | B39: ₹ lakh | L39: =L38*L35 -> 16920.34
A40: FCFF incl. terminal value (for IRR) | B40: ₹ lakh | C40: =C33 -> -223.80611 | D40: =D33 -> -394.90198 | E40: =E33 -> 262.22084 | F40: =F33 -> 2231.3975 | G40: =G33 -> 6440.06 | H40: =H33 -> 6767.3825 | I40: =I33 -> 7109.6355 | J40: =J33 -> 7459.9754 | K40: =K33 -> 7814.3541 | L40: =L33+L38 -> 60719.259
A41: Payback helper (year number once cumulative FCFF > 0) | B41: # | C41: =IF(C37>0,C19,99) -> 99 | D41: =IF(D37>0,D19,99) -> 99 | E41: =IF(E37>0,E19,99) -> 99 | F41: =IF(F37>0,F19,99) -> 4 | G41: =IF(G37>0,G19,99) -> 5 | H41: =IF(H37>0,H19,99) -> 6 | I41: =IF(I37>0,I19,99) -> 7 | J41: =IF(J37>0,J19,99) -> 8 | ... L41: =IF(L37>0,L19,99) -> 10
A43: C. TERMINAL VALUE: STEADY-STATE CHECK (value-driver method: TV = NOPAT₍FY37₎ × (1 − g ÷ RONIC) ÷ (WACC − g))
A44: Item | B44: Unit | C44: Value | D44: Type | E44: Source / rationale
A45: India 10-year G-sec yield (ceiling for nominal g) | B45: % | C45: 0.072 | D45: Verified fact | E45: Trading Economics, 1-Oct-2026: benchmark 10-year yield ~7.21%.
A46: RBI CPI inflation target | B46: % | C46: 0.04 | D46: Verified fact | E46: Government notification, 25-Mar-2026: 4% ± 2% for 1-Apr-2026 to 31-Mar-2031.
A47: Terminal growth (g) | B47: % | C47: =C7 -> 0.05 | D47: Link | E47: From section A.
A48: Implied real perpetual growth | B48: % | C48: =(1+C47)/(1+C46)-1 -> 0.0096153846 | D48: Calculated | E48: About 1% real: a mature niche software vendor, not a market leader growing with the economy.
A49: Return on new invested capital in perpetuity (RONIC) | B49: % | C49: 0.2 | D49: Assumption | E49: Above the 12% WACC (switching costs, asset-light) but finite: competition erodes returns on new growth. RONIC = WACC means growth adds no value (section E).
A50: Reinvestment rate needed to sustain g (g ÷ RONIC) | B50: % of NOPAT | C50: =C47/C49 -> 0.25 | D50: Calculated | E50: Share of terminal profit that must be ploughed back (capacity, product, working capital) to grow at g.
A51: FY36 revenue growth less g | B51: pts | C51: =L22-C47 -> 0.07 | D51: Calculated | E51: Fade ends at 12% growth; the perpetuity assumes 5%. Value of the step-down is not credited.
A52: FY37 revenue | B52: ₹ lakh | C52: =L21*(1+C47) -> 27310.364 | D52: Calculated
A53: FY36 EBITDA margin (end of fade) | B53: % | C53: =L24 -> 0.43213157 | D53: Calculated
A54: Steady-state EBITDA margin used in the terminal year | B54: % | C54: =MIN(C10,C53) -> 0.25 | D54: Calculated | E54: Lower of the scenario's steady-state margin and the FY36 margin: a business still loss-making in FY36 earns no perpetuity value.
A55: Steady-state capex = D&A | B55: % of revenue | C55: =C12 -> 0.01 | D55: Link
A56: FY37 EBIT | B56: ₹ lakh | C56: =C52*(C54-C55) -> 6554.4873 | D56: Calculated
A57: FY37 NOPAT (taxed in full) | B57: ₹ lakh | C57: =MAX(0,C56)*(1-C13) -> 4904.8539 | D57: Calculated | E57: Carried-forward losses are used up by FY33 in the base case (row 30).
A58: Net reinvestment in FY37 | B58: ₹ lakh | C58: =-C57*C50 -> -1226.2135 | D58: Calculated
A59: FY37 FCFF (steady state) | B59: ₹ lakh | C59: =C57+C58 -> 3678.6405 | D59: Calculated
A60: Terminal value at end-FY36 | B60: ₹ lakh | C60: =IF(C59>0,C59/(C6-C47),0) -> 52552.006 | D60: Calculated | E60: Feeds row 38.
A61: PV of terminal value | B61: ₹ lakh | C61: =C60*L35 -> 16920.34 | D61: Calculated
A62: Memo: reinvestment actually in the FY36 cash flow | B62: % of NOPAT | C62: =IFERROR((-(L27-L25)-L32)/(MAX(0,L26)*(1-C13)),0) -> 0.0059629209 | D62: Calculated | E62: Capex equals D&A and working capital is small, so FY36 reinvests almost nothing. Capitalising that cash flow at 5% growth overstated value.
A63: Memo: terminal value, previous method (FY36 FCFF × (1+g) ÷ (WACC − g)) | B63: ₹ lakh | C63: =IF(L33>0,L33*(1+C47)/(C6-C47),0) -> 122508.78 | D63: Calculated | E63: v2 method, kept for the reconciliation in section I.
A64: Memo: PV of previous-method terminal value | B64: ₹ lakh | C64: =C63*L35 -> 39444.549 | D64: Calculated
A65: Implied terminal value ÷ FY37 EBITDA | B65: x | C65: =IFERROR(C60/(C52*C54),0) -> 7.6970057 | D65: Calculated | E65: Cross-check: PTC, a mature listed industrial software company, trades at 16.6x LTM EBITDA (section G).
A66: Implied terminal value ÷ FY36 revenue | B66: x | C66: =IFERROR(C60/L21,0) -> 2.020464 | D66: Calculated
A67: Check: g < WACC, g ≤ 10-year G-sec yield, RONIC ≥ WACC | C67: =AND(C47<C6,C47<=C45,C49>=C6) -> TRUE | D67: Check
A69: D. BASE DCF SUMMARY (active scenario on Inputs!C3)
A70: Measure | B70: Unit | C70: Value | D70: Share of EV | E70: Comment
A71: PV of FCFF, FY27-FY31 (monthly engine) | B71: ₹ lakh | C71: =SUM(C36:G36) -> 4744.3597 | D71: =IFERROR(C71/$C$74,0) -> 0.12902859 | E71: The J-curve: investment years before break-even.
A72: PV of FCFF, FY32-FY36 (fade) | B72: ₹ lakh | C72: =SUM(H36:L36) -> 15105.135 | D72: =IFERROR(C72/$C$74,0) -> 0.41080236
A73: PV of terminal value | B73: ₹ lakh | C73: =C61 -> 16920.34 | D73: =IFERROR(C73/$C$74,0) -> 0.46016905 | E73: Steady-state method (section C).
A74: Enterprise value (NPV of FCFF) at the model start date | B74: ₹ lakh | C74: =SUM(C71:C73) -> 36769.834 | D74: =IFERROR(C74/$C$74,0) -> 1
A75: Enterprise value, base DCF @ WACC | B75: ₹ crore | C75: =C74/100 -> 367.69834 | E75: Headline. Probability-weighted value: section F.
A76: Meets the ₹10 crore NPV target? | C76: =IF(C75>=C15,"YES","NO") -> YES
A77: IRR on FCFF including terminal value | B77: % | C77: =IFERROR(IRR(C40:L40),"n.m.") -> 1.6660658
A78: Payback year (cumulative FCFF turns positive) | C78: =IF(MIN(C41:L41)=99,"Beyond FY36",INDEX(C18:L18,1,MIN(C41:L41))) -> FY30
A79: DCF value at end-FY31 (FY32+ cash flows and terminal value) | B79: ₹ lakh | C79: =(C72+C73)*(1+C6)^5 -> 56439.828 | E79: Same date as FY31 ARR; used in sections G and H.
